Workbook
Name AN_Vorhaben1: 'FuE Vorhaben'!$B$17:$H$26
Name AN_Vorhaben2: 'FuE Vorhaben'!#REF!
Name AN_Vorhaben3: 'FuE Vorhaben'!#REF!
Name AN_Vorhaben4: 'FuE Vorhaben'!#REF!
Name AN_Vorhaben5: 'FuE Vorhaben'!#REF!
Name AN_Vorhaben6: 'FuE Vorhaben'!#REF!
Name AN_Vorhaben7: 'FuE Vorhaben'!#REF!
Name ausschließlich_eigenbetriebliche_Nutzung?: Tabelle1!$B$2:$B$3
Name BeantrFZ2020: 'Ganzes Unternehmen'!$H$57
Name BeantrFZ2021: 'Ganzes Unternehmen'!$I$57
Name BeantrFZ2022: 'Ganzes Unternehmen'!$J$57
Name BeantrFZ2023: 'Ganzes Unternehmen'!$K$57
Name BeantrFZ2024: 'Ganzes Unternehmen'!$L$57
Name BeantrFZ2025: 'Ganzes Unternehmen'!$M$57
Name Bundesland: 'Ganzes Unternehmen'!$C$11
Name CountLines: _xlfn.LAMBDA(_xlpm.Zelle,LEN(_xlpm.Zelle)-LEN(SUBSTITUTE(_xlpm.Zelle,CHAR(10),""))+1)
Name Display_Week: Arbeitsplan!$C$4
Name GetAGBeitrag: _xlfn.LAMBDA(_xlpm.links,_xlpm.rechts,IF(CountLines(_xlpm.links)+CountLines(_xlpm.rechts)=6,GetSteuerbruttoZ3(_xlpm.links)&","&GetSteuerbruttoZ3(_xlpm.rechts),""))
Name GetColOfAry: _xlfn.LAMBDA(_xlpm.targetcol,_xlpm.ary, _xlfn.TAKE(_xlfn.TAKE(_xlpm.ary,,_xlpm.targetcol),,-1) )
Name GetNumbers: _xlfn.LAMBDA(_xlpm.Zelle,SUM(MID(0&_xlpm.Zelle,LARGE(INDEX(ISNUMBER(--MID(_xlpm.Zelle,ROW(#REF!),1))*ROW(#REF!),),ROW(#REF!))+1,1)*10^ROW(#REF!)/10))
Name GewählterMA: Stundenzettel!$C$8
Name GewähltesVorhaben: Stundenzettel!$C$9
Name Jahr1: Stundenzettel!$C$15
Name Jahr2: Stundenzettel!$C$43
Name Jahr3: Stundenzettel!$C$71
Name Jahr4: Stundenzettel!$C$99
Name Jahr5: Stundenzettel!$C$127
Name Jahr6: Stundenzettel!$C$155
Name Kosten2020: Dashboard!$E$17
Name Kosten2021: Dashboard!$F$17
Name Kosten2022: Dashboard!$G$17
Name Kosten2023: Dashboard!$H$17
Name Kosten2024: Dashboard!$I$17
Name Kosten2025: Dashboard!$J$17
Name Mitarbeiter: _xlfn.ANCHORARRAY(Personaleingabe!$AZ$11)
Name Proj1: 'Ganzes Unternehmen'!$B$16
Name Proj2: 'Ganzes Unternehmen'!$B$17
Name Proj3: 'Ganzes Unternehmen'!$B$18
Name Proj4: 'Ganzes Unternehmen'!$B$19
Name Proj5: 'Ganzes Unternehmen'!$B$20
Name Proj6: 'Ganzes Unternehmen'!$B$21
Name Proj7: 'Ganzes Unternehmen'!$B$22
Name Project_Start: Arbeitsplan!$C$3
Name Steuerland: Steuernummern!$A$3
Name Steuernummer_kurz: 'Ganzes Unternehmen'!$C$10
Name Steuernummer_lang: 'Ganzes Unternehmen'!$C$9
Name task_end: [1]ProjectSchedule!$D1
Name task_start: [1]ProjectSchedule!$C1
Name WJ: #REF!
Name WJ_2020: 'Ganzes Unternehmen'!$C$23
Name WJ_2021: 'Ganzes Unternehmen'!$D$23
Name WJ_2022: 'Ganzes Unternehmen'!$E$23
Name WJ_2023: 'Ganzes Unternehmen'!$F$23
Name WJ_2024: 'Ganzes Unternehmen'!$G$23
Name WJ_2025: 'Ganzes Unternehmen'!$H$23
Name Year_Valid_V1: 'FuE Vorhaben'!$C$9:$H$9
Name Year_Valid_V2: 'FuE Vorhaben'!#REF!
Name Year_Valid_V3: 'FuE Vorhaben'!#REF!
Name Year_Valid_V4: 'FuE Vorhaben'!#REF!
Name Year_Valid_V5: 'FuE Vorhaben'!#REF!

Sheet Ganzes Unternehmen
B5: Dieses Tabellenblatt fragt allgemeine Daten über die Unternehmensgruppe, das Unternehmen und die geplanten Vorhaben ab.
B7: Allgemeine Daten
B8: Name der Firma | C8: Ping Zhou Consulting
B9: Steuernummer (lang; 13-stellig)
B10: Steuernummer (kurz)
B11: Bundesland Finanzamt | C11: Baden-Württemberg
B12: Seid ihr ein KMU? | C12: ja
B14: Liste der Vorhaben
B15: Arbeitstitel | C15: Start | D15: Ende
A16: {=IFERROR("#"&_xlfn.SEQUENCE(COUNTA(Vorhaben_1[Arbeitstitel])),"")} -> #1 | B16: Ping-Pong-Roboter | C16: 46024 | D16: 47118 | E16: =IF(C16>D16,"Das Startdatum muss vor dem Enddatum liegen.","")
E17: =IF(C17>D17,"Das Startdatum muss vor dem Enddatum liegen.","")
E18: =IF(C18>D18,"Das Startdatum muss vor dem Enddatum liegen.","")
E19: =IF(C19>D19,"Das Startdatum muss vor dem Enddatum liegen.","")
E20: =IF(C20>D20,"Das Startdatum muss vor dem Enddatum liegen.","")
E21: =IF(C21>D21,"Das Startdatum muss vor dem Enddatum liegen.","")
E22: =IF(C22>D22,"Das Startdatum muss vor dem Enddatum liegen.","")
C23: =C25&C24&" - "&C26&C24 -> 01.012025 - 31.12.2025 | D23: =D25&D24&" - "&D26&D24 -> - | E23: =E25&E24&" - "&E26&E24 -> - | F23: =F25&F24&" - "&F26&F24 -> 01 - 01 | G23: =G25&G24&" - "&G26&G24 -> 02 - 02 | H23: =H25&H24&" - "&H26&H24 -> 03 - 03
B24: Allgemein | C24: 2025 | F24: =E24+1 -> 1 | G24: =F24+1 -> 2 | H24: =G24+1 -> 3
B25: Start Wirtschaftsjahr | C25: 01.01 | F25: =E25 -> 0 | G25: =F25 -> 0 | H25: =G25 -> 0
B26: Ende Wirtschaftsjahr | C26: 31.12. | F26: =E26 -> 0 | G26: =F26 -> 0 | H26: =G26 -> 0
B27: Ist Rumpfwirtschatsjahr | C27: nein
B28: Jahresumsatz [€] | C28: 1
B29: Zahl der Mitarbeitenden [VZÄ] | C29: 1
B30: =_xlfn.LET( _xlpm.VZÄ_Unt_FuE, C32>C29, _xlpm.Personalkosten, C34<Dashboard!E10, _xlpm.Sachkosten, C35<Dashboard!E14, _xlpm.Auftragskosten, C47<Dashboard!E13, _xlpm.Förderung, C40<Dashboard!E15, IF(_xlpm.VZÄ_Unt_FuE,"Die VZÄ aus dem FuE können nicht größer sein, als das ganze Unternehmen.", IF(AND(_xlpm.Personalkosten,_xlpm.Sachkosten,_xlpm.Auftragskosten),"Die Personal- und Sach- und Auftragskosten der Projekte sind höher als die, des FuE Bereichs.", IF(AND(_xlpm.Personalkosten,_xlpm.Sachkosten),"Die Personal- und Sachkosten der Projekte sind höher als die, des FuE Bereichs.", IF(AND(_xlpm.Auftragskosten,_xlpm.Sachkosten),"Die Sach- und Auftragskosten der Projekte sind höher als die, des FuE Bereichs.", IF(AND(_xlpm.Auftragskosten,_xlpm.Personalkosten),"Die Personal- und Auftragskosten der Projekte sind höher als die, des FuE Bereichs.", IF(_xlpm.Personalkosten,"Die Personalkosten der Projekte sind höher als die des FuE Bereichs.", IF(_xlpm.Sachkosten,"Die Sachkosten der Projekte sind höher als die des FuE Bereichs.", IF(_xlpm.Auftragskosten,"Die Auftragskosten der Projekte sind höher als die des FuE Bereichs.", IF(_xlpm.Förderung,"Die sonstige FuE-Förderung der Projekte sind höher als die des FuE Bereichs.", "" ))))))))))
B31: FuE | C31: =C24 -> 2025
B32: Zahl der Mitarbeitenden in FuE [VZÄ]
B33: Interne Aufwendungen [€] | C33: =SUM(C34:C35) -> 0
B34: Personalaufwendungen [€]
B35: Sachaufwendungen und Investitionen [€]
B36: Externe Aufwendungen (FuE gesamt) [€] | C36: =SUM(C37:C38) -> 0
B37: Davon an Auftragnehmer innerhalb der EU/EWR [€]
B38: Davon an Auftragnehmer außerhalb der EU/EWR [€]
B39: Wurden öffentliche Förderungen für FuE in genutzt? | C39: nein
B40: Sonstige Öffentliche Förderungen für FuE [€]
B42: Verbundene Unternehmen
B43: Firmierung / Name | C43: Bundesland | D43: Adresse | E43: Steuernummer (nicht UStID) | F43: Umsatz [€] | G43: Mitarbeiter [VZÄ] | H43: Kosten für die, die Forschungszulage beantragt wurde/wird
F44: =C24 -> 2025 | G44: =C24 -> 2025 | H44: 2022 | I44: =H44+1 -> 2023 | J44: =I44+1 -> 2024 | K44: =J44+1 -> 2025 | L44: =K44+1 -> 2026 | M44: =L44+1 -> 2027
A45: {=IFERROR("#"&_xlfn.SEQUENCE(COUNTA(B45:B56)),"")}
H57: =SUM(H45:H56) -> 0 | I57: =SUM(I45:I56) -> 0 | J57: =SUM(J45:J56) -> 0 | K57: =SUM(K45:K56) -> 0 | L57: =SUM(L45:L56) -> 0 | M57: =SUM(M45:M56) -> 0
B59: Angaben zum Unternehmensverbund | C59: =C24 -> 2025
B60: Jahresumsatz [€] | C60: =C28+SUM(F45:F56) -> 1
B61: Zahl der Mitarbeitenden [VZÄ] | C61: =C29+SUM(G45:G56) -> 1
B65: Disclaimer: Alle kalkulierten Zahlen sind vom Anwender zu überprüfen. | G65: © consider it GmbH (2023). Die Vervielfältigung oder Veräußerung dieser Datei ist Dritten untersagt.

Sheet FuE Vorhaben
A1: 12 | B1: =$B$6 -> 1 | C1: =$B$6 -> 1 | D1: =$B$6 -> 1 | E1: =$B$6 -> 1 | F1: =$B$6 -> 1 | G1: =$B$6 -> 1 | H1: =$B$6 -> 1 | I1: =$B$6 -> 1 | ... L1: =$B$6 -> 1 | N1: =$O$6 -> 2 | O1: =$O$6 -> 2 | P1: =$O$6 -> 2 | Q1: =$O$6 -> 2 | R1: =$O$6 -> 2 | S1: =$O$6 -> 2 | T1: =$O$6 -> 2 | U1: =$O$6 -> 2 | ... Y1: =$O$6 -> 2 | AA1: =$AB$6 -> 3 | AB1: =$AB$6 -> 3 | AC1: =$AB$6 -> 3 | AD1: =$AB$6 -> 3 | AE1: =$AB$6 -> 3 | AF1: =$AB$6 -> 3 | AG1: =$AB$6 -> 3 | AH1: =$AB$6 -> 3 | ... AL1: =$AB$6 -> 3 | AN1: =$AO$6 -> 4 | AO1: =$AO$6 -> 4 | AP1: =$AO$6 -> 4 | AQ1: =$AO$6 -> 4 | AR1: =$AO$6 -> 4 | AS1: =$AO$6 -> 4 | AT1: =$AO$6 -> 4 | AU1: =$AO$6 -> 4 | ... AY1: =$AO$6 -> 4 | BA1: =$BB$6 -> 5 | BB1: =$BB$6 -> 5 | BC1: =$BB$6 -> 5 | BD1: =$BB$6 -> 5 | BE1: =$BB$6 -> 5 | BF1: =$BB$6 -> 5 | BG1: =$BB$6 -> 5 | BH1: =$BB$6 -> 5 | ... BL1: =$BB$6 -> 5 | BN1: =$BO$6 -> 6 | BO1: =$BO$6 -> 6 | BP1: =$BO$6 -> 6 | BQ1: =$BO$6 -> 6 | BR1: =$BO$6 -> 6 | BS1: =$BO$6 -> 6 | BT1: =$BO$6 -> 6 | BU1: =$BO$6 -> 6 | ... BY1: =$BO$6 -> 6 | CA1: =$CB$6 -> 7 | CB1: =$CB$6 -> 7 | CC1: =$CB$6 -> 7 | CD1: =$CB$6 -> 7 | CE1: =$CB$6 -> 7 | CF1: =$CB$6 -> 7 | CG1: =$CB$6 -> 7 | CH1: =$CB$6 -> 7 | ... CJ1: =$CB$6 -> 7 | CL1: =$CB$6 -> 7
B2: ="Angaben zum F&E Vorhaben: "& C6 -> Angaben zum F&E Vorhaben: Ping-Pong-Roboter | O2: ="Angaben zum F&E Vorhaben: "& P6 -> Angaben zum F&E Vorhaben: 0 | AB2: ="Angaben zum F&E Vorhaben: "& AC6 -> Angaben zum F&E Vorhaben: 0 | AO2: ="Angaben zum F&E Vorhaben: "& AP6 -> Angaben zum F&E Vorhaben: 0 | BB2: ="Angaben zum F&E Vorhaben: "& BC6 -> Angaben zum F&E Vorhaben: 0 | BO2: ="Angaben zum F&E Vorhaben: "& BP6 -> Angaben zum F&E Vorhaben: 0 | CB2: ="Angaben zum F&E Vorhaben: "& CC6 -> Angaben zum F&E Vorhaben: 0
B3: Dieses Tabellenblatt beschreibt ein einzelnes FuE-Vorhaben. | O3: Dieses Tabellenblatt beschreibt ein einzelnes FuE-Vorhaben. | AB3: Dieses Tabellenblatt beschreibt ein einzelnes FuE-Vorhaben. | AO3: Dieses Tabellenblatt beschreibt ein einzelnes FuE-Vorhaben. | BB3: Dieses Tabellenblatt beschreibt ein einzelnes FuE-Vorhaben. | BO3: Dieses Tabellenblatt beschreibt ein einzelnes FuE-Vorhaben. | CB3: Dieses Tabellenblatt beschreibt ein einzelnes FuE-Vorhaben.
B5: Allgemein | O5: Allgemein | AB5: Allgemein | AO5: Allgemein | BB5: Allgemein | BO5: Allgemein | CB5: Allgemein
B6: =ROUNDUP(COLUMN(C6)/$A$1,0) -> 1 | C6: {=INDIRECT("proj"&B6)} -> Ping-Pong-Roboter | O6: =ROUNDUP(COLUMN(P6)/$A$1,0) -> 2 | P6: {=INDIRECT("proj"&O6)} -> 0 | AB6: =ROUNDUP(COLUMN(AC6)/$A$1,0) -> 3 | AC6: {=INDIRECT("proj"&AB6)} -> 0 | AO6: =ROUNDUP(COLUMN(AP6)/$A$1,0) -> 4 | AP6: {=INDIRECT("proj"&AO6)} -> 0 | BB6: =ROUNDUP(COLUMN(BC6)/$A$1,0) -> 5 | BC6: {=INDIRECT("proj"&BB6)} -> 0 | BO6: =ROUNDUP(COLUMN(BP6)/$A$1,0) -> 6 | BP6: {=INDIRECT("proj"&BO6)} -> 0 | CB6: =ROUNDUP(COLUMN(CC6)/$A$1,0) -> 7 | CC6: {=INDIRECT("proj"&CB6)} -> 0
B7: Projektstart | C7: {=_xlfn.LET(_xlpm.datum,_xlfn.XLOOKUP(C6,'Ganzes Unternehmen'!$B$16:$B$22,'Ganzes Unternehmen'!$C$16:$C$22,"",0,1),IF(_xlpm.datum=0,"Bei Allg. Angaben eingeben.",_xlpm.datum))} -> 46024 | O7: Projektstart | P7: =_xlfn.LET(_xlpm.datum,_xlfn.XLOOKUP(P6,'Ganzes Unternehmen'!$B$16:$B$22,'Ganzes Unternehmen'!$C$16:$C$22,"",0,1),IF(_xlpm.datum=0,"Bei Allg. Angaben eingeben.",_xlpm.datum)) | AB7: Projektstart | AC7: =_xlfn.LET(_xlpm.datum,_xlfn.XLOOKUP(AC6,'Ganzes Unternehmen'!$B$16:$B$22,'Ganzes Unternehmen'!$C$16:$C$22,"",0,1),IF(_xlpm.datum=0,"Bei Allg. Angaben eingeben.",_xlpm.datum)) | AO7: Projektstart | AP7: =_xlfn.LET(_xlpm.datum,_xlfn.XLOOKUP(AP6,'Ganzes Unternehmen'!$B$16:$B$22,'Ganzes Unternehmen'!$C$16:$C$22,"",0,1),IF(_xlpm.datum=0,"Bei Allg. Angaben eingeben.",_xlpm.datum)) | BB7: Projektstart | BC7: =_xlfn.LET(_xlpm.datum,_xlfn.XLOOKUP(BC6,'Ganzes Unternehmen'!$B$16:$B$22,'Ganzes Unternehmen'!$C$16:$C$22,"",0,1),IF(_xlpm.datum=0,"Bei Allg. Angaben eingeben.",_xlpm.datum)) | BO7: Projektstart | BP7: =_xlfn.LET(_xlpm.datum,_xlfn.XLOOKUP(BP6,'Ganzes Unternehmen'!$B$16:$B$22,'Ganzes Unternehmen'!$C$16:$C$22,"",0,1),IF(_xlpm.datum=0,"Bei Allg. Angaben eingeben.",_xlpm.datum)) | CB7: Projektstart | CC7: =_xlfn.LET(_xlpm.datum,_xlfn.XLOOKUP(CC6,'Ganzes Unternehmen'!$B$16:$B$22,'Ganzes Unternehmen'!$C$16:$C$22,"",0,1),IF(_xlpm.datum=0,"Bei Allg. Angaben eingeben.",_xlpm.datum))
B8: Projektende | C8: {=_xlfn.LET(_xlpm.datum,_xlfn.XLOOKUP(C6,'Ganzes Unternehmen'!$B$16:$B$22,'Ganzes Unternehmen'!$D$16:$D$22,"",0,1),IF(_xlpm.datum&"1"="1","Bei Allg. Angaben eingeben.",_xlpm.datum))} -> 47118 | O8: Projektende | P8: =_xlfn.LET(_xlpm.datum,_xlfn.XLOOKUP(P6,'Ganzes Unternehmen'!$B$16:$B$22,'Ganzes Unternehmen'!$D$16:$D$22,"",0,1),IF(_xlpm.datum&"1"="1","Bei Allg. Angaben eingeben.",_xlpm.datum)) -> Bei Allg. Angaben eingeben. | AB8: Projektende | AC8: =_xlfn.LET(_xlpm.datum,_xlfn.XLOOKUP(AC6,'Ganzes Unternehmen'!$B$16:$B$22,'Ganzes Unternehmen'!$D$16:$D$22,"",0,1),IF(_xlpm.datum&"1"="1","Bei Allg. Angaben eingeben.",_xlpm.datum)) -> Bei Allg. Angaben eingeben. | AO8: Projektende | AP8: =_xlfn.LET(_xlpm.datum,_xlfn.XLOOKUP(AP6,'Ganzes Unternehmen'!$B$16:$B$22,'Ganzes Unternehmen'!$D$16:$D$22,"",0,1),IF(_xlpm.datum&"1"="1","Bei Allg. Angaben eingeben.",_xlpm.datum)) -> Bei Allg. Angaben eingeben. | BB8: Projektende | BC8: =_xlfn.LET(_xlpm.datum,_xlfn.XLOOKUP(BC6,'Ganzes Unternehmen'!$B$16:$B$22,'Ganzes Unternehmen'!$D$16:$D$22,"",0,1),IF(_xlpm.datum&"1"="1","Bei Allg. Angaben eingeben.",_xlpm.datum)) -> Bei Allg. Angaben eingeben. | BO8: Projektende | BP8: =_xlfn.LET(_xlpm.datum,_xlfn.XLOOKUP(BP6,'Ganzes Unternehmen'!$B$16:$B$22,'Ganzes Unternehmen'!$D$16:$D$22,"",0,1),IF(_xlpm.datum&"1"="1","Bei Allg. Angaben eingeben.",_xlpm.datum)) -> Bei Allg. Angaben eingeben. | CB8: Projektende | CC8: =_xlfn.LET(_xlpm.datum,_xlfn.XLOOKUP(CC6,'Ganzes Unternehmen'!$B$16:$B$22,'Ganzes Unternehmen'!$D$16:$D$22,"",0,1),IF(_xlpm.datum&"1"="1","Bei Allg. Angaben eingeben.",_xlpm.datum)) -> Bei Allg. Angaben eingeben.
C9: =IFERROR(AND(C10>=YEAR(C7),C10<=YEAR(C8)),FALSE) -> FALSE | D9: =IFERROR(AND(D10>=YEAR(C7),D10<=YEAR(C8)),FALSE) -> FALSE | E9: =IFERROR(AND(E10>=YEAR(C7),E10<=YEAR(C8)),FALSE) -> FALSE | F9: =IFERROR(AND(F10>=YEAR(C7),F10<=YEAR(C8)),FALSE) -> FALSE | G9: =IFERROR(AND(G10>=YEAR(C7),G10<=YEAR(C8)),FALSE) -> TRUE | H9: =IFERROR(AND(H10>=YEAR(C7),H10<=YEAR(C8)),FALSE) -> TRUE | I9: =IFERROR(AND(I10>=YEAR(C7),I10<=YEAR(C8)),FALSE) -> TRUE | J9: =IFERROR(AND(J10>=YEAR(C7),J10<=YEAR(C8)),FALSE) -> FALSE | P9: =IFERROR(AND(P10>=YEAR(P7),P10<=YEAR(P8)),FALSE) -> FALSE | Q9: =IFERROR(AND(Q10>=YEAR(P7),Q10<=YEAR(P8)),FALSE) -> FALSE | R9: =IFERROR(AND(R10>=YEAR(P7),R10<=YEAR(P8)),FALSE) -> FALSE | S9: =IFERROR(AND(S10>=YEAR(P7),S10<=YEAR(P8)),FALSE) -> FALSE | T9: =IFERROR(AND(T10>=YEAR(P7),T10<=YEAR(P8)),FALSE) -> FALSE | U9: =IFERROR(AND(U10>=YEAR(P7),U10<=YEAR(P8)),FALSE) -> FALSE | V9: =IFERROR(AND(V10>=YEAR(Q7),V10<=YEAR(Q8)),FALSE) -> FALSE | W9: =IFERROR(AND(W10>=YEAR(R7),W10<=YEAR(R8)),FALSE) -> FALSE | AC9: =IFERROR(AND(AC10>=YEAR(AC7),AC10<=YEAR(AC8)),FALSE) -> FALSE | AD9: =IFERROR(AND(AD10>=YEAR(AC7),AD10<=YEAR(AC8)),FALSE) -> FALSE | AE9: =IFERROR(AND(AE10>=YEAR(AC7),AE10<=YEAR(AC8)),FALSE) -> FALSE | AF9: =IFERROR(AND(AF10>=YEAR(AC7),AF10<=YEAR(AC8)),FALSE) -> FALSE | AG9: =IFERROR(AND(AG10>=YEAR(AC7),AG10<=YEAR(AC8)),FALSE) -> FALSE | AH9: =IFERROR(AND(AH10>=YEAR(AC7),AH10<=YEAR(AC8)),FALSE) -> FALSE | AI9: =IFERROR(AND(AI10>=YEAR(AD7),AI10<=YEAR(AD8)),FALSE) -> FALSE | AJ9: =IFERROR(AND(AJ10>=YEAR(AE7),AJ10<=YEAR(AE8)),FALSE) -> FALSE | AP9: =IFERROR(AND(AP10>=YEAR(AP7),AP10<=YEAR(AP8)),FALSE) -> FALSE | AQ9: =IFERROR(AND(AQ10>=YEAR(AP7),AQ10<=YEAR(AP8)),FALSE) -> FALSE | AR9: =IFERROR(AND(AR10>=YEAR(AP7),AR10<=YEAR(AP8)),FALSE) -> FALSE | AS9: =IFERROR(AND(AS10>=YEAR(AP7),AS10<=YEAR(AP8)),FALSE) -> FALSE | AT9: =IFERROR(AND(AT10>=YEAR(AP7),AT10<=YEAR(AP8)),FALSE) -> FALSE | AU9: =IFERROR(AND(AU10>=YEAR(AP7),AU10<=YEAR(AP8)),FALSE) -> FALSE | AV9: =IFERROR(AND(AV10>=YEAR(AQ7),AV10<=YEAR(AQ8)),FALSE) -> FALSE | AW9: =IFERROR(AND(AW10>=YEAR(AR7),AW10<=YEAR(AR8)),FALSE) -> FALSE | BC9: =IFERROR(AND(BC10>=YEAR(BC7),BC10<=YEAR(BC8)),FALSE) -> FALSE | BD9: =IFERROR(AND(BD10>=YEAR(BC7),BD10<=YEAR(BC8)),FALSE) -> FALSE | BE9: =IFERROR(AND(BE10>=YEAR(BC7),BE10<=YEAR(BC8)),FALSE) -> FALSE | BF9: =IFERROR(AND(BF10>=YEAR(BC7),BF10<=YEAR(BC8)),FALSE) -> FALSE | BG9: =IFERROR(AND(BG10>=YEAR(BC7),BG10<=YEAR(BC8)),FALSE) -> FALSE | BH9: =IFERROR(AND(BH10>=YEAR(BC7),BH10<=YEAR(BC8)),FALSE) -> FALSE | BI9: =IFERROR(AND(BI10>=YEAR(BD7),BI10<=YEAR(BD8)),FALSE) -> FALSE | BJ9: =IFERROR(AND(BJ10>=YEAR(BE7),BJ10<=YEAR(BE8)),FALSE) -> FALSE | BP9: =IFERROR(AND(BP10>=YEAR(BP7),BP10<=YEAR(BP8)),FALSE) -> FALSE | BQ9: =IFERROR(AND(BQ10>=YEAR(BP7),BQ10<=YEAR(BP8)),FALSE) -> FALSE | BR9: =IFERROR(AND(BR10>=YEAR(BP7),BR10<=YEAR(BP8)),FALSE) -> FALSE | BS9: =IFERROR(AND(BS10>=YEAR(BP7),BS10<=YEAR(BP8)),FALSE) -> FALSE | BT9: =IFERROR(AND(BT10>=YEAR(BP7),BT10<=YEAR(BP8)),FALSE) -> FALSE | BU9: =IFERROR(AND(BU10>=YEAR(BP7),BU10<=YEAR(BP8)),FALSE) -> FALSE | BV9: =IFERROR(AND(BV10>=YEAR(BQ7),BV10<=YEAR(BQ8)),FALSE) -> FALSE | BW9: =IFERROR(AND(BW10>=YEAR(BR7),BW10<=YEAR(BR8)),FALSE) -> FALSE | CC9: =IFERROR(AND(CC10>=YEAR(CC7),CC10<=YEAR(CC8)),FALSE) -> FALSE | CD9: =IFERROR(AND(CD10>=YEAR(CC7),CD10<=YEAR(CC8)),FALSE) -> FALSE | CE9: =IFERROR(AND(CE10>=YEAR(CC7),CE10<=YEAR(CC8)),FALSE) -> FALSE | CF9: =IFERROR(AND(CF10>=YEAR(CC7),CF10<=YEAR(CC8)),FALSE) -> FALSE | CG9: =IFERROR(AND(CG10>=YEAR(CC7),CG10<=YEAR(CC8)),FALSE) -> FALSE | CH9: =IFERROR(AND(CH10>=YEAR(CC7),CH10<=YEAR(CC8)),FALSE) -> FALSE | CI9: =IFERROR(AND(CI10>=YEAR(CD7),CI10<=YEAR(CD8)),FALSE) -> FALSE | CJ9: =IFERROR(AND(CJ10>=YEAR(CE7),CJ10<=YEAR(CE8)),FALSE) -> FALSE
B10: Finanzieller Rahmen | C10: 2022 | D10: =C10+1 -> 2023 | E10: =D10+1 -> 2024 | F10: =E10+1 -> 2025 | G10: =F10+1 -> 2026 | H10: =G10+1 -> 2027 | I10: =H10+1 -> 2028 | J10: =I10+1 -> 2029 | O10: Finanzieller Rahmen | P10: =C10 -> 2022 | Q10: =P10+1 -> 2023 | R10: =Q10+1 -> 2024 | S10: =R10+1 -> 2025 | T10: =S10+1 -> 2026 | U10: =T10+1 -> 2027 | V10: =U10+1 -> 2028 | W10: =V10+1 -> 2029 | AB10: Finanzieller Rahmen | AC10: =C10 -> 2022 | AD10: =AC10+1 -> 2023 | AE10: =AD10+1 -> 2024 | AF10: =AE10+1 -> 2025 | AG10: =AF10+1 -> 2026 | AH10: =AG10+1 -> 2027 | AI10: =AH10+1 -> 2028 | AJ10: =AI10+1 -> 2029 | AO10: Finanzieller Rahmen | AP10: =C10 -> 2022 | AQ10: =AP10+1 -> 2023 | AR10: =AQ10+1 -> 2024 | AS10: =AR10+1 -> 2025 | AT10: =AS10+1 -> 2026 | AU10: =AT10+1 -> 2027 | AV10: =AU10+1 -> 2028 | AW10: =AV10+1 -> 2029 | BB10: Finanzieller Rahmen | BC10: =C10 -> 2022 | BD10: =BC10+1 -> 2023 | BE10: =BD10+1 -> 2024 | BF10: =BE10+1 -> 2025 | BG10: =BF10+1 -> 2026 | BH10: =BG10+1 -> 2027 | BI10: =BH10+1 -> 2028 | BJ10: =BI10+1 -> 2029 | BO10: Finanzieller Rahmen | BP10: =C10 -> 2022 | BQ10: =BP10+1 -> 2023 | BR10: =BQ10+1 -> 2024 | BS10: =BR10+1 -> 2025 | BT10: =BS10+1 -> 2026 | BU10: =BT10+1 -> 2027 | BV10: =BU10+1 -> 2028 | BW10: =BV10+1 -> 2029 | CB10: Finanzieller Rahmen | CC10: =C10 -> 2022 | CD10: =CC10+1 -> 2023 | CE10: =CD10+1 -> 2024 | CF10: =CE10+1 -> 2025 | CG10: =CF10+1 -> 2026 | CH10: =CG10+1 -> 2027 | CI10: =CH10+1 -> 2028 | CJ10: =CH10+1 -> 2028
B11: Personalkosten [€] | C11: =_xlfn.LET(_xlpm.out,ROUND((1+C13/100)*C12,2), IF(C9,_xlpm.out,0)) -> 0 | D11: =_xlfn.LET(_xlpm.out,ROUND((1+D13/100)*D12,2), IF(D9,_xlpm.out,0)) -> 0 | E11: =_xlfn.LET(_xlpm.out,ROUND((1+E13/100)*E12,2), IF(E9,_xlpm.out,0)) -> 0 | F11: =_xlfn.LET(_xlpm.out,ROUND((1+F13/100)*F12,2), IF(F9,_xlpm.out,0)) -> 0 | G11: {=_xlfn.LET(_xlpm.out,ROUND((1+G13/100)*G12,2), IF(G9,_xlpm.out,0))} -> 2730 | H11: {=_xlfn.LET(_xlpm.out,ROUND((1+H13/100)*H12,2), IF(H9,_xlpm.out,0))} -> 8190 | I11: {=_xlfn.LET(_xlpm.out,ROUND((1+I13/100)*I12,2), IF(I9,_xlpm.out,0))} -> 16380 | J11: {=_xlfn.LET(_xlpm.out,ROUND((1+J13/100)*J12,2), IF(J9,_xlpm.out,0))} -> 0 | O11: Personalkosten [€] | P11: =_xlfn.LET(_xlpm.out,ROUND((1+P13/100)*P12+P14,2), IF(P9,_xlpm.out,0)) -> 0 | Q11: =_xlfn.LET(_xlpm.out,ROUND((1+Q13/100)*Q12+Q14,2), IF(Q9,_xlpm.out,0)) -> 0 | R11: =_xlfn.LET(_xlpm.out,ROUND((1+R13/100)*R12+R14,2), IF(R9,_xlpm.out,0)) -> 0 | S11: =_xlfn.LET(_xlpm.out,ROUND((1+S13/100)*S12+S14,2), IF(S9,_xlpm.out,0)) -> 0 | T11: =_xlfn.LET(_xlpm.out,ROUND((1+T13/100)*T12+T14,2), IF(T9,_xlpm.out,0)) -> 0 | U11: =_xlfn.LET(_xlpm.out,ROUND((1+U13/100)*U12+U14,2), IF(U9,_xlpm.out,0)) -> 0 | V11: =_xlfn.LET(_xlpm.out,ROUND((1+V13/100)*V12+V14,2), IF(V9,_xlpm.out,0)) -> 0 | W11: =_xlfn.LET(_xlpm.out,ROUND((1+W13/100)*W12+W14,2), IF(W9,_xlpm.out,0)) -> 0 | AB11: Personalkosten [€] | AC11: =_xlfn.LET(_xlpm.out,ROUND((1+AC13/100)*AC12+AC14,2), IF(AC9,_xlpm.out,0)) -> 0 | AD11: =_xlfn.LET(_xlpm.out,ROUND((1+AD13/100)*AD12+AD14,2), IF(AD9,_xlpm.out,0)) -> 0 | AE11: =_xlfn.LET(_xlpm.out,ROUND((1+AE13/100)*AE12+AE14,2), IF(AE9,_xlpm.out,0)) -> 0 | AF11: =_xlfn.LET(_xlpm.out,ROUND((1+AF13/100)*AF12+AF14,2), IF(AF9,_xlpm.out,0)) -> 0 | AG11: =_xlfn.LET(_xlpm.out,ROUND((1+AG13/100)*AG12+AG14,2), IF(AG9,_xlpm.out,0)) -> 0 | AH11: =_xlfn.LET(_xlpm.out,ROUND((1+AH13/100)*AH12+AH14,2), IF(AH9,_xlpm.out,0)) -> 0 | AI11: =_xlfn.LET(_xlpm.out,ROUND((1+AI13/100)*AI12+AI14,2), IF(AI9,_xlpm.out,0)) -> 0 | AJ11: =_xlfn.LET(_xlpm.out,ROUND((1+AJ13/100)*AJ12+AJ14,2), IF(AJ9,_xlpm.out,0)) -> 0 | AO11: Personalkosten [€] | AP11: =_xlfn.LET(_xlpm.out,ROUND((1+AP13/100)*AP12+AP14,2), IF(AP9,_xlpm.out,0)) -> 0 | AQ11: =_xlfn.LET(_xlpm.out,ROUND((1+AQ13/100)*AQ12+AQ14,2), IF(AQ9,_xlpm.out,0)) -> 0 | AR11: =_xlfn.LET(_xlpm.out,ROUND((1+AR13/100)*AR12+AR14,2), IF(AR9,_xlpm.out,0)) -> 0 | AS11: =_xlfn.LET(_xlpm.out,ROUND((1+AS13/100)*AS12+AS14,2), IF(AS9,_xlpm.out,0)) -> 0 | AT11: =_xlfn.LET(_xlpm.out,ROUND((1+AT13/100)*AT12+AT14,2), IF(AT9,_xlpm.out,0)) -> 0 | AU11: =_xlfn.LET(_xlpm.out,ROUND((1+AU13/100)*AU12+AU14,2), IF(AU9,_xlpm.out,0)) -> 0 | AV11: =_xlfn.LET(_xlpm.out,ROUND((1+AV13/100)*AV12+AV14,2), IF(AV9,_xlpm.out,0)) -> 0 | AW11: =_xlfn.LET(_xlpm.out,ROUND((1+AW13/100)*AW12+AW14,2), IF(AW9,_xlpm.out,0)) -> 0 | BB11: Personalkosten [€] | BC11: =_xlfn.LET(_xlpm.out,ROUND((1+BC13/100)*BC12+BC14,2), IF(BC9,_xlpm.out,0)) -> 0 | BD11: =_xlfn.LET(_xlpm.out,ROUND((1+BD13/100)*BD12+BD14,2), IF(BD9,_xlpm.out,0)) -> 0 | BE11: =_xlfn.LET(_xlpm.out,ROUND((1+BE13/100)*BE12+BE14,2), IF(BE9,_xlpm.out,0)) -> 0 | BF11: =_xlfn.LET(_xlpm.out,ROUND((1+BF13/100)*BF12+BF14,2), IF(BF9,_xlpm.out,0)) -> 0 | BG11: =_xlfn.LET(_xlpm.out,ROUND((1+BG13/100)*BG12+BG14,2), IF(BG9,_xlpm.out,0)) -> 0 | BH11: =_xlfn.LET(_xlpm.out,ROUND((1+BH13/100)*BH12+BH14,2), IF(BH9,_xlpm.out,0)) -> 0 | BI11: =_xlfn.LET(_xlpm.out,ROUND((1+BI13/100)*BI12+BI14,2), IF(BI9,_xlpm.out,0)) -> 0 | BJ11: =_xlfn.LET(_xlpm.out,ROUND((1+BJ13/100)*BJ12+BJ14,2), IF(BJ9,_xlpm.out,0)) -> 0 | BO11: Personalkosten [€] | BP11: =_xlfn.LET(_xlpm.out,ROUND((1+BP13/100)*BP12+BP14,2), IF(BP9,_xlpm.out,0)) -> 0 | BQ11: =_xlfn.LET(_xlpm.out,ROUND((1+BQ13/100)*BQ12+BQ14,2), IF(BQ9,_xlpm.out,0)) -> 0 | BR11: =_xlfn.LET(_xlpm.out,ROUND((1+BR13/100)*BR12+BR14,2), IF(BR9,_xlpm.out,0)) -> 0 | BS11: =_xlfn.LET(_xlpm.out,ROUND((1+BS13/100)*BS12+BS14,2), IF(BS9,_xlpm.out,0)) -> 0 | BT11: =_xlfn.LET(_xlpm.out,ROUND((1+BT13/100)*BT12+BT14,2), IF(BT9,_xlpm.out,0)) -> 0 | BU11: =_xlfn.LET(_xlpm.out,ROUND((1+BU13/100)*BU12+BU14,2), IF(BU9,_xlpm.out,0)) -> 0 | BV11: =_xlfn.LET(_xlpm.out,ROUND((1+BV13/100)*BV12+BV14,2), IF(BV9,_xlpm.out,0)) -> 0 | BW11: =_xlfn.LET(_xlpm.out,ROUND((1+BW13/100)*BW12+BW14,2), IF(BW9,_xlpm.out,0)) -> 0 | CB11: Personalkosten [€] | CC11: =_xlfn.LET(_xlpm.out,ROUND((1+CC13/100)*CC12+CC14,2), IF(CC9,_xlpm.out,0)) -> 0 | CD11: =_xlfn.LET(_xlpm.out,ROUND((1+CD13/100)*CD12+CD14,2), IF(CD9,_xlpm.out,0)) -> 0 | CE11: =_xlfn.LET(_xlpm.out,ROUND((1+CE13/100)*CE12+CE14,2), IF(CE9,_xlpm.out,0)) -> 0 | CF11: =_xlfn.LET(_xlpm.out,ROUND((1+CF13/100)*CF12+CF14,2), IF(CF9,_xlpm.out,0)) -> 0 | CG11: =_xlfn.LET(_xlpm.out,ROUND((1+CG13/100)*CG12+CG14,2), IF(CG9,_xlpm.out,0)) -> 0 | CH11: =_xlfn.LET(_xlpm.out,ROUND((1+CH13/100)*CH12+CH14,2), IF(CH9,_xlpm.out,0)) -> 0 | CI11: =_xlfn.LET(_xlpm.out,ROUND((1+CI13/100)*CI12+CI14,2), IF(CI9,_xlpm.out,0)) -> 0 | CJ11: =_xlfn.LET(_xlpm.out,ROUND((1+CJ13/100)*CJ12+CJ14,2), IF(CJ9,_xlpm.out,0)) -> 0
B12: Personalkosten kalkuliert [€] | C12: =ROUND(SUMIFS(MitarbeiterFTE[[Kosten]:[Kosten]],MitarbeiterFTE[[Jahr]:[Jahr]],C10,MitarbeiterFTE[[Vorhaben]:[Vorhaben]],C75),2) -> 0 | D12: =ROUND(SUMIFS(MitarbeiterFTE[[Kosten]:[Kosten]],MitarbeiterFTE[[Jahr]:[Jahr]],D10,MitarbeiterFTE[[Vorhaben]:[Vorhaben]],D75),2) -> 0 | E12: =ROUND(SUMIFS(MitarbeiterFTE[[Kosten]:[Kosten]],MitarbeiterFTE[[Jahr]:[Jahr]],E10,MitarbeiterFTE[[Vorhaben]:[Vorhaben]],E75),2) -> 0 | F12: =ROUND(SUMIFS(MitarbeiterFTE[[Kosten]:[Kosten]],MitarbeiterFTE[[Jahr]:[Jahr]],F10,MitarbeiterFTE[[Vorhaben]:[Vorhaben]],F75),2) -> 0 | G12: =ROUND(SUMIFS(MitarbeiterFTE[[Kosten]:[Kosten]],MitarbeiterFTE[[Jahr]:[Jahr]],G10,MitarbeiterFTE[[Vorhaben]:[Vorhaben]],G75),2) -> 2600 | H12: =ROUND(SUMIFS(MitarbeiterFTE[[Kosten]:[Kosten]],MitarbeiterFTE[[Jahr]:[Jahr]],H10,MitarbeiterFTE[[Vorhaben]:[Vorhaben]],H75),2) -> 7800 | I12: =ROUND(SUMIFS(MitarbeiterFTE[[Kosten]:[Kosten]],MitarbeiterFTE[[Jahr]:[Jahr]],I10,MitarbeiterFTE[[Vorhaben]:[Vorhaben]],I75),2) -> 15600 | J12: =ROUND(SUMIFS(MitarbeiterFTE[[Kosten]:[Kosten]],MitarbeiterFTE[[Jahr]:[Jahr]],J10,MitarbeiterFTE[[Vorhaben]:[Vorhaben]],J75),2) -> 0 | O12: Personalkosten kalkuliert [€] | P12: =ROUND(SUMIFS(MitarbeiterFTE[[Kosten]:[Kosten]],MitarbeiterFTE[[Jahr]:[Jahr]],P10,MitarbeiterFTE[[Vorhaben]:[Vorhaben]],P75),2) -> 0 | Q12: =ROUND(SUMIFS(MitarbeiterFTE[[Kosten]:[Kosten]],MitarbeiterFTE[[Jahr]:[Jahr]],Q10,MitarbeiterFTE[[Vorhaben]:[Vorhaben]],Q75),2) -> 0 | R12: =ROUND(SUMIFS(MitarbeiterFTE[[Kosten]:[Kosten]],MitarbeiterFTE[[Jahr]:[Jahr]],R10,MitarbeiterFTE[[Vorhaben]:[Vorhaben]],R75),2) -> 0 | S12: =ROUND(SUMIFS(MitarbeiterFTE[[Kosten]:[Kosten]],MitarbeiterFTE[[Jahr]:[Jahr]],S10,MitarbeiterFTE[[Vorhaben]:[Vorhaben]],S75),2) -> 0 | T12: =ROUND(SUMIFS(MitarbeiterFTE[[Kosten]:[Kosten]],MitarbeiterFTE[[Jahr]:[Jahr]],T10,MitarbeiterFTE[[Vorhaben]:[Vorhaben]],T75),2) -> 0 | U12: =ROUND(SUMIFS(MitarbeiterFTE[[Kosten]:[Kosten]],MitarbeiterFTE[[Jahr]:[Jahr]],U10,MitarbeiterFTE[[Vorhaben]:[Vorhaben]],U75),2) -> 0 | V12: =ROUND(SUMIFS(MitarbeiterFTE[[Kosten]:[Kosten]],MitarbeiterFTE[[Jahr]:[Jahr]],V10,MitarbeiterFTE[[Vorhaben]:[Vorhaben]],V75),2) -> 0 | W12: =ROUND(SUMIFS(MitarbeiterFTE[[Kosten]:[Kosten]],MitarbeiterFTE[[Jahr]:[Jahr]],W10,MitarbeiterFTE[[Vorhaben]:[Vorhaben]],W75),2) -> 0 | AB12: Personalkosten kalkuliert [€] | AC12: =ROUND(SUMIFS(MitarbeiterFTE[[Kosten]:[Kosten]],MitarbeiterFTE[[Jahr]:[Jahr]],AC10,MitarbeiterFTE[[Vorhaben]:[Vorhaben]],AC75),2) -> 0 | AE12: =ROUND(SUMIFS(MitarbeiterFTE[[Kosten]:[Kosten]],MitarbeiterFTE[[Jahr]:[Jahr]],AE10,MitarbeiterFTE[[Vorhaben]:[Vorhaben]],AE75),2) -> 0 | AF12: =ROUND(SUMIFS(MitarbeiterFTE[[Kosten]:[Kosten]],MitarbeiterFTE[[Jahr]:[Jahr]],AF10,MitarbeiterFTE[[Vorhaben]:[Vorhaben]],AF75),2) -> 0 | AG12: =ROUND(SUMIFS(MitarbeiterFTE[[Kosten]:[Kosten]],MitarbeiterFTE[[Jahr]:[Jahr]],AG10,MitarbeiterFTE[[Vorhaben]:[Vorhaben]],AG75),2) -> 0 | AH12: =ROUND(SUMIFS(MitarbeiterFTE[[Kosten]:[Kosten]],MitarbeiterFTE[[Jahr]:[Jahr]],AH10,MitarbeiterFTE[[Vorhaben]:[Vorhaben]],AH75),2) -> 0 | AI12: =ROUND(SUMIFS(MitarbeiterFTE[[Kosten]:[Kosten]],MitarbeiterFTE[[Jahr]:[Jahr]],AI10,MitarbeiterFTE[[Vorhaben]:[Vorhaben]],AI75),2) -> 0 | AJ12: =ROUND(SUMIFS(MitarbeiterFTE[[Kosten]:[Kosten]],MitarbeiterFTE[[Jahr]:[Jahr]],AJ10,MitarbeiterFTE[[Vorhaben]:[Vorhaben]],AJ75),2) -> 0 | AO12: Personalkosten kalkuliert [€] | AP12: =ROUND(SUMIFS(MitarbeiterFTE[[Kosten]:[Kosten]],MitarbeiterFTE[[Jahr]:[Jahr]],AP10,MitarbeiterFTE[[Vorhaben]:[Vorhaben]],AP75),2) -> 0 | AR12: =ROUND(SUMIFS(MitarbeiterFTE[[Kosten]:[Kosten]],MitarbeiterFTE[[Jahr]:[Jahr]],AR10,MitarbeiterFTE[[Vorhaben]:[Vorhaben]],AR75),2) -> 0 | AS12: =ROUND(SUMIFS(MitarbeiterFTE[[Kosten]:[Kosten]],MitarbeiterFTE[[Jahr]:[Jahr]],AS10,MitarbeiterFTE[[Vorhaben]:[Vorhaben]],AS75),2) -> 0 | AT12: =ROUND(SUMIFS(MitarbeiterFTE[[Kosten]:[Kosten]],MitarbeiterFTE[[Jahr]:[Jahr]],AT10,MitarbeiterFTE[[Vorhaben]:[Vorhaben]],AT75),2) -> 0 | AU12: =ROUND(SUMIFS(MitarbeiterFTE[[Kosten]:[Kosten]],MitarbeiterFTE[[Jahr]:[Jahr]],AU10,MitarbeiterFTE[[Vorhaben]:[Vorhaben]],AU75),2) -> 0 | AV12: =ROUND(SUMIFS(MitarbeiterFTE[[Kosten]:[Kosten]],MitarbeiterFTE[[Jahr]:[Jahr]],AV10,MitarbeiterFTE[[Vorhaben]:[Vorhaben]],AV75),2) -> 0 | AW12: =ROUND(SUMIFS(MitarbeiterFTE[[Kosten]:[Kosten]],MitarbeiterFTE[[Jahr]:[Jahr]],AW10,MitarbeiterFTE[[Vorhaben]:[Vorhaben]],AW75),2) -> 0 | BB12: Personalkosten kalkuliert [€] | BC12: =ROUND(SUMIFS(MitarbeiterFTE[[Kosten]:[Kosten]],MitarbeiterFTE[[Jahr]:[Jahr]],BC10,MitarbeiterFTE[[Vorhaben]:[Vorhaben]],BC75),2) -> 0 | BE12: =ROUND(SUMIFS(MitarbeiterFTE[[Kosten]:[Kosten]],MitarbeiterFTE[[Jahr]:[Jahr]],BE10,MitarbeiterFTE[[Vorhaben]:[Vorhaben]],BE75),2) -> 0 | BF12: =ROUND(SUMIFS(MitarbeiterFTE[[Kosten]:[Kosten]],MitarbeiterFTE[[Jahr]:[Jahr]],BF10,MitarbeiterFTE[[Vorhaben]:[Vorhaben]],BF75),2) -> 0 | BG12: =ROUND(SUMIFS(MitarbeiterFTE[[Kosten]:[Kosten]],MitarbeiterFTE[[Jahr]:[Jahr]],BG10,MitarbeiterFTE[[Vorhaben]:[Vorhaben]],BG75),2) -> 0 | BH12: =ROUND(SUMIFS(MitarbeiterFTE[[Kosten]:[Kosten]],MitarbeiterFTE[[Jahr]:[Jahr]],BH10,MitarbeiterFTE[[Vorhaben]:[Vorhaben]],BH75),2) -> 0 | BI12: =ROUND(SUMIFS(MitarbeiterFTE[[Kosten]:[Kosten]],MitarbeiterFTE[[Jahr]:[Jahr]],BI10,MitarbeiterFTE[[Vorhaben]:[Vorhaben]],BI75),2) -> 0 | BJ12: =ROUND(SUMIFS(MitarbeiterFTE[[Kosten]:[Kosten]],MitarbeiterFTE[[Jahr]:[Jahr]],BJ10,MitarbeiterFTE[[Vorhaben]:[Vorhaben]],BJ75),2) -> 0 | BO12: Personalkosten kalkuliert [€] | BP12: =ROUND(SUMIFS(MitarbeiterFTE[[Kosten]:[Kosten]],MitarbeiterFTE[[Jahr]:[Jahr]],BP10,MitarbeiterFTE[[Vorhaben]:[Vorhaben]],BP75),2) -> 0 | BR12: =ROUND(SUMIFS(MitarbeiterFTE[[Kosten]:[Kosten]],MitarbeiterFTE[[Jahr]:[Jahr]],BR10,MitarbeiterFTE[[Vorhaben]:[Vorhaben]],BR75),2) -> 0 | BS12: =ROUND(SUMIFS(MitarbeiterFTE[[Kosten]:[Kosten]],MitarbeiterFTE[[Jahr]:[Jahr]],BS10,MitarbeiterFTE[[Vorhaben]:[Vorhaben]],BS75),2) -> 0 | BT12: =ROUND(SUMIFS(MitarbeiterFTE[[Kosten]:[Kosten]],MitarbeiterFTE[[Jahr]:[Jahr]],BT10,MitarbeiterFTE[[Vorhaben]:[Vorhaben]],BT75),2) -> 0 | BU12: =ROUND(SUMIFS(MitarbeiterFTE[[Kosten]:[Kosten]],MitarbeiterFTE[[Jahr]:[Jahr]],BU10,MitarbeiterFTE[[Vorhaben]:[Vorhaben]],BU75),2) -> 0 | BV12: =ROUND(SUMIFS(MitarbeiterFTE[[Kosten]:[Kosten]],MitarbeiterFTE[[Jahr]:[Jahr]],BV10,MitarbeiterFTE[[Vorhaben]:[Vorhaben]],BV75),2) -> 0 | BW12: =ROUND(SUMIFS(MitarbeiterFTE[[Kosten]:[Kosten]],MitarbeiterFTE[[Jahr]:[Jahr]],BW10,MitarbeiterFTE[[Vorhaben]:[Vorhaben]],BW75),2) -> 0 | CB12: Personalkosten kalkuliert [€] | CC12: =ROUND(SUMIFS(MitarbeiterFTE[[Kosten]:[Kosten]],MitarbeiterFTE[[Jahr]:[Jahr]],CC10,MitarbeiterFTE[[Vorhaben]:[Vorhaben]],CC75),2) -> 0 | CE12: =ROUND(SUMIFS(MitarbeiterFTE[[Kosten]:[Kosten]],MitarbeiterFTE[[Jahr]:[Jahr]],CE10,MitarbeiterFTE[[Vorhaben]:[Vorhaben]],CE75),2) -> 0 | CF12: =ROUND(SUMIFS(MitarbeiterFTE[[Kosten]:[Kosten]],MitarbeiterFTE[[Jahr]:[Jahr]],CF10,MitarbeiterFTE[[Vorhaben]:[Vorhaben]],CF75),2) -> 0 | CG12: 0 | CH12: =ROUND(SUMIFS(MitarbeiterFTE[[Kosten]:[Kosten]],MitarbeiterFTE[[Jahr]:[Jahr]],CH10,MitarbeiterFTE[[Vorhaben]:[Vorhaben]],CH75),2) -> 0 | CI12: =ROUND(SUMIFS(MitarbeiterFTE[[Kosten]:[Kosten]],MitarbeiterFTE[[Jahr]:[Jahr]],CI10,MitarbeiterFTE[[Vorhaben]:[Vorhaben]],CI75),2) -> 0 | CJ12: =ROUND(SUMIFS(MitarbeiterFTE[[Kosten]:[Kosten]],MitarbeiterFTE[[Jahr]:[Jahr]],CJ10,MitarbeiterFTE[[Vorhaben]:[Vorhaben]],CJ75),2) -> 0
B13: Aufschlag für Puffer [%] | C13: =_xlfn.LET( _xlpm.aktuellesJahrt,YEAR(TODAY()), IF(C10<_xlpm.aktuellesJahrt,0,IF(C10=_xlpm.aktuellesJahrt,15,IF(C10>_xlpm.aktuellesJahrt,30))) ) -> 0 | D13: =_xlfn.LET( _xlpm.aktuellesJahrt,YEAR(TODAY()), IF(D10<_xlpm.aktuellesJahrt,0,IF(D10=_xlpm.aktuellesJahrt,15,IF(D10>_xlpm.aktuellesJahrt,30))) ) -> 0 | E13: {=_xlfn.LET( _xlpm.aktuellesJahrt,YEAR(TODAY()), IF(E10<_xlpm.aktuellesJahrt,0,IF(E10=_xlpm.aktuellesJahrt,15,IF(E10>_xlpm.aktuellesJahrt,30))) )} -> 0 | F13: 0 | G13: 5 | H13: 5 | I13: 5 | J13: 5 | O13: Aufschlag für Puffer [%] | P13: =_xlfn.LET( _xlpm.aktuellesJahrt,YEAR(TODAY()), IF(P10<_xlpm.aktuellesJahrt,0,IF(P10=_xlpm.aktuellesJahrt,15,IF(P10>_xlpm.aktuellesJahrt,30))) ) -> 0 | Q13: =_xlfn.LET( _xlpm.aktuellesJahrt,YEAR(TODAY()), IF(Q10<_xlpm.aktuellesJahrt,0,IF(Q10=_xlpm.aktuellesJahrt,15,IF(Q10>_xlpm.aktuellesJahrt,30))) ) -> 0 | R13: =_xlfn.LET( _xlpm.aktuellesJahrt,YEAR(TODAY()), IF(R10<_xlpm.aktuellesJahrt,0,IF(R10=_xlpm.aktuellesJahrt,15,IF(R10>_xlpm.aktuellesJahrt,30))) ) -> 0 | S13: 5 | T13: 5 | U13: 5 | V13: 5 | W13: 5 | AB13: Aufschlag für Puffer [%] | AC13: =_xlfn.LET( _xlpm.aktuellesJahrt,YEAR(TODAY()), IF(AC10<_xlpm.aktuellesJahrt,0,IF(AC10=_xlpm.aktuellesJahrt,15,IF(AC10>_xlpm.aktuellesJahrt,30))) ) -> 0 | AD13: =_xlfn.LET( _xlpm.aktuellesJahrt,YEAR(TODAY()), IF(AD10<_xlpm.aktuellesJahrt,0,IF(AD10=_xlpm.aktuellesJahrt,15,IF(AD10>_xlpm.aktuellesJahrt,30))) ) -> 0 | AE13: =_xlfn.LET( _xlpm.aktuellesJahrt,YEAR(TODAY()), IF(AE10<_xlpm.aktuellesJahrt,0,IF(AE10=_xlpm.aktuellesJahrt,15,IF(AE10>_xlpm.aktuellesJahrt,30))) ) -> 0 | AF13: 5 | AG13: 5 | AH13: 5 | AI13: 5 | AJ13: 5 | AO13: Aufschlag für Puffer [%] | AP13: =_xlfn.LET( _xlpm.aktuellesJahrt,YEAR(TODAY()), IF(AP10<_xlpm.aktuellesJahrt,0,IF(AP10=_xlpm.aktuellesJahrt,15,IF(AP10>_xlpm.aktuellesJahrt,30))) ) -> 0 | AQ13: =_xlfn.LET( _xlpm.aktuellesJahrt,YEAR(TODAY()), IF(AQ10<_xlpm.aktuellesJahrt,0,IF(AQ10=_xlpm.aktuellesJahrt,15,IF(AQ10>_xlpm.aktuellesJahrt,30))) ) -> 0 | AR13: =_xlfn.LET( _xlpm.aktuellesJahrt,YEAR(TODAY()), IF(AR10<_xlpm.aktuellesJahrt,0,IF(AR10=_xlpm.aktuellesJahrt,15,IF(AR10>_xlpm.aktuellesJahrt,30))) ) -> 0 | AS13: 5 | AT13: 5 | AU13: 5 | AV13: 5 | AW13: 5 | BB13: Aufschlag für Puffer [%] | BC13: =_xlfn.LET( _xlpm.aktuellesJahrt,YEAR(TODAY()), IF(BC10<_xlpm.aktuellesJahrt,0,IF(BC10=_xlpm.aktuellesJahrt,15,IF(BC10>_xlpm.aktuellesJahrt,30))) ) -> 0 | BD13: =_xlfn.LET( _xlpm.aktuellesJahrt,YEAR(TODAY()), IF(BD10<_xlpm.aktuellesJahrt,0,IF(BD10=_xlpm.aktuellesJahrt,15,IF(BD10>_xlpm.aktuellesJahrt,30))) ) -> 0 | BE13: =_xlfn.LET( _xlpm.aktuellesJahrt,YEAR(TODAY()), IF(BE10<_xlpm.aktuellesJahrt,0,IF(BE10=_xlpm.aktuellesJahrt,15,IF(BE10>_xlpm.aktuellesJahrt,30))) ) -> 0 | BF13: 5 | BG13: 5 | BH13: 5 | BI13: 5 | BJ13: 5 | BO13: Aufschlag für Puffer [%] | BP13: =_xlfn.LET( _xlpm.aktuellesJahrt,YEAR(TODAY()), IF(BP10<_xlpm.aktuellesJahrt,0,IF(BP10=_xlpm.aktuellesJahrt,15,IF(BP10>_xlpm.aktuellesJahrt,30))) ) -> 0 | BQ13: =_xlfn.LET( _xlpm.aktuellesJahrt,YEAR(TODAY()), IF(BQ10<_xlpm.aktuellesJahrt,0,IF(BQ10=_xlpm.aktuellesJahrt,15,IF(BQ10>_xlpm.aktuellesJahrt,30))) ) -> 0 | BR13: =_xlfn.LET( _xlpm.aktuellesJahrt,YEAR(TODAY()), IF(BR10<_xlpm.aktuellesJahrt,0,IF(BR10=_xlpm.aktuellesJahrt,15,IF(BR10>_xlpm.aktuellesJahrt,30))) ) -> 0 | BS13: 5 | BT13: 5 | BU13: 5 | BV13: 5 | BW13: 5 | CB13: Aufschlag für Puffer [%] | CC13: =_xlfn.LET( _xlpm.aktuellesJahrt,YEAR(TODAY()), IF(CC10<_xlpm.aktuellesJahrt,0,IF(CC10=_xlpm.aktuellesJahrt,15,IF(CC10>_xlpm.aktuellesJahrt,30))) ) -> 0 | CD13: =_xlfn.LET( _xlpm.aktuellesJahrt,YEAR(TODAY()), IF(CD10<_xlpm.aktuellesJahrt,0,IF(CD10=_xlpm.aktuellesJahrt,15,IF(CD10>_xlpm.aktuellesJahrt,30))) ) -> 0 | CE13: =_xlfn.LET( _xlpm.aktuellesJahrt,YEAR(TODAY()), IF(CE10<_xlpm.aktuellesJahrt,0,IF(CE10=_xlpm.aktuellesJahrt,15,IF(CE10>_xlpm.aktuellesJahrt,30))) ) -> 0 | CF13: 5 | CG13: 5 | CH13: 5 | CI13: 5 | CJ13: 5
B14: Kosten aus Eigenleistung [€] (nur bei Einzelunternehmen und Personengesellschaft) | C14: =C15*(IF(C10<2025,40,IF(C10<2026,70,100))) -> 0 | D14: =D15*(IF(D10<2025,40,IF(D10<2026,70,100))) -> 0 | E14: =E15*(IF(E10<2025,40,IF(E10<2026,70,100))) -> 0 | F14: =F15*(IF(F10<2025,40,IF(F10<2026,70,100))) -> 0 | G14: =G15*(IF(G10<2025,40,IF(G10<2026,70,100))) -> 42000 | H14: =H15*(IF(H10<2025,40,IF(H10<2026,70,100))) -> 104000 | I14: =I15*(IF(I10<2025,40,IF(I10<2026,70,100))) -> 104000 | J14: =J15*(IF(J10<2025,40,IF(J10<2026,70,100))) -> 0 | O14: Personalkosten Einzelunternehmen | P14: =P15*(IF(P10<2025,40,IF(P10<2026,70,100))) -> 0 | Q14: =Q15*(IF(Q10<2025,40,IF(Q10<2026,70,100))) -> 0 | R14: =R15*(IF(R10<2025,40,IF(R10<2026,70,100))) -> 0 | S14: =S15*(IF(S10<2025,40,IF(S10<2026,70,100))) -> 0 | T14: =T15*(IF(T10<2025,40,IF(T10<2026,70,100))) -> 0 | U14: =U15*(IF(U10<2025,40,IF(U10<2026,70,100))) -> 0 | V14: =V15*(IF(V10<2025,40,IF(V10<2026,70,100))) -> 0 | W14: =W15*(IF(W10<2025,40,IF(W10<2026,70,100))) -> 0 | AB14: Personalkosten Einzelunternehmen | AC14: =AC15*(IF(AC10<2025,40,IF(AC10<2026,70,100))) -> 0 | AD14: =AD15*(IF(AD10<2025,40,IF(AD10<2026,70,100))) -> 0 | AE14: =AE15*(IF(AE10<2025,40,IF(AE10<2026,70,100))) -> 0 | AF14: =AF15*(IF(AF10<2025,40,IF(AF10<2026,70,100))) -> 0 | AG14: =AG15*(IF(AG10<2025,40,IF(AG10<2026,70,100))) -> 0 | AH14: =AH15*(IF(AH10<2025,40,IF(AH10<2026,70,100))) -> 0 | AI14: =AI15*(IF(AI10<2025,40,IF(AI10<2026,70,100))) -> 0 | AJ14: =AJ15*(IF(AJ10<2025,40,IF(AJ10<2026,70,100))) -> 0 | AO14: Personalkosten Einzelunternehmen | AP14: =AP15*(IF(AP10<2025,40,IF(AP10<2026,70,100))) -> 0 | AQ14: =AQ15*(IF(AQ10<2025,40,IF(AQ10<2026,70,100))) -> 0 | AR14: =AR15*(IF(AR10<2025,40,IF(AR10<2026,70,100))) -> 0 | AS14: =AS15*(IF(AS10<2025,40,IF(AS10<2026,70,100))) -> 0 | AT14: =AT15*(IF(AT10<2025,40,IF(AT10<2026,70,100))) -> 0 | AU14: =AU15*(IF(AU10<2025,40,IF(AU10<2026,70,100))) -> 0 | AV14: =AV15*(IF(AV10<2025,40,IF(AV10<2026,70,100))) -> 0 | AW14: =AW15*(IF(AW10<2025,40,IF(AW10<2026,70,100))) -> 0 | BB14: Personalkosten Einzelunternehmen | BC14: =BC15*(IF(BC10<2025,40,IF(BC10<2026,70,100))) -> 0 | BD14: =BD15*(IF(BD10<2025,40,IF(BD10<2026,70,100))) -> 0 | BE14: =BE15*(IF(BE10<2025,40,IF(BE10<2026,70,100))) -> 0 | BF14: =BF15*(IF(BF10<2025,40,IF(BF10<2026,70,100))) -> 0 | BG14: =BG15*(IF(BG10<2025,40,IF(BG10<2026,70,100))) -> 0 | BH14: =BH15*(IF(BH10<2025,40,IF(BH10<2026,70,100))) -> 0 | BI14: =BI15*(IF(BI10<2025,40,IF(BI10<2026,70,100))) -> 0 | BJ14: =BJ15*(IF(BJ10<2025,40,IF(BJ10<2026,70,100))) -> 0 | BO14: Personalkosten Einzelunternehmen | BP14: =BP15*(IF(BP10<2025,40,IF(BP10<2026,70,100))) -> 0 | BQ14: =BQ15*(IF(BQ10<2025,40,IF(BQ10<2026,70,100))) -> 0 | BR14: =BR15*(IF(BR10<2025,40,IF(BR10<2026,70,100))) -> 0 | BS14: =BS15*(IF(BS10<2025,40,IF(BS10<2026,70,100))) -> 0 | BT14: =BT15*(IF(BT10<2025,40,IF(BT10<2026,70,100))) -> 0 | BU14: =BU15*(IF(BU10<2025,40,IF(BU10<2026,70,100))) -> 0 | BV14: =BV15*(IF(BV10<2025,40,IF(BV10<2026,70,100))) -> 0 | BW14: =BW15*(IF(BW10<2025,40,IF(BW10<2026,70,100))) -> 0 | CB14: Personalkosten Einzelunternehmen | CC14: =CC15*(IF(CC10<2025,40,IF(CC10<2026,70,100))) -> 0 | CD14: =CD15*(IF(CD10<2025,40,IF(CD10<2026,70,100))) -> 0 | CE14: =CE15*(IF(CE10<2025,40,IF(CE10<2026,70,100))) -> 0 | CF14: =CF15*(IF(CF10<2025,40,IF(CF10<2026,70,100))) -> 0 | CG14: =CG15*(IF(CG10<2025,40,IF(CG10<2026,70,100))) -> 0 | CH14: =CH15*(IF(CH10<2025,40,IF(CH10<2026,70,100))) -> 0 | CI14: =CI15*(IF(CI10<2025,40,IF(CI10<2026,70,100))) -> 0 | CJ14: =CJ15*(IF(CJ10<2025,40,IF(CJ10<2026,70,100))) -> 0
B15: Arbeitsstunden aus Eigenleistung gesamt am Projekt | G15: =100+4*20*4 -> 420 | H15: =52*20 -> 1040 | I15: =52*20 -> 1040 | O15: Arbeitsstunden gesamt am Projekt | AB15: Arbeitsstunden gesamt am Projekt | AO15: Arbeitsstunden gesamt am Projekt | BB15: Arbeitsstunden gesamt am Projekt | BO15: Arbeitsstunden gesamt am Projekt | CB15: Arbeitsstunden gesamt am Projekt
B16: Auftragskosten netto (EU/EWR) [€] | C16: =_xlfn.LET(_xlpm.sum,SUM(C17:C26),IF(C9,_xlpm.sum,0)) -> 0 | D16: =_xlfn.LET(_xlpm.sum,SUM(D17:D26),IF(D9,_xlpm.sum,0)) -> 0 | E16: =_xlfn.LET(_xlpm.sum,SUM(E17:E26),IF(E9,_xlpm.sum,0)) -> 0 | F16: {=_xlfn.LET(_xlpm.sum,SUM(F17:F26),IF(F9,_xlpm.sum,0))} -> 0 | G16: =_xlfn.LET(_xlpm.sum,SUM(G17:G26),IF(G9,_xlpm.sum,0)) -> 0 | H16: =_xlfn.LET(_xlpm.sum,SUM(H17:H26),IF(H9,_xlpm.sum,0)) -> 0 | I16: =_xlfn.LET(_xlpm.sum,SUM(I17:I26),IF(I9,_xlpm.sum,0)) -> 0 | J16: =_xlfn.LET(_xlpm.sum,SUM(J17:J26),IF(J9,_xlpm.sum,0)) -> 0 | O16: Auftragskosten netto (EU/EWR) [€] | P16: =_xlfn.LET(_xlpm.sum,SUM(P17:P26),IF(P9,_xlpm.sum,0)) -> 0 | Q16: =_xlfn.LET(_xlpm.sum,SUM(Q17:Q26),IF(Q9,_xlpm.sum,0)) -> 0 | R16: =_xlfn.LET(_xlpm.sum,SUM(R17:R26),IF(R9,_xlpm.sum,0)) -> 0 | S16: =_xlfn.LET(_xlpm.sum,SUM(S17:S26),IF(S9,_xlpm.sum,0)) -> 0 | T16: =_xlfn.LET(_xlpm.sum,SUM(T17:T26),IF(T9,_xlpm.sum,0)) -> 0 | U16: =_xlfn.LET(_xlpm.sum,SUM(U17:U26),IF(U9,_xlpm.sum,0)) -> 0 | V16: =_xlfn.LET(_xlpm.sum,SUM(V17:V26),IF(V9,_xlpm.sum,0)) -> 0 | W16: =_xlfn.LET(_xlpm.sum,SUM(W17:W26),IF(W9,_xlpm.sum,0)) -> 0 | AB16: Auftragskosten netto (EU/EWR) [€] | AC16: =_xlfn.LET(_xlpm.sum,SUM(AC17:AC26),IF(AC9,_xlpm.sum,0)) -> 0 | AD16: =_xlfn.LET(_xlpm.sum,SUM(AD17:AD26),IF(AD9,_xlpm.sum,0)) -> 0 | AE16: =_xlfn.LET(_xlpm.sum,SUM(AE17:AE26),IF(AE9,_xlpm.sum,0)) -> 0 | AF16: =_xlfn.LET(_xlpm.sum,SUM(AF17:AF26),IF(AF9,_xlpm.sum,0)) -> 0 | AG16: =_xlfn.LET(_xlpm.sum,SUM(AG17:AG26),IF(AG9,_xlpm.sum,0)) -> 0 | AH16: =_xlfn.LET(_xlpm.sum,SUM(AH17:AH26),IF(AH9,_xlpm.sum,0)) -> 0 | AI16: =_xlfn.LET(_xlpm.sum,SUM(AI17:AI26),IF(AI9,_xlpm.sum,0)) -> 0 | AJ16: =_xlfn.LET(_xlpm.sum,SUM(AJ17:AJ26),IF(AJ9,_xlpm.sum,0)) -> 0 | AO16: Auftragskosten netto (EU/EWR) [€] | AP16: =_xlfn.LET(_xlpm.sum,SUM(AP17:AP26),IF(AP9,_xlpm.sum,0)) -> 0 | AQ16: =_xlfn.LET(_xlpm.sum,SUM(AQ17:AQ26),IF(AQ9,_xlpm.sum,0)) -> 0 | AR16: =_xlfn.LET(_xlpm.sum,SUM(AR17:AR26),IF(AR9,_xlpm.sum,0)) -> 0 | AS16: =_xlfn.LET(_xlpm.sum,SUM(AS17:AS26),IF(AS9,_xlpm.sum,0)) -> 0 | AT16: =_xlfn.LET(_xlpm.sum,SUM(AT17:AT26),IF(AT9,_xlpm.sum,0)) -> 0 | AU16: =_xlfn.LET(_xlpm.sum,SUM(AU17:AU26),IF(AU9,_xlpm.sum,0)) -> 0 | AV16: =_xlfn.LET(_xlpm.sum,SUM(AV17:AV26),IF(AV9,_xlpm.sum,0)) -> 0 | AW16: =_xlfn.LET(_xlpm.sum,SUM(AW17:AW26),IF(AW9,_xlpm.sum,0)) -> 0 | BB16: Auftragskosten netto (EU/EWR) [€] | BC16: =_xlfn.LET(_xlpm.sum,SUM(BC17:BC26),IF(BC9,_xlpm.sum,0)) -> 0 | BD16: =_xlfn.LET(_xlpm.sum,SUM(BD17:BD26),IF(BD9,_xlpm.sum,0)) -> 0 | BE16: =_xlfn.LET(_xlpm.sum,SUM(BE17:BE26),IF(BE9,_xlpm.sum,0)) -> 0 | BF16: =_xlfn.LET(_xlpm.sum,SUM(BF17:BF26),IF(BF9,_xlpm.sum,0)) -> 0 | BG16: =_xlfn.LET(_xlpm.sum,SUM(BG17:BG26),IF(BG9,_xlpm.sum,0)) -> 0 | BH16: =_xlfn.LET(_xlpm.sum,SUM(BH17:BH26),IF(BH9,_xlpm.sum,0)) -> 0 | BI16: =_xlfn.LET(_xlpm.sum,SUM(BI17:BI26),IF(BI9,_xlpm.sum,0)) -> 0 | BJ16: =_xlfn.LET(_xlpm.sum,SUM(BJ17:BJ26),IF(BJ9,_xlpm.sum,0)) -> 0 | BO16: Auftragskosten netto (EU/EWR) [€] | BP16: =_xlfn.LET(_xlpm.sum,SUM(BP17:BP26),IF(BP9,_xlpm.sum,0)) -> 0 | BQ16: =_xlfn.LET(_xlpm.sum,SUM(BQ17:BQ26),IF(BQ9,_xlpm.sum,0)) -> 0 | BR16: =_xlfn.LET(_xlpm.sum,SUM(BR17:BR26),IF(BR9,_xlpm.sum,0)) -> 0 | BS16: =_xlfn.LET(_xlpm.sum,SUM(BS17:BS26),IF(BS9,_xlpm.sum,0)) -> 0 | BT16: =_xlfn.LET(_xlpm.sum,SUM(BT17:BT26),IF(BT9,_xlpm.sum,0)) -> 0 | BU16: =_xlfn.LET(_xlpm.sum,SUM(BU17:BU26),IF(BU9,_xlpm.sum,0)) -> 0 | BV16: =_xlfn.LET(_xlpm.sum,SUM(BV17:BV26),IF(BV9,_xlpm.sum,0)) -> 0 | BW16: =_xlfn.LET(_xlpm.sum,SUM(BW17:BW26),IF(BW9,_xlpm.sum,0)) -> 0 | CB16: Auftragskosten netto (EU/EWR) [€] | CC16: =_xlfn.LET(_xlpm.sum,SUM(CC17:CC26),IF(CC9,_xlpm.sum,0)) -> 0 | CD16: =_xlfn.LET(_xlpm.sum,SUM(CD17:CD26),IF(CD9,_xlpm.sum,0)) -> 0 | CE16: =_xlfn.LET(_xlpm.sum,SUM(CE17:CE26),IF(CE9,_xlpm.sum,0)) -> 0 | CF16: =_xlfn.LET(_xlpm.sum,SUM(CF17:CF26),IF(CF9,_xlpm.sum,0)) -> 0 | CG16: =_xlfn.LET(_xlpm.sum,SUM(CG17:CG26),IF(CG9,_xlpm.sum,0)) -> 0 | CH16: =_xlfn.LET(_xlpm.sum,SUM(CH17:CH26),IF(CH9,_xlpm.sum,0)) -> 0 | CI16: =_xlfn.LET(_xlpm.sum,SUM(CI17:CI26),IF(CI9,_xlpm.sum,0)) -> 0 | CJ16: =_xlfn.LET(_xlpm.sum,SUM(CJ17:CJ26),IF(CJ9,_xlpm.sum,0)) -> 0
B17: Auftragnehmer 1 | O17: Auftragnehmer 1 | AB17: Auftragnehmer 1 | AO17: Auftragnehmer 1 | BB17: Auftragnehmer 1 | BO17: Auftragnehmer 1 | CB17: Auftragnehmer 1
B18: Auftragnehmer 2 | O18: Auftragnehmer 2 | AB18: Auftragnehmer 2 | AO18: Auftragnehmer 2 | BB18: Auftragnehmer 2 | BO18: Auftragnehmer 2 | CB18: Auftragnehmer 2
B19: Auftragnehmer 3 | O19: Auftragnehmer 3 | AB19: Auftragnehmer 3 | AO19: Auftragnehmer 3 | BB19: Auftragnehmer 3 | BO19: Auftragnehmer 3 | CB19: Auftragnehmer 3
B20: Auftragnehmer 4 | O20: Auftragnehmer 4 | AB20: Auftragnehmer 4 | AO20: Auftragnehmer 4 | BB20: Auftragnehmer 4 | BO20: Auftragnehmer 4 | CB20: Auftragnehmer 4
B21: Auftragnehmer 5 | O21: Auftragnehmer 5 | AB21: Auftragnehmer 5 | AO21: Auftragnehmer 5 | BB21: Auftragnehmer 5 | BO21: Auftragnehmer 5 | CB21: Auftragnehmer 5
B22: Auftragnehmer 6 | O22: Auftragnehmer 6 | AB22: Auftragnehmer 6 | AO22: Auftragnehmer 6 | BB22: Auftragnehmer 6 | BO22: Auftragnehmer 6 | CB22: Auftragnehmer 6
B23: Auftragnehmer 7 | O23: Auftragnehmer 7 | AB23: Auftragnehmer 7 | AO23: Auftragnehmer 7 | BB23: Auftragnehmer 7 | BO23: Auftragnehmer 7 | CB23: Auftragnehmer 7
B24: Auftragnehmer 8 | O24: Auftragnehmer 8 | AB24: Auftragnehmer 8 | AO24: Auftragnehmer 8 | BB24: Auftragnehmer 8 | BO24: Auftragnehmer 8 | CB24: Auftragnehmer 8
B25: Auftragnehmer 9 | O25: Auftragnehmer 9 | AB25: Auftragnehmer 9 | AO25: Auftragnehmer 9 | BB25: Auftragnehmer 9 | BO25: Auftragnehmer 9 | CB25: Auftragnehmer 9
B26: Auftragnehmer 10 | O26: Auftragnehmer 10 | AB26: Auftragnehmer 10 | AO26: Auftragnehmer 10 | BB26: Auftragnehmer 10 | BO26: Auftragnehmer 10 | CB26: Auftragnehmer 10
B27: Materialkosten netto (nicht förderfähig) [€] | O27: Materialkosten netto (nicht förderfähig) [€] | AB27: Materialkosten netto (nicht förderfähig) [€] | AO27: Materialkosten netto (nicht förderfähig) [€] | BB27: Materialkosten netto (nicht förderfähig) [€] | BO27: Materialkosten netto (nicht förderfähig) [€] | CB27: Materialkosten netto (nicht förderfähig) [€]
B28: Abschreibungswert Sachanlagen (förderfähig ab Projektstart am 28.03.2024) [€] | C28: =SUM(C29:C33) -> 0 | D28: =SUM(D29:D33) -> 0 | E28: =SUM(E29:E33) -> 0 | F28: =SUM(F29:F33) -> 0 | G28: =SUM(G29:G33) -> 0 | H28: =SUM(H29:H33) -> 0 | I28: =SUM(I29:I33) -> 0 | J28: =SUM(J29:J33) -> 0 | O28: Sachanlagen (förderfähig ab 28.03.2024) [€] | P28: =SUM(P29:P33) -> 0 | Q28: =SUM(Q29:Q33) -> 0 | R28: =SUM(R29:R33) -> 0 | S28: =SUM(S29:S33) -> 0 | T28: =SUM(T29:T33) -> 0 | U28: =SUM(U29:U33) -> 0 | V28: =SUM(V29:V33) -> 0 | W28: =SUM(W29:W33) -> 0 | AB28: Sachanlagen (förderfähig ab 28.03.2024) [€] | AC28: =SUM(AC29:AC33) -> 0 | AD28: =SUM(AD29:AD33) -> 0 | AE28: =SUM(AE29:AE33) -> 0 | AF28: =SUM(AF29:AF33) -> 0 | AG28: =SUM(AG29:AG33) -> 0 | AH28: =SUM(AH29:AH33) -> 0 | AI28: =SUM(AI29:AI33) -> 0 | AJ28: =SUM(AJ29:AJ33) -> 0 | AO28: Sachanlagen (förderfähig ab 28.03.2024) [€] | AP28: =SUM(AP29:AP33) -> 0 | AQ28: =SUM(AQ29:AQ33) -> 0 | AR28: =SUM(AR29:AR33) -> 0 | AS28: =SUM(AS29:AS33) -> 0 | AT28: =SUM(AT29:AT33) -> 0 | AU28: =SUM(AU29:AU33) -> 0 | AV28: =SUM(AV29:AV33) -> 0 | AW28: =SUM(AW29:AW33) -> 0 | BB28: Sachanlagen (förderfähig ab 28.03.2024) [€] | BC28: =SUM(BC29:BC33) -> 0 | BD28: =SUM(BD29:BD33) -> 0 | BE28: =SUM(BE29:BE33) -> 0 | BF28: =SUM(BF29:BF33) -> 0 | BG28: =SUM(BG29:BG33) -> 0 | BH28: =SUM(BH29:BH33) -> 0 | BI28: =SUM(BI29:BI33) -> 0 | BJ28: =SUM(BJ29:BJ33) -> 0 | BO28: Sachanlagen (förderfähig ab 28.03.2024) [€] | BP28: =SUM(BP29:BP33) -> 0 | BQ28: =SUM(BQ29:BQ33) -> 0 | BR28: =SUM(BR29:BR33) -> 0 | BS28: =SUM(BS29:BS33) -> 0 | BT28: =SUM(BT29:BT33) -> 0 | BU28: =SUM(BU29:BU33) -> 0 | BV28: =SUM(BV29:BV33) -> 0 | BW28: =SUM(BW29:BW33) -> 0 | CB28: Sachanlagen (förderfähig ab 28.03.2024) [€] | CC28: =SUM(CC29:CC33) -> 0 | CD28: =SUM(CD29:CD33) -> 0 | CE28: =SUM(CE29:CE33) -> 0 | CF28: =SUM(CF29:CF33) -> 0 | CG28: =SUM(CG29:CG33) -> 0 | CH28: =SUM(CH29:CH33) -> 0 | CI28: =SUM(CI29:CI33) -> 0 | CJ28: =SUM(CJ29:CJ33) -> 0
B29: Sachanlage 1 | O29: Sachanlage 1 | AB29: Sachanlage 1 | AO29: Sachanlage 1 | BB29: Sachanlage 1 | BO29: Sachanlage 1 | CB29: Sachanlage 1
B30: Sachanlage 2 | O30: Sachanlage 2 | AB30: Sachanlage 2 | AO30: Sachanlage 2 | BB30: Sachanlage 2 | BO30: Sachanlage 2 | CB30: Sachanlage 2
B31: Sachanlage 3 | O31: Sachanlage 3 | AB31: Sachanlage 3 | AO31: Sachanlage 3 | BB31: Sachanlage 3 | BO31: Sachanlage 3 | CB31: Sachanlage 3
B32: Sachanlage 4 | O32: Sachanlage 4 | AB32: Sachanlage 4 | AO32: Sachanlage 4 | BB32: Sachanlage 4 | BO32: Sachanlage 4 | CB32: Sachanlage 4
B33: Sachanlage 5 | O33: Sachanlage 5 | AB33: Sachanlage 5 | AO33: Sachanlage 5 | BB33: Sachanlage 5 | BO33: Sachanlage 5 | CB33: Sachanlage 5
B34: Gesamtkosten [€] | C34: =C27+C16+C11+C28 -> 0 | D34: =D27+D16+D11+D28 -> 0 | E34: =E27+E16+E11+E28 -> 0 | F34: =F27+F16+F11+F28 -> 0 | G34: =G27+G16+G11+G28 -> 2730 | H34: =H27+H16+H11+H28 -> 8190 | I34: =I27+I16+I11+I28 -> 16380 | J34: =J27+J16+J11+J28 -> 0 | O34: Gesamtkosten [€] | P34: =P27+P16+P11+P28 -> 0 | Q34: =Q27+Q16+Q11+Q28 -> 0 | R34: =R27+R16+R11+R28 -> 0 | S34: =S27+S16+S11+S28 -> 0 | T34: =T27+T16+T11+T28 -> 0 | U34: =U27+U16+U11+U28 -> 0 | V34: =V27+V16+V11+V28 -> 0 | W34: =W27+W16+W11+W28 -> 0 | AB34: Gesamtkosten [€] | AC34: =AC27+AC16+AC11+AC28 -> 0 | AD34: =AD27+AD16+AD11+AD28 -> 0 | AE34: =AE27+AE16+AE11+AE28 -> 0 | AF34: =AF27+AF16+AF11+AF28 -> 0 | AG34: =AG27+AG16+AG11+AG28 -> 0 | AH34: =AH27+AH16+AH11+AH28 -> 0 | AI34: =AI27+AI16+AI11+AI28 -> 0 | AJ34: =AJ27+AJ16+AJ11+AJ28 -> 0 | AO34: Gesamtkosten [€] | AP34: =AP27+AP16+AP11+AP28 -> 0 | AQ34: =AQ27+AQ16+AQ11+AQ28 -> 0 | AR34: =AR27+AR16+AR11+AR28 -> 0 | AS34: =AS27+AS16+AS11+AS28 -> 0 | AT34: =AT27+AT16+AT11+AT28 -> 0 | AU34: =AU27+AU16+AU11+AU28 -> 0 | AV34: =AV27+AV16+AV11+AV28 -> 0 | AW34: =AW27+AW16+AW11+AW28 -> 0 | BB34: Gesamtkosten [€] | BC34: =BC27+BC16+BC11+BC28 -> 0 | BD34: =BD27+BD16+BD11+BD28 -> 0 | BE34: =BE27+BE16+BE11+BE28 -> 0 | BF34: =BF27+BF16+BF11+BF28 -> 0 | BG34: =BG27+BG16+BG11+BG28 -> 0 | BH34: =BH27+BH16+BH11+BH28 -> 0 | BI34: =BI27+BI16+BI11+BI28 -> 0 | BJ34: =BJ27+BJ16+BJ11+BJ28 -> 0 | BO34: Gesamtkosten [€] | BP34: =BP27+BP16+BP11+BP28 -> 0 | BQ34: =BQ27+BQ16+BQ11+BQ28 -> 0 | BR34: =BR27+BR16+BR11+BR28 -> 0 | BS34: =BS27+BS16+BS11+BS28 -> 0 | BT34: =BT27+BT16+BT11+BT28 -> 0 | BU34: =BU27+BU16+BU11+BU28 -> 0 | BV34: =BV27+BV16+BV11+BV28 -> 0 | BW34: =BW27+BW16+BW11+BW28 -> 0 | CB34: Gesamtkosten [€] | CC34: =CC27+CC16+CC11+CC28 -> 0 | CD34: =CD27+CD16+CD11+CD28 -> 0 | CE34: =CE27+CE16+CE11+CE28 -> 0 | CF34: =CF27+CF16+CF11+CF28 -> 0 | CG34: =CG27+CG16+CG11+CG28 -> 0 | CH34: =CH27+CH16+CH11+CH28 -> 0 | CI34: =CI27+CI16+CI11+CI28 -> 0 | CJ34: =CJ27+CJ16+CJ11+CJ28 -> 0
B35: Wurden/Werden die Personalkosten und/oder Auftragskosten für Aufträge innerhalb der EU/des EWR für dieses FuE-Vorhaben im Rahmen anderer Förderungen oder staatlicher Beihilfen gefördert? | E35: nein | G35: nein | H35: nein | I35: nein | O35: Wurden/Werden die Personalkosten und/oder Auftragskosten für Aufträge innerhalb der EU/des EWR für dieses FuE-Vorhaben im Rahmen anderer Förderungen oder staatlicher Beihilfen gefördert? | AB35: Wurden/Werden die Personalkosten und/oder Auftragskosten für Aufträge innerhalb der EU/des EWR für dieses FuE-Vorhaben im Rahmen anderer Förderungen oder staatlicher Beihilfen gefördert? | AO35: Wurden/Werden die Personalkosten und/oder Auftragskosten für Aufträge innerhalb der EU/des EWR für dieses FuE-Vorhaben im Rahmen anderer Förderungen oder staatlicher Beihilfen gefördert? | BB35: Wurden/Werden die Personalkosten und/oder Auftragskosten für Aufträge innerhalb der EU/des EWR für dieses FuE-Vorhaben im Rahmen anderer Förderungen oder staatlicher Beihilfen gefördert? | BO35: Wurden/Werden die Personalkosten und/oder Auftragskosten für Aufträge innerhalb der EU/des EWR für dieses FuE-Vorhaben im Rahmen anderer Förderungen oder staatlicher Beihilfen gefördert? | CB35: Wurden/Werden die Personalkosten und/oder Auftragskosten für Aufträge innerhalb der EU/des EWR für dieses FuE-Vorhaben im Rahmen anderer Förderungen oder staatlicher Beihilfen gefördert?
B36: Öffentliche Förderungen für dieses FuE-Vorhaben [€] | K36: Summe | O36: Öffentliche Förderungen für dieses FuE-Vorhaben [€] | X36: Summe | AB36: Öffentliche Förderungen für dieses FuE-Vorhaben [€] | AK36: Summe | AO36: Öffentliche Förderungen für dieses FuE-Vorhaben [€] | AX36: Summe | BB36: Öffentliche Förderungen für dieses FuE-Vorhaben [€] | BK36: Summe | BO36: Öffentliche Förderungen für dieses FuE-Vorhaben [€] | BX36: Summe | CB36: Öffentliche Förderungen für dieses FuE-Vorhaben [€] | CK36: Summe
B37: Gesamtkosten | C37: =IF(C9,C11+C14+C16,0) -> 0 | D37: =IF(D9,D11+D14+D16,0) -> 0 | E37: =IF(E9,E11+E14+E16,0) -> 0 | F37: =IF(F9,F11+F14+F16,0) -> 0 | G37: =IF(G9,G11+G14+G16,0) -> 44730 | H37: =IF(H9,H11+H14+H16,0) -> 112190 | I37: =IF(I9,I11+I14+I16,0) -> 120380 | J37: =IF(J9,J11+J14+J16+J28,0) -> 0 | K37: =SUM(C37:J37) -> 277300 | O37: Gesamtkosten | P37: =IF(P9,P11+P14+P16,0) -> 0 | Q37: =IF(Q9,Q11+Q14+Q16,0) -> 0 | R37: =IF(R9,R11+R14+R16,0) -> 0 | S37: =IF(S9,S11+S14+S16,0) -> 0 | T37: =IF(T9,T11+T14+T16,0) -> 0 | U37: =IF(U9,U11+U14+U16,0) -> 0 | V37: =IF(V9,V11+V14+V16,0) -> 0 | W37: =IF(W9,W11+W14+W16+W28,0) -> 0 | X37: =SUM(P37:W37) -> 0 | AB37: Gesamtkosten | AC37: =IF(AC9,AC11+AC14+AC16,0) -> 0 | AD37: =IF(AD9,AD11+AD14+AD16,0) -> 0 | AE37: =IF(AE9,AE11+AE14+AE16,0) -> 0 | AF37: =IF(AF9,AF11+AF14+AF16,0) -> 0 | AG37: =IF(AG9,AG11+AG14+AG16,0) -> 0 | AH37: =IF(AH9,AH11+AH14+AH16,0) -> 0 | AI37: =IF(AI9,AI11+AI14+AI16,0) -> 0 | AJ37: =IF(AJ9,AJ11+AJ14+AJ16+AJ28,0) -> 0 | AK37: =SUM(AC37:AJ37) -> 0 | AO37: Gesamtkosten | AP37: =IF(AP9,AP11+AP14+AP16,0) -> 0 | AQ37: =IF(AQ9,AQ11+AQ14+AQ16,0) -> 0 | AR37: =IF(AR9,AR11+AR14+AR16,0) -> 0 | AS37: =IF(AS9,AS11+AS14+AS16,0) -> 0 | AT37: =IF(AT9,AT11+AT14+AT16,0) -> 0 | AU37: =IF(AU9,AU11+AU14+AU16,0) -> 0 | AV37: =IF(AV9,AV11+AV14+AV16,0) -> 0 | AW37: =IF(AW9,AW11+AW14+AW16+AW28,0) -> 0 | AX37: =SUM(AP37:AW37) -> 0 | BB37: Gesamtkosten | BC37: =IF(BC9,BC11+BC14+BC16,0) -> 0 | BD37: =IF(BD9,BD11+BD14+BD16,0) -> 0 | BE37: =IF(BE9,BE11+BE14+BE16,0) -> 0 | BF37: =IF(BF9,BF11+BF14+BF16,0) -> 0 | BG37: =IF(BG9,BG11+BG14+BG16,0) -> 0 | BH37: =IF(BH9,BH11+BH14+BH16,0) -> 0 | BI37: =IF(BI9,BI11+BI14+BI16,0) -> 0 | BJ37: =IF(BJ9,BJ11+BJ14+BJ16+BJ28,0) -> 0 | BK37: =SUM(BC37:BJ37) -> 0 | BO37: Gesamtkosten | BP37: =IF(BP9,BP11+BP14+BP16,0) -> 0 | BQ37: =IF(BQ9,BQ11+BQ14+BQ16,0) -> 0 | BR37: =IF(BR9,BR11+BR14+BR16,0) -> 0 | BS37: =IF(BS9,BS11+BS14+BS16,0) -> 0 | BT37: =IF(BT9,BT11+BT14+BT16,0) -> 0 | BU37: =IF(BU9,BU11+BU14+BU16,0) -> 0 | BV37: =IF(BV9,BV11+BV14+BV16,0) -> 0 | BW37: =IF(BW9,BW11+BW14+BW16+BW28,0) -> 0 | BX37: =SUM(BP37:BW37) -> 0 | CB37: Gesamtkosten | CC37: =IF(CC9,CC11+CC14+CC16,0) -> 0 | CD37: =IF(CD9,CD11+CD14+CD16,0) -> 0 | CE37: =IF(CE9,CE11+CE14+CE16,0) -> 0 | CF37: =IF(CF9,CF11+CF14+CF16,0) -> 0 | CG37: =IF(CG9,CG11+CG14+CG16,0) -> 0 | CH37: =IF(CH9,CH11+CH14+CH16,0) -> 0 | CI37: =IF(CI9,CI11+CI14+CI16,0) -> 0 | CJ37: =IF(CJ9,CJ11+CJ14+CJ16+CJ28,0) -> 0 | CK37: =SUM(CC37:CJ37) -> 0
B38: Anteil förderfähiger Auftragnehmerkosten | C38: =IF(C7>=DATE(2024,3,27),70%,60%) -> 0.7 | D38: =IF(C7>=DATE(2024,3,27),70%,60%) -> 0.7 | E38: =IF(C7>=DATE(2024,3,27),70%,60%) -> 0.7 | F38: =IF(C7>=DATE(2024,3,27),70%,60%) -> 0.7 | G38: =IF(C7>=DATE(2024,3,27),70%,60%) -> 0.7 | H38: =IF(C7>=DATE(2024,3,27),70%,60%) -> 0.7 | I38: =IF(C7>=DATE(2024,3,27),70%,60%) -> 0.7 | J38: =IF(C7>=DATE(2024,3,27),70%,60%) -> 0.7 | O38: Anteil förderfähiger Auftragnehmerkosten | P38: =IF(P7>=DATE(2024,3,27),70%,60%) -> 0.7 | Q38: =IF(P7>=DATE(2024,3,27),70%,60%) -> 0.7 | R38: =IF(P7>=DATE(2024,3,27),70%,60%) -> 0.7 | S38: =IF(P7>=DATE(2024,3,27),70%,60%) -> 0.7 | T38: =IF(P7>=DATE(2024,3,27),70%,60%) -> 0.7 | U38: =IF(P7>=DATE(2024,3,27),70%,60%) -> 0.7 | V38: =IF(P7>=DATE(2024,3,27),70%,60%) -> 0.7 | W38: =IF(P7>=DATE(2024,3,27),70%,60%) -> 0.7 | AB38: Anteil förderfähiger Auftragnehmerkosten | AC38: =IF(AC7>=DATE(2024,3,27),70%,60%) -> 0.7 | AD38: =IF(AC7>=DATE(2024,3,27),70%,60%) -> 0.7 | AE38: =IF(AC7>=DATE(2024,3,27),70%,60%) -> 0.7 | AF38: =IF(AC7>=DATE(2024,3,27),70%,60%) -> 0.7 | AG38: =IF(AC7>=DATE(2024,3,27),70%,60%) -> 0.7 | AH38: =IF(AC7>=DATE(2024,3,27),70%,60%) -> 0.7 | AI38: =IF(AC7>=DATE(2024,3,27),70%,60%) -> 0.7 | AJ38: =IF(AC7>=DATE(2024,3,27),70%,60%) -> 0.7 | AO38: Anteil förderfähiger Auftragnehmerkosten | AP38: =IF(AP7>=DATE(2024,3,27),70%,60%) -> 0.7 | AQ38: =IF(AP7>=DATE(2024,3,27),70%,60%) -> 0.7 | AR38: =IF(AP7>=DATE(2024,3,27),70%,60%) -> 0.7 | AS38: =IF(AP7>=DATE(2024,3,27),70%,60%) -> 0.7 | AT38: =IF(AP7>=DATE(2024,3,27),70%,60%) -> 0.7 | AU38: =IF(AP7>=DATE(2024,3,27),70%,60%) -> 0.7 | AV38: =IF(AP7>=DATE(2024,3,27),70%,60%) -> 0.7 | AW38: =IF(AP7>=DATE(2024,3,27),70%,60%) -> 0.7 | BB38: Anteil förderfähiger Auftragnehmerkosten | BC38: =IF(BC7>=DATE(2024,3,27),70%,60%) -> 0.7 | BD38: =IF(BC7>=DATE(2024,3,27),70%,60%) -> 0.7 | BE38: =IF(BC7>=DATE(2024,3,27),70%,60%) -> 0.7 | BF38: =IF(BC7>=DATE(2024,3,27),70%,60%) -> 0.7 | BG38: =IF(BC7>=DATE(2024,3,27),70%,60%) -> 0.7 | BH38: =IF(BC7>=DATE(2024,3,27),70%,60%) -> 0.7 | BI38: =IF(BC7>=DATE(2024,3,27),70%,60%) -> 0.7 | BJ38: =IF(BC7>=DATE(2024,3,27),70%,60%) -> 0.7 | BO38: Anteil förderfähiger Auftragnehmerkosten | BP38: =IF(BP7>=DATE(2024,3,27),70%,60%) -> 0.7 | BQ38: =IF(BP7>=DATE(2024,3,27),70%,60%) -> 0.7 | BR38: =IF(BP7>=DATE(2024,3,27),70%,60%) -> 0.7 | BS38: =IF(BP7>=DATE(2024,3,27),70%,60%) -> 0.7 | BT38: =IF(BP7>=DATE(2024,3,27),70%,60%) -> 0.7 | BU38: =IF(BP7>=DATE(2024,3,27),70%,60%) -> 0.7 | BV38: =IF(BP7>=DATE(2024,3,27),70%,60%) -> 0.7 | BW38: =IF(BP7>=DATE(2024,3,27),70%,60%) -> 0.7 | CB38: Anteil förderfähiger Auftragnehmerkosten | CC38: =IF(CC7>=DATE(2024,3,27),70%,60%) -> 0.7 | CD38: =IF(CC7>=DATE(2024,3,27),70%,60%) -> 0.7 | CE38: =IF(CC7>=DATE(2024,3,27),70%,60%) -> 0.7 | CF38: =IF(CC7>=DATE(2024,3,27),70%,60%) -> 0.7 | CG38: =IF(CC7>=DATE(2024,3,27),70%,60%) -> 0.7 | CH38: =IF(CC7>=DATE(2024,3,27),70%,60%) -> 0.7 | CI38: =IF(CC7>=DATE(2024,3,27),70%,60%) -> 0.7 | CJ38: =IF(CC7>=DATE(2024,3,27),70%,60%) -> 0.7
B39: Förderfähige Projektkosten | C39: =IF(C9,C11+C14+C16*C38,0) -> 0 | D39: =IF(D9,D11+D14+D16*D38,0) -> 0 | E39: =IF(E9,E11+E14+E16*E38+E28,0) -> 0 | F39: =IF(F9,F11+F14+F16*F38+F28,0) -> 0 | G39: =IF(G9,G11+G14+G16*G38+G28,0) -> 44730 | H39: =IF(H9,H11+H14+H16*H38+H28,0) -> 112190 | I39: =IF(I9,I11+I14+I16*I38+I28,0) -> 120380 | J39: =IF(J9,J11+J14+J16*J38+J28,0) -> 0 | O39: Förderfähige Projektkosten | P39: =IF(P9,P11+P14+P16*P38,0) -> 0 | Q39: =IF(Q9,Q11+Q14+Q16*Q38,0) -> 0 | R39: =IF(R9,R11+R14+R16*R38+R28,0) -> 0 | S39: =IF(S9,S11+S14+S16*S38+S28,0) -> 0 | T39: =IF(T9,T11+T14+T16*T38+T28,0) -> 0 | U39: =IF(U9,U11+U14+U16*U38+U28,0) -> 0 | V39: =IF(V9,V11+V14+V16*V38+V28,0) -> 0 | W39: =IF(W9,W11+W14+W16*W38+W28,0) -> 0 | AB39: Förderfähige Projektkosten | AC39: =IF(AC9,AC11+AC14+AC16*AC38,0) -> 0 | AD39: =IF(AD9,AD11+AD14+AD16*AD38,0) -> 0 | AE39: =IF(AE9,AE11+AE14+AE16*AE38+AE28,0) -> 0 | AF39: =IF(AF9,AF11+AF14+AF16*AF38+AF28,0) -> 0 | AG39: =IF(AG9,AG11+AG14+AG16*AG38+AG28,0) -> 0 | AH39: =IF(AH9,AH11+AH14+AH16*AH38+AH28,0) -> 0 | AI39: =IF(AI9,AI11+AI14+AI16*AI38+AI28,0) -> 0 | AJ39: =IF(AJ9,AJ11+AJ14+AJ16*AJ38+AJ28,0) -> 0 | AO39: Förderfähige Projektkosten | AP39: =IF(AP9,AP11+AP14+AP16*AP38,0) -> 0 | AQ39: =IF(AQ9,AQ11+AQ14+AQ16*AQ38,0) -> 0 | AR39: =IF(AR9,AR11+AR14+AR16*AR38+AR28,0) -> 0 | AS39: =IF(AS9,AS11+AS14+AS16*AS38+AS28,0) -> 0 | AT39: =IF(AT9,AT11+AT14+AT16*AT38+AT28,0) -> 0 | AU39: =IF(AU9,AU11+AU14+AU16*AU38+AU28,0) -> 0 | AV39: =IF(AV9,AV11+AV14+AV16*AV38+AV28,0) -> 0 | AW39: =IF(AW9,AW11+AW14+AW16*AW38+AW28,0) -> 0 | BB39: Förderfähige Projektkosten | BC39: =IF(BC9,BC11+BC14+BC16*BC38,0) -> 0 | BD39: =IF(BD9,BD11+BD14+BD16*BD38,0) -> 0 | BE39: =IF(BE9,BE11+BE14+BE16*BE38+BE28,0) -> 0 | BF39: =IF(BF9,BF11+BF14+BF16*BF38+BF28,0) -> 0 | BG39: =IF(BG9,BG11+BG14+BG16*BG38+BG28,0) -> 0 | BH39: =IF(BH9,BH11+BH14+BH16*BH38+BH28,0) -> 0 | BI39: =IF(BI9,BI11+BI14+BI16*BI38+BI28,0) -> 0 | BJ39: =IF(BJ9,BJ11+BJ14+BJ16*BJ38+BJ28,0) -> 0 | BO39: Förderfähige Projektkosten | BP39: =IF(BP9,BP11+BP14+BP16*BP38,0) -> 0 | BQ39: =IF(BQ9,BQ11+BQ14+BQ16*BQ38,0) -> 0 | BR39: =IF(BR9,BR11+BR14+BR16*BR38+BR28,0) -> 0 | BS39: =IF(BS9,BS11+BS14+BS16*BS38+BS28,0) -> 0 | BT39: =IF(BT9,BT11+BT14+BT16*BT38+BT28,0) -> 0 | BU39: =IF(BU9,BU11+BU14+BU16*BU38+BU28,0) -> 0 | BV39: =IF(BV9,BV11+BV14+BV16*BV38+BV28,0) -> 0 | BW39: =IF(BW9,BW11+BW14+BW16*BW38+BW28,0) -> 0 | CB39: Förderfähige Projektkosten | CC39: =IF(CC9,CC11+CC14+CC16*CC38,0) -> 0 | CD39: =IF(CD9,CD11+CD14+CD16*CD38,0) -> 0 | CE39: =IF(CE9,CE11+CE14+CE16*CE38+CE28,0) -> 0 | CF39: =IF(CF9,CF11+CF14+CF16*CF38+CF28,0) -> 0 | CG39: =IF(CG9,CG11+CG14+CG16*CG38+CG28,0) -> 0 | CH39: =IF(CH9,CH11+CH14+CH16*CH38+CH28,0) -> 0 | CI39: =IF(CI9,CI11+CI14+CI16*CI38+CI28,0) -> 0 | CJ39: =IF(CJ9,CJ11+CJ14+CJ16*CJ38+CJ28,0) -> 0
B40: Overhead-Kosten (20% d. fördf. Projektkosten; ansetzbar ab Projektstart am 01.01.2026) | C40: =IF(C7>=DATE(2026,1,1),C39*20%,0) -> 0 | D40: =IF(C7>=DATE(2026,1,1),D39*20%,0) -> 0 | E40: =IF(C7>=DATE(2026,1,1),E39*20%,0) -> 0 | F40: =IF(C7>=DATE(2026,1,1),F39*20%,0) -> 0 | G40: =IF(C7>=DATE(2026,1,1),G39*20%,0) -> 8946 | H40: =IF(C7>=DATE(2026,1,1),H39*20%,0) -> 22438 | I40: =IF(C7>=DATE(2026,1,1),I39*20%,0) -> 24076 | J40: =IF(C7>=DATE(2026,1,1),J39*20%,0) -> 0 | O40: Overhead-Kosten (20% d. fördf. Projektkosten; ansetzbar ab Projektstart am 01.01.2026) | P40: =IF(P7>=DATE(2026,1,1),P39*20%,0) -> 0 | Q40: =IF(P7>=DATE(2026,1,1),Q39*20%,0) -> 0 | R40: =IF(P7>=DATE(2026,1,1),R39*20%,0) -> 0 | S40: =IF(P7>=DATE(2026,1,1),S39*20%,0) -> 0 | T40: =IF(P7>=DATE(2026,1,1),T39*20%,0) -> 0 | U40: =IF(P7>=DATE(2026,1,1),U39*20%,0) -> 0 | V40: =IF(P7>=DATE(2026,1,1),V39*20%,0) -> 0 | W40: =IF(P7>=DATE(2026,1,1),W39*20%,0) -> 0 | AB40: Overhead-Kosten (20% d. fördf. Projektkosten; ansetzbar ab Projektstart am 01.01.2026) | AC40: =IF(AC7>=DATE(2026,1,1),AC39*20%,0) -> 0 | AD40: =IF(AC7>=DATE(2026,1,1),AD39*20%,0) -> 0 | AE40: =IF(AC7>=DATE(2026,1,1),AE39*20%,0) -> 0 | AF40: =IF(AC7>=DATE(2026,1,1),AF39*20%,0) -> 0 | AG40: =IF(AC7>=DATE(2026,1,1),AG39*20%,0) -> 0 | AH40: =IF(AC7>=DATE(2026,1,1),AH39*20%,0) -> 0 | AI40: =IF(AC7>=DATE(2026,1,1),AI39*20%,0) -> 0 | AJ40: =IF(AC7>=DATE(2026,1,1),AJ39*20%,0) -> 0 | AO40: Overhead-Kosten (20% d. fördf. Projektkosten; ansetzbar ab Projektstart am 01.01.2026) | AP40: =IF(AP7>=DATE(2026,1,1),AP39*20%,0) -> 0 | AQ40: =IF(AP7>=DATE(2026,1,1),AQ39*20%,0) -> 0 | AR40: =IF(AP7>=DATE(2026,1,1),AR39*20%,0) -> 0 | AS40: =IF(AP7>=DATE(2026,1,1),AS39*20%,0) -> 0 | AT40: =IF(AP7>=DATE(2026,1,1),AT39*20%,0) -> 0 | AU40: =IF(AP7>=DATE(2026,1,1),AU39*20%,0) -> 0 | AV40: =IF(AP7>=DATE(2026,1,1),AV39*20%,0) -> 0 | AW40: =IF(AP7>=DATE(2026,1,1),AW39*20%,0) -> 0 | BB40: Overhead-Kosten (20% d. fördf. Projektkosten; ansetzbar ab Projektstart am 01.01.2026) | BC40: =IF(BC7>=DATE(2026,1,1),BC39*20%,0) -> 0 | BD40: =IF(BC7>=DATE(2026,1,1),BD39*20%,0) -> 0 | BE40: =IF(BC7>=DATE(2026,1,1),BE39*20%,0) -> 0 | BF40: =IF(BC7>=DATE(2026,1,1),BF39*20%,0) -> 0 | BG40: =IF(BC7>=DATE(2026,1,1),BG39*20%,0) -> 0 | BH40: =IF(BC7>=DATE(2026,1,1),BH39*20%,0) -> 0 | BI40: =IF(BC7>=DATE(2026,1,1),BI39*20%,0) -> 0 | BJ40: =IF(BC7>=DATE(2026,1,1),BJ39*20%,0) -> 0 | BO40: Overhead-Kosten (20% d. fördf. Projektkosten; ansetzbar ab Projektstart am 01.01.2026) | BP40: =IF(BP7>=DATE(2026,1,1),BP39*20%,0) -> 0 | BQ40: =IF(BP7>=DATE(2026,1,1),BQ39*20%,0) -> 0 | BR40: =IF(BP7>=DATE(2026,1,1),BR39*20%,0) -> 0 | BS40: =IF(BP7>=DATE(2026,1,1),BS39*20%,0) -> 0 | BT40: =IF(BP7>=DATE(2026,1,1),BT39*20%,0) -> 0 | BU40: =IF(BP7>=DATE(2026,1,1),BU39*20%,0) -> 0 | BV40: =IF(BP7>=DATE(2026,1,1),BV39*20%,0) -> 0 | BW40: =IF(BP7>=DATE(2026,1,1),BW39*20%,0) -> 0 | CB40: Overhead-Kosten (20% d. fördf. Projektkosten; ansetzbar ab Projektstart am 01.01.2026) | CC40: =IF(CC7>=DATE(2026,1,1),CC39*20%,0) -> 0 | CD40: =IF(CC7>=DATE(2026,1,1),CD39*20%,0) -> 0 | CE40: =IF(CC7>=DATE(2026,1,1),CE39*20%,0) -> 0 | CF40: =IF(CC7>=DATE(2026,1,1),CF39*20%,0) -> 0 | CG40: =IF(CC7>=DATE(2026,1,1),CG39*20%,0) -> 0 | CH40: =IF(CC7>=DATE(2026,1,1),CH39*20%,0) -> 0 | CI40: =IF(CC7>=DATE(2026,1,1),CI39*20%,0) -> 0 | CJ40: =IF(CC7>=DATE(2026,1,1),CJ39*20%,0) -> 0
B41: Förderfähige Gesamtprojektkosten | C41: =C39+C40 -> 0 | D41: =D39+D40 -> 0 | E41: =E39+E40 -> 0 | F41: =F39+F40 -> 0 | G41: =G39+G40 -> 53676 | H41: =H39+H40 -> 134628 | I41: =I39+I40 -> 144456 | J41: =J39+J40 -> 0 | K41: =SUM(C41:J41) -> 332760 | O41: Förderfähige Gesamtprojektkosten | P41: =P39+P40 -> 0 | Q41: =Q39+Q40 -> 0 | R41: =R39+R40 -> 0 | S41: =S39+S40 -> 0 | T41: =T39+T40 -> 0 | U41: =U39+U40 -> 0 | V41: =V39+V40 -> 0 | W41: =W39+W40 -> 0 | X41: =SUM(P41:W41) -> 0 | AB41: Förderfähige Gesamtprojektkosten | AC41: =AC39+AC40 -> 0 | AD41: =AD39+AD40 -> 0 | AE41: =AE39+AE40 -> 0 | AF41: =AF39+AF40 -> 0 | AG41: =AG39+AG40 -> 0 | AH41: =AH39+AH40 -> 0 | AI41: =AI39+AI40 -> 0 | AJ41: =AJ39+AJ40 -> 0 | AK41: =SUM(AC41:AJ41) -> 0 | AO41: Förderfähige Gesamtprojektkosten | AP41: =AP39+AP40 -> 0 | AQ41: =AQ39+AQ40 -> 0 | AR41: =AR39+AR40 -> 0 | AS41: =AS39+AS40 -> 0 | AT41: =AT39+AT40 -> 0 | AU41: =AU39+AU40 -> 0 | AV41: =AV39+AV40 -> 0 | AW41: =AW39+AW40 -> 0 | AX41: =SUM(AP41:AW41) -> 0 | BB41: Förderfähige Gesamtprojektkosten | BC41: =BC39+BC40 -> 0 | BD41: =BD39+BD40 -> 0 | BE41: =BE39+BE40 -> 0 | BF41: =BF39+BF40 -> 0 | BG41: =BG39+BG40 -> 0 | BH41: =BH39+BH40 -> 0 | BI41: =BI39+BI40 -> 0 | BJ41: =BJ39+BJ40 -> 0 | BK41: =SUM(BC41:BJ41) -> 0 | BO41: Förderfähige Gesamtprojektkosten | BP41: =BP39+BP40 -> 0 | BQ41: =BQ39+BQ40 -> 0 | BR41: =BR39+BR40 -> 0 | BS41: =BS39+BS40 -> 0 | BT41: =BT39+BT40 -> 0 | BU41: =BU39+BU40 -> 0 | BV41: =BV39+BV40 -> 0 | BW41: =BW39+BW40 -> 0 | BX41: =SUM(BP41:BW41) -> 0 | CB41: Förderfähige Gesamtprojektkosten | CC41: =CC39+CC40 -> 0 | CD41: =CD39+CD40 -> 0 | CE41: =CE39+CE40 -> 0 | CF41: =CF39+CF40 -> 0 | CG41: =CG39+CG40 -> 0 | CH41: =CH39+CH40 -> 0 | CI41: =CI39+CI40 -> 0 | CJ41: =CJ39+CJ40 -> 0 | CK41: =SUM(CC41:CJ41) -> 0
B42: KMU Förderzuschlag | C42: 0 | D42: 0 | E42: =IF('Ganzes Unternehmen'!$C$12="ja",0.1,0) -> 0.1 | F42: =IF('Ganzes Unternehmen'!$C$12="ja",0.1,0) -> 0.1 | G42: =IF('Ganzes Unternehmen'!$C$12="ja",0.1,0) -> 0.1 | H42: =IF('Ganzes Unternehmen'!$C$12="ja",0.1,0) -> 0.1 | I42: =IF('Ganzes Unternehmen'!$C$12="ja",0.1,0) -> 0.1 | J42: =IF('Ganzes Unternehmen'!$C$12="ja",0.1,0) -> 0.1 | O42: KMU Förderzuschlag | P42: 0 | Q42: 0 | R42: =IF('Ganzes Unternehmen'!$C$12="ja",0.1,0) -> 0.1 | S42: =IF('Ganzes Unternehmen'!$C$12="ja",0.1,0) -> 0.1 | T42: =IF('Ganzes Unternehmen'!$C$12="ja",0.1,0) -> 0.1 | U42: =IF('Ganzes Unternehmen'!$C$12="ja",0.1,0) -> 0.1 | V42: =IF('Ganzes Unternehmen'!$C$12="ja",0.1,0) -> 0.1 | W42: =IF('Ganzes Unternehmen'!$C$12="ja",0.1,0) -> 0.1 | AB42: KMU Förderzuschlag | AC42: 0 | AD42: 0 | AE42: =IF('Ganzes Unternehmen'!$C$12="ja",0.1,0) -> 0.1 | AF42: =IF('Ganzes Unternehmen'!$C$12="ja",0.1,0) -> 0.1 | AG42: =IF('Ganzes Unternehmen'!$C$12="ja",0.1,0) -> 0.1 | AH42: =IF('Ganzes Unternehmen'!$C$12="ja",0.1,0) -> 0.1 | AI42: =IF('Ganzes Unternehmen'!$C$12="ja",0.1,0) -> 0.1 | AJ42: =IF('Ganzes Unternehmen'!$C$12="ja",0.1,0) -> 0.1 | AO42: KMU Förderzuschlag | AP42: 0 | AQ42: 0 | AR42: =IF('Ganzes Unternehmen'!$C$12="ja",0.1,0) -> 0.1 | AS42: =IF('Ganzes Unternehmen'!$C$12="ja",0.1,0) -> 0.1 | AT42: =IF('Ganzes Unternehmen'!$C$12="ja",0.1,0) -> 0.1 | AU42: =IF('Ganzes Unternehmen'!$C$12="ja",0.1,0) -> 0.1 | AV42: =IF('Ganzes Unternehmen'!$C$12="ja",0.1,0) -> 0.1 | AW42: =IF('Ganzes Unternehmen'!$C$12="ja",0.1,0) -> 0.1 | BB42: KMU Förderzuschlag | BC42: 0 | BD42: 0 | BE42: =IF('Ganzes Unternehmen'!$C$12="ja",0.1,0) -> 0.1 | BF42: =IF('Ganzes Unternehmen'!$C$12="ja",0.1,0) -> 0.1 | BG42: =IF('Ganzes Unternehmen'!$C$12="ja",0.1,0) -> 0.1 | BH42: =IF('Ganzes Unternehmen'!$C$12="ja",0.1,0) -> 0.1 | BI42: =IF('Ganzes Unternehmen'!$C$12="ja",0.1,0) -> 0.1 | BJ42: =IF('Ganzes Unternehmen'!$C$12="ja",0.1,0) -> 0.1 | BO42: KMU Förderzuschlag | BP42: 0 | BQ42: 0 | BR42: =IF('Ganzes Unternehmen'!$C$12="ja",0.1,0) -> 0.1 | BS42: =IF('Ganzes Unternehmen'!$C$12="ja",0.1,0) -> 0.1 | BT42: =IF('Ganzes Unternehmen'!$C$12="ja",0.1,0) -> 0.1 | BU42: =IF('Ganzes Unternehmen'!$C$12="ja",0.1,0) -> 0.1 | BV42: =IF('Ganzes Unternehmen'!$C$12="ja",0.1,0) -> 0.1 | BW42: =IF('Ganzes Unternehmen'!$C$12="ja",0.1,0) -> 0.1 | CB42: KMU Förderzuschlag | CC42: 0 | CD42: 0 | CE42: =IF('Ganzes Unternehmen'!$C$12="ja",0.1,0) -> 0.1 | CF42: =IF('Ganzes Unternehmen'!$C$12="ja",0.1,0) -> 0.1 | CG42: =IF('Ganzes Unternehmen'!$C$12="ja",0.1,0) -> 0.1 | CH42: =IF('Ganzes Unternehmen'!$C$12="ja",0.1,0) -> 0.1 | CI42: =IF('Ganzes Unternehmen'!$C$12="ja",0.1,0) -> 0.1 | CJ42: =IF('Ganzes Unternehmen'!$C$12="ja",0.1,0) -> 0.1
B43: Forschungszulage | C43: =IF(C9,(C41*(25%+C42)),0) -> 0 | D43: =IF(D9,(D41*(25%+D42)),0) -> 0 | E43: =IF(E9,(E41*25%)*25%+(E41*75%)*(25%+E42),0) -> 0 | F43: =IF(F9,(F41*(25%+F42)),0) -> 0 | G43: =IF(G9,(G41*(25%+G42)),0) -> 18786.6 | H43: =IF(H9,(H41*(25%+H42)),0) -> 47119.8 | I43: =IF(I9,(I41*(25%+I42)),0) -> 50559.6 | J43: =IF(J9,(J41*(25%+J42)),0) -> 0 | K43: =SUM(C43:J43) -> 116466 | O43: Forschungszulage | P43: =IF(P9,(P41*(25%+P42)),0) -> 0 | Q43: =IF(Q9,(Q41*(25%+Q42)),0) -> 0 | R43: =IF(R9,(R41*25%)*25%+(R41*75%)*(25%+R42),0) -> 0 | S43: =IF(S9,(S41*(25%+S42)),0) -> 0 | T43: =IF(T9,(T41*(25%+T42)),0) -> 0 | U43: =IF(U9,(U41*(25%+U42)),0) -> 0 | V43: =IF(V9,(V41*(25%+V42)),0) -> 0 | W43: =IF(W9,(W41*(25%+W42)),0) -> 0 | X43: =SUM(P43:W43) -> 0 | AB43: Forschungszulage | AC43: =IF(AC9,(AC41*(25%+AC42)),0) -> 0 | AD43: =IF(AD9,(AD41*(25%+AD42)),0) -> 0 | AE43: =IF(AE9,(AE41*25%)*25%+(AE41*75%)*(25%+AE42),0) -> 0 | AF43: =IF(AF9,(AF41*(25%+AF42)),0) -> 0 | AG43: =IF(AG9,(AG41*(25%+AG42)),0) -> 0 | AH43: =IF(AH9,(AH41*(25%+AH42)),0) -> 0 | AI43: =IF(AI9,(AI41*(25%+AI42)),0) -> 0 | AJ43: =IF(AJ9,(AJ41*(25%+AJ42)),0) -> 0 | AK43: =SUM(AC43:AJ43) -> 0 | AO43: Forschungszulage | AP43: =IF(AP9,(AP41*(25%+AP42)),0) -> 0 | AQ43: =IF(AQ9,(AQ41*(25%+AQ42)),0) -> 0 | AR43: =IF(AR9,(AR41*25%)*25%+(AR41*75%)*(25%+AR42),0) -> 0 | AS43: =IF(AS9,(AS41*(25%+AS42)),0) -> 0 | AT43: =IF(AT9,(AT41*(25%+AT42)),0) -> 0 | AU43: =IF(AU9,(AU41*(25%+AU42)),0) -> 0 | AV43: =IF(AV9,(AV41*(25%+AV42)),0) -> 0 | AW43: =IF(AW9,(AW41*(25%+AW42)),0) -> 0 | AX43: =SUM(AP43:AW43) -> 0 | BB43: Forschungszulage | BC43: =IF(BC9,(BC41*(25%+BC42)),0) -> 0 | BD43: =IF(BD9,(BD41*(25%+BD42)),0) -> 0 | BE43: =IF(BE9,(BE41*25%)*25%+(BE41*75%)*(25%+BE42),0) -> 0 | BF43: =IF(BF9,(BF41*(25%+BF42)),0) -> 0 | BG43: =IF(BG9,(BG41*(25%+BG42)),0) -> 0 | BH43: =IF(BH9,(BH41*(25%+BH42)),0) -> 0 | BI43: =IF(BI9,(BI41*(25%+BI42)),0) -> 0 | BJ43: =IF(BJ9,(BJ41*(25%+BJ42)),0) -> 0 | BK43: =SUM(BC43:BJ43) -> 0 | BO43: Forschungszulage | BP43: =IF(BP9,(BP41*(25%+BP42)),0) -> 0 | BQ43: =IF(BQ9,(BQ41*(25%+BQ42)),0) -> 0 | BR43: =IF(BR9,(BR41*25%)*25%+(BR41*75%)*(25%+BR42),0) -> 0 | BS43: =IF(BS9,(BS41*(25%+BS42)),0) -> 0 | BT43: =IF(BT9,(BT41*(25%+BT42)),0) -> 0 | BU43: =IF(BU9,(BU41*(25%+BU42)),0) -> 0 | BV43: =IF(BV9,(BV41*(25%+BV42)),0) -> 0 | BW43: =IF(BW9,(BW41*(25%+BW42)),0) -> 0 | BX43: =SUM(BP43:BW43) -> 0 | CB43: Forschungszulage | CC43: =IF(CC9,(CC41*(25%+CC42)),0) -> 0 | CD43: =IF(CD9,(CD41*(25%+CD42)),0) -> 0 | CE43: =IF(CE9,(CE41*25%)*25%+(CE41*75%)*(25%+CE42),0) -> 0 | CF43: =IF(CF9,(CF41*(25%+CF42)),0) -> 0 | CG43: =IF(CG9,(CG41*(25%+CG42)),0) -> 0 | CH43: =IF(CH9,(CH41*(25%+CH42)),0) -> 0 | CI43: =IF(CI9,(CI41*(25%+CI42)),0) -> 0 | CJ43: =IF(CJ9,(CJ41*(25%+CJ42)),0) -> 0 | CK43: =SUM(CC43:CJ43) -> 0
B45: Personeller Rahmen | C45: =C10 -> 2022 | D45: =D10 -> 2023 | E45: =E10 -> 2024 | F45: =F10 -> 2025 | G45: =G10 -> 2026 | H45: =H10 -> 2027 | I45: =I10 -> 2028 | J45: =J10 -> 2029 | O45: Personeller Rahmen | P45: =P10 -> 2022 | Q45: =Q10 -> 2023 | R45: =R10 -> 2024 | S45: =S10 -> 2025 | T45: =T10 -> 2026 | U45: =U10 -> 2027 | V45: =V10 -> 2028 | W45: =W10 -> 2029 | AB45: Personeller Rahmen | AC45: =AC10 -> 2022 | AD45: =AD10 -> 2023 | AE45: =AE10 -> 2024 | AF45: =AF10 -> 2025 | AG45: =AG10 -> 2026 | AH45: =AH10 -> 2027 | AI45: =AI10 -> 2028 | AJ45: =AJ10 -> 2029 | AO45: Personeller Rahmen | AP45: =AP10 -> 2022 | AQ45: =AQ10 -> 2023 | AR45: =AR10 -> 2024 | AS45: =AS10 -> 2025 | AT45: =AT10 -> 2026 | AU45: =AU10 -> 2027 | AV45: =AV10 -> 2028 | AW45: =AW10 -> 2029 | BB45: Personeller Rahmen | BC45: =BC10 -> 2022 | BD45: =BD10 -> 2023 | BE45: =BE10 -> 2024 | BF45: =BF10 -> 2025 | BG45: =BG10 -> 2026 | BH45: =BH10 -> 2027 | BI45: =BI10 -> 2028 | BJ45: =BJ10 -> 2029 | BO45: Personeller Rahmen | BP45: =BP10 -> 2022 | BQ45: =BQ10 -> 2023 | BR45: =BR10 -> 2024 | BS45: =BS10 -> 2025 | BT45: =BT10 -> 2026 | BU45: =BU10 -> 2027 | BV45: =BV10 -> 2028 | BW45: =BW10 -> 2029 | CB45: Personeller Rahmen | CC45: =CC10 -> 2022 | CD45: =CD10 -> 2023 | CE45: =CE10 -> 2024 | CF45: =CF10 -> 2025 | CG45: =CG10 -> 2026 | CH45: =CH10 -> 2027 | CI45: =CI10 -> 2028 | CJ45: =CJ10 -> 2028
B46: MA mit Hochschulabschluss [Std.] | C46: =ROUND(SUMIFS(MitarbeiterFTE[[Stunden]:[Stunden]],MitarbeiterFTE[[Jahr]:[Jahr]],'FuE Vorhaben'!C$45,MitarbeiterFTE[[Ausbildungsstatus]:[Ausbildungsstatus]],2,MitarbeiterFTE[[Vorhaben]:[Vorhaben]],C75),2) -> 0 | D46: =ROUND(SUMIFS(MitarbeiterFTE[[Stunden]:[Stunden]],MitarbeiterFTE[[Jahr]:[Jahr]],'FuE Vorhaben'!D$45,MitarbeiterFTE[[Ausbildungsstatus]:[Ausbildungsstatus]],2,MitarbeiterFTE[[Vorhaben]:[Vorhaben]],D75),2) -> 0 | E46: =ROUND(SUMIFS(MitarbeiterFTE[[Stunden]:[Stunden]],MitarbeiterFTE[[Jahr]:[Jahr]],'FuE Vorhaben'!E$45,MitarbeiterFTE[[Ausbildungsstatus]:[Ausbildungsstatus]],2,MitarbeiterFTE[[Vorhaben]:[Vorhaben]],E75),2) -> 0 | F46: =ROUND(SUMIFS(MitarbeiterFTE[[Stunden]:[Stunden]],MitarbeiterFTE[[Jahr]:[Jahr]],'FuE Vorhaben'!F$45,MitarbeiterFTE[[Ausbildungsstatus]:[Ausbildungsstatus]],2,MitarbeiterFTE[[Vorhaben]:[Vorhaben]],F75),2) -> 0 | G46: =ROUND(SUMIFS(MitarbeiterFTE[[Stunden]:[Stunden]],MitarbeiterFTE[[Jahr]:[Jahr]],'FuE Vorhaben'!G$45,MitarbeiterFTE[[Ausbildungsstatus]:[Ausbildungsstatus]],2,MitarbeiterFTE[[Vorhaben]:[Vorhaben]],G75),2) -> 117.81 | H46: =ROUND(SUMIFS(MitarbeiterFTE[[Stunden]:[Stunden]],MitarbeiterFTE[[Jahr]:[Jahr]],'FuE Vorhaben'!H$45,MitarbeiterFTE[[Ausbildungsstatus]:[Ausbildungsstatus]],2,MitarbeiterFTE[[Vorhaben]:[Vorhaben]],H75),2) -> 340.64 | I46: =ROUND(SUMIFS(MitarbeiterFTE[[Stunden]:[Stunden]],MitarbeiterFTE[[Jahr]:[Jahr]],'FuE Vorhaben'!I$45,MitarbeiterFTE[[Ausbildungsstatus]:[Ausbildungsstatus]],2,MitarbeiterFTE[[Vorhaben]:[Vorhaben]],I75),2) -> 668.48 | J46: =ROUND(SUMIFS(MitarbeiterFTE[[Stunden]:[Stunden]],MitarbeiterFTE[[Jahr]:[Jahr]],'FuE Vorhaben'!J$45,MitarbeiterFTE[[Ausbildungsstatus]:[Ausbildungsstatus]],2,MitarbeiterFTE[[Vorhaben]:[Vorhaben]],J75),2) -> 0 | O46: MA mit Hochschulabschluss [Std.] | P46: =ROUND(SUMIFS(MitarbeiterFTE[[Stunden]:[Stunden]],MitarbeiterFTE[[Jahr]:[Jahr]],'FuE Vorhaben'!P$45,MitarbeiterFTE[[Ausbildungsstatus]:[Ausbildungsstatus]],2,MitarbeiterFTE[[Vorhaben]:[Vorhaben]],P75),2) -> 0 | Q46: =ROUND(SUMIFS(MitarbeiterFTE[[Stunden]:[Stunden]],MitarbeiterFTE[[Jahr]:[Jahr]],'FuE Vorhaben'!Q$45,MitarbeiterFTE[[Ausbildungsstatus]:[Ausbildungsstatus]],2,MitarbeiterFTE[[Vorhaben]:[Vorhaben]],Q75),2) -> 0 | R46: =ROUND(SUMIFS(MitarbeiterFTE[[Stunden]:[Stunden]],MitarbeiterFTE[[Jahr]:[Jahr]],'FuE Vorhaben'!R$45,MitarbeiterFTE[[Ausbildungsstatus]:[Ausbildungsstatus]],2,MitarbeiterFTE[[Vorhaben]:[Vorhaben]],R75),2) -> 0 | S46: =ROUND(SUMIFS(MitarbeiterFTE[[Stunden]:[Stunden]],MitarbeiterFTE[[Jahr]:[Jahr]],'FuE Vorhaben'!S$45,MitarbeiterFTE[[Ausbildungsstatus]:[Ausbildungsstatus]],2,MitarbeiterFTE[[Vorhaben]:[Vorhaben]],S75),2) -> 0 | T46: =ROUND(SUMIFS(MitarbeiterFTE[[Stunden]:[Stunden]],MitarbeiterFTE[[Jahr]:[Jahr]],'FuE Vorhaben'!T$45,MitarbeiterFTE[[Ausbildungsstatus]:[Ausbildungsstatus]],2,MitarbeiterFTE[[Vorhaben]:[Vorhaben]],T75),2) -> 0 | U46: =ROUND(SUMIFS(MitarbeiterFTE[[Stunden]:[Stunden]],MitarbeiterFTE[[Jahr]:[Jahr]],'FuE Vorhaben'!U$45,MitarbeiterFTE[[Ausbildungsstatus]:[Ausbildungsstatus]],2,MitarbeiterFTE[[Vorhaben]:[Vorhaben]],U75),2) -> 0 | V46: =ROUND(SUMIFS(MitarbeiterFTE[[Stunden]:[Stunden]],MitarbeiterFTE[[Jahr]:[Jahr]],'FuE Vorhaben'!V$45,MitarbeiterFTE[[Ausbildungsstatus]:[Ausbildungsstatus]],2,MitarbeiterFTE[[Vorhaben]:[Vorhaben]],V75),2) -> 0 | W46: =ROUND(SUMIFS(MitarbeiterFTE[[Stunden]:[Stunden]],MitarbeiterFTE[[Jahr]:[Jahr]],'FuE Vorhaben'!W$45,MitarbeiterFTE[[Ausbildungsstatus]:[Ausbildungsstatus]],2,MitarbeiterFTE[[Vorhaben]:[Vorhaben]],W75),2) -> 0 | AB46: MA mit Hochschulabschluss [Std.] | AC46: =ROUND(SUMIFS(MitarbeiterFTE[[Stunden]:[Stunden]],MitarbeiterFTE[[Jahr]:[Jahr]],'FuE Vorhaben'!AC$45,MitarbeiterFTE[[Ausbildungsstatus]:[Ausbildungsstatus]],2,MitarbeiterFTE[[Vorhaben]:[Vorhaben]],AC75),2) -> 0 | AD46: =ROUND(SUMIFS(MitarbeiterFTE[[Stunden]:[Stunden]],MitarbeiterFTE[[Jahr]:[Jahr]],'FuE Vorhaben'!AD$45,MitarbeiterFTE[[Ausbildungsstatus]:[Ausbildungsstatus]],2,MitarbeiterFTE[[Vorhaben]:[Vorhaben]],AD75),2) -> 0 | AE46: =ROUND(SUMIFS(MitarbeiterFTE[[Stunden]:[Stunden]],MitarbeiterFTE[[Jahr]:[Jahr]],'FuE Vorhaben'!AE$45,MitarbeiterFTE[[Ausbildungsstatus]:[Ausbildungsstatus]],2,MitarbeiterFTE[[Vorhaben]:[Vorhaben]],AE75),2) -> 0 | AF46: =ROUND(SUMIFS(MitarbeiterFTE[[Stunden]:[Stunden]],MitarbeiterFTE[[Jahr]:[Jahr]],'FuE Vorhaben'!AF$45,MitarbeiterFTE[[Ausbildungsstatus]:[Ausbildungsstatus]],2,MitarbeiterFTE[[Vorhaben]:[Vorhaben]],AF75),2) -> 0 | AG46: =ROUND(SUMIFS(MitarbeiterFTE[[Stunden]:[Stunden]],MitarbeiterFTE[[Jahr]:[Jahr]],'FuE Vorhaben'!AG$45,MitarbeiterFTE[[Ausbildungsstatus]:[Ausbildungsstatus]],2,MitarbeiterFTE[[Vorhaben]:[Vorhaben]],AG75),2) -> 0 | AH46: =ROUND(SUMIFS(MitarbeiterFTE[[Stunden]:[Stunden]],MitarbeiterFTE[[Jahr]:[Jahr]],'FuE Vorhaben'!AH$45,MitarbeiterFTE[[Ausbildungsstatus]:[Ausbildungsstatus]],2,MitarbeiterFTE[[Vorhaben]:[Vorhaben]],AH75),2) -> 0 | AI46: =ROUND(SUMIFS(MitarbeiterFTE[[Stunden]:[Stunden]],MitarbeiterFTE[[Jahr]:[Jahr]],'FuE Vorhaben'!AI$45,MitarbeiterFTE[[Ausbildungsstatus]:[Ausbildungsstatus]],2,MitarbeiterFTE[[Vorhaben]:[Vorhaben]],AI75),2) -> 0 | AJ46: =ROUND(SUMIFS(MitarbeiterFTE[[Stunden]:[Stunden]],MitarbeiterFTE[[Jahr]:[Jahr]],'FuE Vorhaben'!AJ$45,MitarbeiterFTE[[Ausbildungsstatus]:[Ausbildungsstatus]],2,MitarbeiterFTE[[Vorhaben]:[Vorhaben]],AJ75),2) -> 0 | AO46: MA mit Hochschulabschluss [Std.] | AP46: =ROUND(SUMIFS(MitarbeiterFTE[[Stunden]:[Stunden]],MitarbeiterFTE[[Jahr]:[Jahr]],'FuE Vorhaben'!AP$45,MitarbeiterFTE[[Ausbildungsstatus]:[Ausbildungsstatus]],2,MitarbeiterFTE[[Vorhaben]:[Vorhaben]],AP75),2) -> 0 | AQ46: =ROUND(SUMIFS(MitarbeiterFTE[[Stunden]:[Stunden]],MitarbeiterFTE[[Jahr]:[Jahr]],'FuE Vorhaben'!AQ$45,MitarbeiterFTE[[Ausbildungsstatus]:[Ausbildungsstatus]],2,MitarbeiterFTE[[Vorhaben]:[Vorhaben]],AQ75),2) -> 0 | AR46: =ROUND(SUMIFS(MitarbeiterFTE[[Stunden]:[Stunden]],MitarbeiterFTE[[Jahr]:[Jahr]],'FuE Vorhaben'!AR$45,MitarbeiterFTE[[Ausbildungsstatus]:[Ausbildungsstatus]],2,MitarbeiterFTE[[Vorhaben]:[Vorhaben]],AR75),2) -> 0 | AS46: =ROUND(SUMIFS(MitarbeiterFTE[[Stunden]:[Stunden]],MitarbeiterFTE[[Jahr]:[Jahr]],'FuE Vorhaben'!AS$45,MitarbeiterFTE[[Ausbildungsstatus]:[Ausbildungsstatus]],2,MitarbeiterFTE[[Vorhaben]:[Vorhaben]],AS75),2) -> 0 | AT46: =ROUND(SUMIFS(MitarbeiterFTE[[Stunden]:[Stunden]],MitarbeiterFTE[[Jahr]:[Jahr]],'FuE Vorhaben'!AT$45,MitarbeiterFTE[[Ausbildungsstatus]:[Ausbildungsstatus]],2,MitarbeiterFTE[[Vorhaben]:[Vorhaben]],AT75),2) -> 0 | AU46: =ROUND(SUMIFS(MitarbeiterFTE[[Stunden]:[Stunden]],MitarbeiterFTE[[Jahr]:[Jahr]],'FuE Vorhaben'!AU$45,MitarbeiterFTE[[Ausbildungsstatus]:[Ausbildungsstatus]],2,MitarbeiterFTE[[Vorhaben]:[Vorhaben]],AU75),2) -> 0 | AV46: =ROUND(SUMIFS(MitarbeiterFTE[[Stunden]:[Stunden]],MitarbeiterFTE[[Jahr]:[Jahr]],'FuE Vorhaben'!AV$45,MitarbeiterFTE[[Ausbildungsstatus]:[Ausbildungsstatus]],2,MitarbeiterFTE[[Vorhaben]:[Vorhaben]],AV75),2) -> 0 | AW46: =ROUND(SUMIFS(MitarbeiterFTE[[Stunden]:[Stunden]],MitarbeiterFTE[[Jahr]:[Jahr]],'FuE Vorhaben'!AW$45,MitarbeiterFTE[[Ausbildungsstatus]:[Ausbildungsstatus]],2,MitarbeiterFTE[[Vorhaben]:[Vorhaben]],AW75),2) -> 0 | BB46: MA mit Hochschulabschluss [Std.] | BC46: =ROUND(SUMIFS(MitarbeiterFTE[[Stunden]:[Stunden]],MitarbeiterFTE[[Jahr]:[Jahr]],'FuE Vorhaben'!BC$45,MitarbeiterFTE[[Ausbildungsstatus]:[Ausbildungsstatus]],2,MitarbeiterFTE[[Vorhaben]:[Vorhaben]],BC75),2) -> 0 | BD46: =ROUND(SUMIFS(MitarbeiterFTE[[Stunden]:[Stunden]],MitarbeiterFTE[[Jahr]:[Jahr]],'FuE Vorhaben'!BD$45,MitarbeiterFTE[[Ausbildungsstatus]:[Ausbildungsstatus]],2,MitarbeiterFTE[[Vorhaben]:[Vorhaben]],BD75),2) -> 0 | BE46: =ROUND(SUMIFS(MitarbeiterFTE[[Stunden]:[Stunden]],MitarbeiterFTE[[Jahr]:[Jahr]],'FuE Vorhaben'!BE$45,MitarbeiterFTE[[Ausbildungsstatus]:[Ausbildungsstatus]],2,MitarbeiterFTE[[Vorhaben]:[Vorhaben]],BE75),2) -> 0 | BF46: =ROUND(SUMIFS(MitarbeiterFTE[[Stunden]:[Stunden]],MitarbeiterFTE[[Jahr]:[Jahr]],'FuE Vorhaben'!BF$45,MitarbeiterFTE[[Ausbildungsstatus]:[Ausbildungsstatus]],2,MitarbeiterFTE[[Vorhaben]:[Vorhaben]],BF75),2) -> 0 | BG46: =ROUND(SUMIFS(MitarbeiterFTE[[Stunden]:[Stunden]],MitarbeiterFTE[[Jahr]:[Jahr]],'FuE Vorhaben'!BG$45,MitarbeiterFTE[[Ausbildungsstatus]:[Ausbildungsstatus]],2,MitarbeiterFTE[[Vorhaben]:[Vorhaben]],BG75),2) -> 0 | BH46: =ROUND(SUMIFS(MitarbeiterFTE[[Stunden]:[Stunden]],MitarbeiterFTE[[Jahr]:[Jahr]],'FuE Vorhaben'!BH$45,MitarbeiterFTE[[Ausbildungsstatus]:[Ausbildungsstatus]],2,MitarbeiterFTE[[Vorhaben]:[Vorhaben]],BH75),2) -> 0 | BI46: =ROUND(SUMIFS(MitarbeiterFTE[[Stunden]:[Stunden]],MitarbeiterFTE[[Jahr]:[Jahr]],'FuE Vorhaben'!BI$45,MitarbeiterFTE[[Ausbildungsstatus]:[Ausbildungsstatus]],2,MitarbeiterFTE[[Vorhaben]:[Vorhaben]],BI75),2) -> 0 | BJ46: =ROUND(SUMIFS(MitarbeiterFTE[[Stunden]:[Stunden]],MitarbeiterFTE[[Jahr]:[Jahr]],'FuE Vorhaben'!BJ$45,MitarbeiterFTE[[Ausbildungsstatus]:[Ausbildungsstatus]],2,MitarbeiterFTE[[Vorhaben]:[Vorhaben]],BJ75),2) -> 0 | BO46: MA mit Hochschulabschluss [Std.] | BP46: =ROUND(SUMIFS(MitarbeiterFTE[[Stunden]:[Stunden]],MitarbeiterFTE[[Jahr]:[Jahr]],'FuE Vorhaben'!BP$45,MitarbeiterFTE[[Ausbildungsstatus]:[Ausbildungsstatus]],2,MitarbeiterFTE[[Vorhaben]:[Vorhaben]],BP75),2) -> 0 | BQ46: =ROUND(SUMIFS(MitarbeiterFTE[[Stunden]:[Stunden]],MitarbeiterFTE[[Jahr]:[Jahr]],'FuE Vorhaben'!BQ$45,MitarbeiterFTE[[Ausbildungsstatus]:[Ausbildungsstatus]],2,MitarbeiterFTE[[Vorhaben]:[Vorhaben]],BQ75),2) -> 0 | BR46: =ROUND(SUMIFS(MitarbeiterFTE[[Stunden]:[Stunden]],MitarbeiterFTE[[Jahr]:[Jahr]],'FuE Vorhaben'!BR$45,MitarbeiterFTE[[Ausbildungsstatus]:[Ausbildungsstatus]],2,MitarbeiterFTE[[Vorhaben]:[Vorhaben]],BR75),2) -> 0 | BS46: =ROUND(SUMIFS(MitarbeiterFTE[[Stunden]:[Stunden]],MitarbeiterFTE[[Jahr]:[Jahr]],'FuE Vorhaben'!BS$45,MitarbeiterFTE[[Ausbildungsstatus]:[Ausbildungsstatus]],2,MitarbeiterFTE[[Vorhaben]:[Vorhaben]],BS75),2) -> 0 | BT46: =ROUND(SUMIFS(MitarbeiterFTE[[Stunden]:[Stunden]],MitarbeiterFTE[[Jahr]:[Jahr]],'FuE Vorhaben'!BT$45,MitarbeiterFTE[[Ausbildungsstatus]:[Ausbildungsstatus]],2,MitarbeiterFTE[[Vorhaben]:[Vorhaben]],BT75),2) -> 0 | BU46: =ROUND(SUMIFS(MitarbeiterFTE[[Stunden]:[Stunden]],MitarbeiterFTE[[Jahr]:[Jahr]],'FuE Vorhaben'!BU$45,MitarbeiterFTE[[Ausbildungsstatus]:[Ausbildungsstatus]],2,MitarbeiterFTE[[Vorhaben]:[Vorhaben]],BU75),2) -> 0 | BV46: =ROUND(SUMIFS(MitarbeiterFTE[[Stunden]:[Stunden]],MitarbeiterFTE[[Jahr]:[Jahr]],'FuE Vorhaben'!BV$45,MitarbeiterFTE[[Ausbildungsstatus]:[Ausbildungsstatus]],2,MitarbeiterFTE[[Vorhaben]:[Vorhaben]],BV75),2) -> 0 | BW46: =ROUND(SUMIFS(MitarbeiterFTE[[Stunden]:[Stunden]],MitarbeiterFTE[[Jahr]:[Jahr]],'FuE Vorhaben'!BW$45,MitarbeiterFTE[[Ausbildungsstatus]:[Ausbildungsstatus]],2,MitarbeiterFTE[[Vorhaben]:[Vorhaben]],BW75),2) -> 0 | CB46: MA mit Hochschulabschluss [Std.] | CC46: =ROUND(SUMIFS(MitarbeiterFTE[[Stunden]:[Stunden]],MitarbeiterFTE[[Jahr]:[Jahr]],'FuE Vorhaben'!CC$45,MitarbeiterFTE[[Ausbildungsstatus]:[Ausbildungsstatus]],2,MitarbeiterFTE[[Vorhaben]:[Vorhaben]],CC75),2) -> 0 | CD46: =ROUND(SUMIFS(MitarbeiterFTE[[Stunden]:[Stunden]],MitarbeiterFTE[[Jahr]:[Jahr]],'FuE Vorhaben'!CD$45,MitarbeiterFTE[[Ausbildungsstatus]:[Ausbildungsstatus]],2,MitarbeiterFTE[[Vorhaben]:[Vorhaben]],CD75),2) -> 0 | CE46: =ROUND(SUMIFS(MitarbeiterFTE[[Stunden]:[Stunden]],MitarbeiterFTE[[Jahr]:[Jahr]],'FuE Vorhaben'!CE$45,MitarbeiterFTE[[Ausbildungsstatus]:[Ausbildungsstatus]],2,MitarbeiterFTE[[Vorhaben]:[Vorhaben]],CE75),2) -> 0 | CF46: =ROUND(SUMIFS(MitarbeiterFTE[[Stunden]:[Stunden]],MitarbeiterFTE[[Jahr]:[Jahr]],'FuE Vorhaben'!CF$45,MitarbeiterFTE[[Ausbildungsstatus]:[Ausbildungsstatus]],2,MitarbeiterFTE[[Vorhaben]:[Vorhaben]],CF75),2) -> 0 | CG46: =ROUND(SUMIFS(MitarbeiterFTE[[Stunden]:[Stunden]],MitarbeiterFTE[[Jahr]:[Jahr]],'FuE Vorhaben'!CG$45,MitarbeiterFTE[[Ausbildungsstatus]:[Ausbildungsstatus]],2,MitarbeiterFTE[[Vorhaben]:[Vorhaben]],CG75),2) -> 0 | CH46: =ROUND(SUMIFS(MitarbeiterFTE[[Stunden]:[Stunden]],MitarbeiterFTE[[Jahr]:[Jahr]],'FuE Vorhaben'!CH$45,MitarbeiterFTE[[Ausbildungsstatus]:[Ausbildungsstatus]],2,MitarbeiterFTE[[Vorhaben]:[Vorhaben]],CH75),2) -> 0 | CI46: =ROUND(SUMIFS(MitarbeiterFTE[[Stunden]:[Stunden]],MitarbeiterFTE[[Jahr]:[Jahr]],'FuE Vorhaben'!CI$45,MitarbeiterFTE[[Ausbildungsstatus]:[Ausbildungsstatus]],2,MitarbeiterFTE[[Vorhaben]:[Vorhaben]],CI75),2) -> 0 | CJ46: =ROUND(SUMIFS(MitarbeiterFTE[[Stunden]:[Stunden]],MitarbeiterFTE[[Jahr]:[Jahr]],'FuE Vorhaben'!CJ$45,MitarbeiterFTE[[Ausbildungsstatus]:[Ausbildungsstatus]],2,MitarbeiterFTE[[Vorhaben]:[Vorhaben]],CJ75),2) -> 0
B47: MA techn. Ausbildung [Std.] | C47: =ROUND(SUMIFS(MitarbeiterFTE[[Stunden]:[Stunden]],MitarbeiterFTE[[Jahr]:[Jahr]],'FuE Vorhaben'!C$45,MitarbeiterFTE[[Ausbildungsstatus]:[Ausbildungsstatus]],1,MitarbeiterFTE[[Vorhaben]:[Vorhaben]],C75),2) -> 0 | D47: =ROUND(SUMIFS(MitarbeiterFTE[[Stunden]:[Stunden]],MitarbeiterFTE[[Jahr]:[Jahr]],'FuE Vorhaben'!D$45,MitarbeiterFTE[[Ausbildungsstatus]:[Ausbildungsstatus]],1,MitarbeiterFTE[[Vorhaben]:[Vorhaben]],D75),2) -> 0 | E47: =ROUND(SUMIFS(MitarbeiterFTE[[Stunden]:[Stunden]],MitarbeiterFTE[[Jahr]:[Jahr]],'FuE Vorhaben'!E$45,MitarbeiterFTE[[Ausbildungsstatus]:[Ausbildungsstatus]],1,MitarbeiterFTE[[Vorhaben]:[Vorhaben]],E75),2) -> 0 | F47: =ROUND(SUMIFS(MitarbeiterFTE[[Stunden]:[Stunden]],MitarbeiterFTE[[Jahr]:[Jahr]],'FuE Vorhaben'!F$45,MitarbeiterFTE[[Ausbildungsstatus]:[Ausbildungsstatus]],1,MitarbeiterFTE[[Vorhaben]:[Vorhaben]],F75),2) -> 0 | G47: =ROUND(SUMIFS(MitarbeiterFTE[[Stunden]:[Stunden]],MitarbeiterFTE[[Jahr]:[Jahr]],'FuE Vorhaben'!G$45,MitarbeiterFTE[[Ausbildungsstatus]:[Ausbildungsstatus]],1,MitarbeiterFTE[[Vorhaben]:[Vorhaben]],G75),2) -> 0 | H47: =ROUND(SUMIFS(MitarbeiterFTE[[Stunden]:[Stunden]],MitarbeiterFTE[[Jahr]:[Jahr]],'FuE Vorhaben'!H$45,MitarbeiterFTE[[Ausbildungsstatus]:[Ausbildungsstatus]],1,MitarbeiterFTE[[Vorhaben]:[Vorhaben]],H75),2) -> 0 | I47: =ROUND(SUMIFS(MitarbeiterFTE[[Stunden]:[Stunden]],MitarbeiterFTE[[Jahr]:[Jahr]],'FuE Vorhaben'!I$45,MitarbeiterFTE[[Ausbildungsstatus]:[Ausbildungsstatus]],1,MitarbeiterFTE[[Vorhaben]:[Vorhaben]],I75),2) -> 0 | J47: =ROUND(SUMIFS(MitarbeiterFTE[[Stunden]:[Stunden]],MitarbeiterFTE[[Jahr]:[Jahr]],'FuE Vorhaben'!J$45,MitarbeiterFTE[[Ausbildungsstatus]:[Ausbildungsstatus]],1,MitarbeiterFTE[[Vorhaben]:[Vorhaben]],J75),2) -> 0 | O47: MA techn. Ausbildung [Std.] | P47: =ROUND(SUMIFS(MitarbeiterFTE[[Stunden]:[Stunden]],MitarbeiterFTE[[Jahr]:[Jahr]],'FuE Vorhaben'!P$45,MitarbeiterFTE[[Ausbildungsstatus]:[Ausbildungsstatus]],1,MitarbeiterFTE[[Vorhaben]:[Vorhaben]],P75),2) -> 0 | Q47: =ROUND(SUMIFS(MitarbeiterFTE[[Stunden]:[Stunden]],MitarbeiterFTE[[Jahr]:[Jahr]],'FuE Vorhaben'!Q$45,MitarbeiterFTE[[Ausbildungsstatus]:[Ausbildungsstatus]],1,MitarbeiterFTE[[Vorhaben]:[Vorhaben]],Q75),2) -> 0 | R47: =ROUND(SUMIFS(MitarbeiterFTE[[Stunden]:[Stunden]],MitarbeiterFTE[[Jahr]:[Jahr]],'FuE Vorhaben'!R$45,MitarbeiterFTE[[Ausbildungsstatus]:[Ausbildungsstatus]],1,MitarbeiterFTE[[Vorhaben]:[Vorhaben]],R75),2) -> 0 | S47: =ROUND(SUMIFS(MitarbeiterFTE[[Stunden]:[Stunden]],MitarbeiterFTE[[Jahr]:[Jahr]],'FuE Vorhaben'!S$45,MitarbeiterFTE[[Ausbildungsstatus]:[Ausbildungsstatus]],1,MitarbeiterFTE[[Vorhaben]:[Vorhaben]],S75),2) -> 0 | T47: =ROUND(SUMIFS(MitarbeiterFTE[[Stunden]:[Stunden]],MitarbeiterFTE[[Jahr]:[Jahr]],'FuE Vorhaben'!T$45,MitarbeiterFTE[[Ausbildungsstatus]:[Ausbildungsstatus]],1,MitarbeiterFTE[[Vorhaben]:[Vorhaben]],T75),2) -> 0 | U47: =ROUND(SUMIFS(MitarbeiterFTE[[Stunden]:[Stunden]],MitarbeiterFTE[[Jahr]:[Jahr]],'FuE Vorhaben'!U$45,MitarbeiterFTE[[Ausbildungsstatus]:[Ausbildungsstatus]],1,MitarbeiterFTE[[Vorhaben]:[Vorhaben]],U75),2) -> 0 | V47: =ROUND(SUMIFS(MitarbeiterFTE[[Stunden]:[Stunden]],MitarbeiterFTE[[Jahr]:[Jahr]],'FuE Vorhaben'!V$45,MitarbeiterFTE[[Ausbildungsstatus]:[Ausbildungsstatus]],1,MitarbeiterFTE[[Vorhaben]:[Vorhaben]],V75),2) -> 0 | W47: =ROUND(SUMIFS(MitarbeiterFTE[[Stunden]:[Stunden]],MitarbeiterFTE[[Jahr]:[Jahr]],'FuE Vorhaben'!W$45,MitarbeiterFTE[[Ausbildungsstatus]:[Ausbildungsstatus]],1,MitarbeiterFTE[[Vorhaben]:[Vorhaben]],W75),2) -> 0 | AB47: MA techn. Ausbildung [Std.] | AC47: =ROUND(SUMIFS(MitarbeiterFTE[[Stunden]:[Stunden]],MitarbeiterFTE[[Jahr]:[Jahr]],'FuE Vorhaben'!AC$45,MitarbeiterFTE[[Ausbildungsstatus]:[Ausbildungsstatus]],1,MitarbeiterFTE[[Vorhaben]:[Vorhaben]],AC75),2) -> 0 | AD47: =ROUND(SUMIFS(MitarbeiterFTE[[Stunden]:[Stunden]],MitarbeiterFTE[[Jahr]:[Jahr]],'FuE Vorhaben'!AD$45,MitarbeiterFTE[[Ausbildungsstatus]:[Ausbildungsstatus]],1,MitarbeiterFTE[[Vorhaben]:[Vorhaben]],AD75),2) -> 0 | AE47: =ROUND(SUMIFS(MitarbeiterFTE[[Stunden]:[Stunden]],MitarbeiterFTE[[Jahr]:[Jahr]],'FuE Vorhaben'!AE$45,MitarbeiterFTE[[Ausbildungsstatus]:[Ausbildungsstatus]],1,MitarbeiterFTE[[Vorhaben]:[Vorhaben]],AE75),2) -> 0 | AF47: =ROUND(SUMIFS(MitarbeiterFTE[[Stunden]:[Stunden]],MitarbeiterFTE[[Jahr]:[Jahr]],'FuE Vorhaben'!AF$45,MitarbeiterFTE[[Ausbildungsstatus]:[Ausbildungsstatus]],1,MitarbeiterFTE[[Vorhaben]:[Vorhaben]],AF75),2) -> 0 | AG47: =ROUND(SUMIFS(MitarbeiterFTE[[Stunden]:[Stunden]],MitarbeiterFTE[[Jahr]:[Jahr]],'FuE Vorhaben'!AG$45,MitarbeiterFTE[[Ausbildungsstatus]:[Ausbildungsstatus]],1,MitarbeiterFTE[[Vorhaben]:[Vorhaben]],AG75),2) -> 0 | AH47: =ROUND(SUMIFS(MitarbeiterFTE[[Stunden]:[Stunden]],MitarbeiterFTE[[Jahr]:[Jahr]],'FuE Vorhaben'!AH$45,MitarbeiterFTE[[Ausbildungsstatus]:[Ausbildungsstatus]],1,MitarbeiterFTE[[Vorhaben]:[Vorhaben]],AH75),2) -> 0 | AI47: =ROUND(SUMIFS(MitarbeiterFTE[[Stunden]:[Stunden]],MitarbeiterFTE[[Jahr]:[Jahr]],'FuE Vorhaben'!AI$45,MitarbeiterFTE[[Ausbildungsstatus]:[Ausbildungsstatus]],1,MitarbeiterFTE[[Vorhaben]:[Vorhaben]],AI75),2) -> 0 | AJ47: =ROUND(SUMIFS(MitarbeiterFTE[[Stunden]:[Stunden]],MitarbeiterFTE[[Jahr]:[Jahr]],'FuE Vorhaben'!AJ$45,MitarbeiterFTE[[Ausbildungsstatus]:[Ausbildungsstatus]],1,MitarbeiterFTE[[Vorhaben]:[Vorhaben]],AJ75),2) -> 0 | AO47: MA techn. Ausbildung [Std.] | AP47: =ROUND(SUMIFS(MitarbeiterFTE[[Stunden]:[Stunden]],MitarbeiterFTE[[Jahr]:[Jahr]],'FuE Vorhaben'!AP$45,MitarbeiterFTE[[Ausbildungsstatus]:[Ausbildungsstatus]],1,MitarbeiterFTE[[Vorhaben]:[Vorhaben]],AP75),2) -> 0 | AQ47: =ROUND(SUMIFS(MitarbeiterFTE[[Stunden]:[Stunden]],MitarbeiterFTE[[Jahr]:[Jahr]],'FuE Vorhaben'!AQ$45,MitarbeiterFTE[[Ausbildungsstatus]:[Ausbildungsstatus]],1,MitarbeiterFTE[[Vorhaben]:[Vorhaben]],AQ75),2) -> 0 | AR47: =ROUND(SUMIFS(MitarbeiterFTE[[Stunden]:[Stunden]],MitarbeiterFTE[[Jahr]:[Jahr]],'FuE Vorhaben'!AR$45,MitarbeiterFTE[[Ausbildungsstatus]:[Ausbildungsstatus]],1,MitarbeiterFTE[[Vorhaben]:[Vorhaben]],AR75),2) -> 0 | AS47: =ROUND(SUMIFS(MitarbeiterFTE[[Stunden]:[Stunden]],MitarbeiterFTE[[Jahr]:[Jahr]],'FuE Vorhaben'!AS$45,MitarbeiterFTE[[Ausbildungsstatus]:[Ausbildungsstatus]],1,MitarbeiterFTE[[Vorhaben]:[Vorhaben]],AS75),2) -> 0 | AT47: =ROUND(SUMIFS(MitarbeiterFTE[[Stunden]:[Stunden]],MitarbeiterFTE[[Jahr]:[Jahr]],'FuE Vorhaben'!AT$45,MitarbeiterFTE[[Ausbildungsstatus]:[Ausbildungsstatus]],1,MitarbeiterFTE[[Vorhaben]:[Vorhaben]],AT75),2) -> 0 | AU47: =ROUND(SUMIFS(MitarbeiterFTE[[Stunden]:[Stunden]],MitarbeiterFTE[[Jahr]:[Jahr]],'FuE Vorhaben'!AU$45,MitarbeiterFTE[[Ausbildungsstatus]:[Ausbildungsstatus]],1,MitarbeiterFTE[[Vorhaben]:[Vorhaben]],AU75),2) -> 0 | AV47: =ROUND(SUMIFS(MitarbeiterFTE[[Stunden]:[Stunden]],MitarbeiterFTE[[Jahr]:[Jahr]],'FuE Vorhaben'!AV$45,MitarbeiterFTE[[Ausbildungsstatus]:[Ausbildungsstatus]],1,MitarbeiterFTE[[Vorhaben]:[Vorhaben]],AV75),2) -> 0 | AW47: =ROUND(SUMIFS(MitarbeiterFTE[[Stunden]:[Stunden]],MitarbeiterFTE[[Jahr]:[Jahr]],'FuE Vorhaben'!AW$45,MitarbeiterFTE[[Ausbildungsstatus]:[Ausbildungsstatus]],1,MitarbeiterFTE[[Vorhaben]:[Vorhaben]],AW75),2) -> 0 | BB47: MA techn. Ausbildung [Std.] | BC47: =ROUND(SUMIFS(MitarbeiterFTE[[Stunden]:[Stunden]],MitarbeiterFTE[[Jahr]:[Jahr]],'FuE Vorhaben'!BC$45,MitarbeiterFTE[[Ausbildungsstatus]:[Ausbildungsstatus]],1,MitarbeiterFTE[[Vorhaben]:[Vorhaben]],BC75),2) -> 0 | BD47: =ROUND(SUMIFS(MitarbeiterFTE[[Stunden]:[Stunden]],MitarbeiterFTE[[Jahr]:[Jahr]],'FuE Vorhaben'!BD$45,MitarbeiterFTE[[Ausbildungsstatus]:[Ausbildungsstatus]],1,MitarbeiterFTE[[Vorhaben]:[Vorhaben]],BD75),2) -> 0 | BE47: =ROUND(SUMIFS(MitarbeiterFTE[[Stunden]:[Stunden]],MitarbeiterFTE[[Jahr]:[Jahr]],'FuE Vorhaben'!BE$45,MitarbeiterFTE[[Ausbildungsstatus]:[Ausbildungsstatus]],1,MitarbeiterFTE[[Vorhaben]:[Vorhaben]],BE75),2) -> 0 | BF47: =ROUND(SUMIFS(MitarbeiterFTE[[Stunden]:[Stunden]],MitarbeiterFTE[[Jahr]:[Jahr]],'FuE Vorhaben'!BF$45,MitarbeiterFTE[[Ausbildungsstatus]:[Ausbildungsstatus]],1,MitarbeiterFTE[[Vorhaben]:[Vorhaben]],BF75),2) -> 0 | BG47: =ROUND(SUMIFS(MitarbeiterFTE[[Stunden]:[Stunden]],MitarbeiterFTE[[Jahr]:[Jahr]],'FuE Vorhaben'!BG$45,MitarbeiterFTE[[Ausbildungsstatus]:[Ausbildungsstatus]],1,MitarbeiterFTE[[Vorhaben]:[Vorhaben]],BG75),2) -> 0 | BH47: =ROUND(SUMIFS(MitarbeiterFTE[[Stunden]:[Stunden]],MitarbeiterFTE[[Jahr]:[Jahr]],'FuE Vorhaben'!BH$45,MitarbeiterFTE[[Ausbildungsstatus]:[Ausbildungsstatus]],1,MitarbeiterFTE[[Vorhaben]:[Vorhaben]],BH75),2) -> 0 | BI47: =ROUND(SUMIFS(MitarbeiterFTE[[Stunden]:[Stunden]],MitarbeiterFTE[[Jahr]:[Jahr]],'FuE Vorhaben'!BI$45,MitarbeiterFTE[[Ausbildungsstatus]:[Ausbildungsstatus]],1,MitarbeiterFTE[[Vorhaben]:[Vorhaben]],BI75),2) -> 0 | BJ47: =ROUND(SUMIFS(MitarbeiterFTE[[Stunden]:[Stunden]],MitarbeiterFTE[[Jahr]:[Jahr]],'FuE Vorhaben'!BJ$45,MitarbeiterFTE[[Ausbildungsstatus]:[Ausbildungsstatus]],1,MitarbeiterFTE[[Vorhaben]:[Vorhaben]],BJ75),2) -> 0 | BO47: MA techn. Ausbildung [Std.] | BP47: =ROUND(SUMIFS(MitarbeiterFTE[[Stunden]:[Stunden]],MitarbeiterFTE[[Jahr]:[Jahr]],'FuE Vorhaben'!BP$45,MitarbeiterFTE[[Ausbildungsstatus]:[Ausbildungsstatus]],1,MitarbeiterFTE[[Vorhaben]:[Vorhaben]],BP75),2) -> 0 | BQ47: =ROUND(SUMIFS(MitarbeiterFTE[[Stunden]:[Stunden]],MitarbeiterFTE[[Jahr]:[Jahr]],'FuE Vorhaben'!BQ$45,MitarbeiterFTE[[Ausbildungsstatus]:[Ausbildungsstatus]],1,MitarbeiterFTE[[Vorhaben]:[Vorhaben]],BQ75),2) -> 0 | BR47: =ROUND(SUMIFS(MitarbeiterFTE[[Stunden]:[Stunden]],MitarbeiterFTE[[Jahr]:[Jahr]],'FuE Vorhaben'!BR$45,MitarbeiterFTE[[Ausbildungsstatus]:[Ausbildungsstatus]],1,MitarbeiterFTE[[Vorhaben]:[Vorhaben]],BR75),2) -> 0 | BS47: =ROUND(SUMIFS(MitarbeiterFTE[[Stunden]:[Stunden]],MitarbeiterFTE[[Jahr]:[Jahr]],'FuE Vorhaben'!BS$45,MitarbeiterFTE[[Ausbildungsstatus]:[Ausbildungsstatus]],1,MitarbeiterFTE[[Vorhaben]:[Vorhaben]],BS75),2) -> 0 | BT47: =ROUND(SUMIFS(MitarbeiterFTE[[Stunden]:[Stunden]],MitarbeiterFTE[[Jahr]:[Jahr]],'FuE Vorhaben'!BT$45,MitarbeiterFTE[[Ausbildungsstatus]:[Ausbildungsstatus]],1,MitarbeiterFTE[[Vorhaben]:[Vorhaben]],BT75),2) -> 0 | BU47: =ROUND(SUMIFS(MitarbeiterFTE[[Stunden]:[Stunden]],MitarbeiterFTE[[Jahr]:[Jahr]],'FuE Vorhaben'!BU$45,MitarbeiterFTE[[Ausbildungsstatus]:[Ausbildungsstatus]],1,MitarbeiterFTE[[Vorhaben]:[Vorhaben]],BU75),2) -> 0 | BV47: =ROUND(SUMIFS(MitarbeiterFTE[[Stunden]:[Stunden]],MitarbeiterFTE[[Jahr]:[Jahr]],'FuE Vorhaben'!BV$45,MitarbeiterFTE[[Ausbildungsstatus]:[Ausbildungsstatus]],1,MitarbeiterFTE[[Vorhaben]:[Vorhaben]],BV75),2) -> 0 | BW47: =ROUND(SUMIFS(MitarbeiterFTE[[Stunden]:[Stunden]],MitarbeiterFTE[[Jahr]:[Jahr]],'FuE Vorhaben'!BW$45,MitarbeiterFTE[[Ausbildungsstatus]:[Ausbildungsstatus]],1,MitarbeiterFTE[[Vorhaben]:[Vorhaben]],BW75),2) -> 0 | CB47: MA techn. Ausbildung [Std.] | CC47: =ROUND(SUMIFS(MitarbeiterFTE[[Stunden]:[Stunden]],MitarbeiterFTE[[Jahr]:[Jahr]],'FuE Vorhaben'!CC$45,MitarbeiterFTE[[Ausbildungsstatus]:[Ausbildungsstatus]],1,MitarbeiterFTE[[Vorhaben]:[Vorhaben]],CC75),2) -> 0 | CD47: =ROUND(SUMIFS(MitarbeiterFTE[[Stunden]:[Stunden]],MitarbeiterFTE[[Jahr]:[Jahr]],'FuE Vorhaben'!CD$45,MitarbeiterFTE[[Ausbildungsstatus]:[Ausbildungsstatus]],1,MitarbeiterFTE[[Vorhaben]:[Vorhaben]],CD75),2) -> 0 | CE47: =ROUND(SUMIFS(MitarbeiterFTE[[Stunden]:[Stunden]],MitarbeiterFTE[[Jahr]:[Jahr]],'FuE Vorhaben'!CE$45,MitarbeiterFTE[[Ausbildungsstatus]:[Ausbildungsstatus]],1,MitarbeiterFTE[[Vorhaben]:[Vorhaben]],CE75),2) -> 0 | CF47: =ROUND(SUMIFS(MitarbeiterFTE[[Stunden]:[Stunden]],MitarbeiterFTE[[Jahr]:[Jahr]],'FuE Vorhaben'!CF$45,MitarbeiterFTE[[Ausbildungsstatus]:[Ausbildungsstatus]],1,MitarbeiterFTE[[Vorhaben]:[Vorhaben]],CF75),2) -> 0 | CG47: =ROUND(SUMIFS(MitarbeiterFTE[[Stunden]:[Stunden]],MitarbeiterFTE[[Jahr]:[Jahr]],'FuE Vorhaben'!CG$45,MitarbeiterFTE[[Ausbildungsstatus]:[Ausbildungsstatus]],1,MitarbeiterFTE[[Vorhaben]:[Vorhaben]],CG75),2) -> 0 | CH47: =ROUND(SUMIFS(MitarbeiterFTE[[Stunden]:[Stunden]],MitarbeiterFTE[[Jahr]:[Jahr]],'FuE Vorhaben'!CH$45,MitarbeiterFTE[[Ausbildungsstatus]:[Ausbildungsstatus]],1,MitarbeiterFTE[[Vorhaben]:[Vorhaben]],CH75),2) -> 0 | CI47: =ROUND(SUMIFS(MitarbeiterFTE[[Stunden]:[Stunden]],MitarbeiterFTE[[Jahr]:[Jahr]],'FuE Vorhaben'!CI$45,MitarbeiterFTE[[Ausbildungsstatus]:[Ausbildungsstatus]],1,MitarbeiterFTE[[Vorhaben]:[Vorhaben]],CI75),2) -> 0 | CJ47: =ROUND(SUMIFS(MitarbeiterFTE[[Stunden]:[Stunden]],MitarbeiterFTE[[Jahr]:[Jahr]],'FuE Vorhaben'!CJ$45,MitarbeiterFTE[[Ausbildungsstatus]:[Ausbildungsstatus]],1,MitarbeiterFTE[[Vorhaben]:[Vorhaben]],CJ75),2) -> 0
B48: MA mit sonstigem Abschluss [Std.] | C48: =ROUND(SUMIFS(MitarbeiterFTE[[Stunden]:[Stunden]],MitarbeiterFTE[[Jahr]:[Jahr]],'FuE Vorhaben'!C$45,MitarbeiterFTE[[Ausbildungsstatus]:[Ausbildungsstatus]],0,MitarbeiterFTE[[Vorhaben]:[Vorhaben]],C75),2) -> 0 | D48: =ROUND(SUMIFS(MitarbeiterFTE[[Stunden]:[Stunden]],MitarbeiterFTE[[Jahr]:[Jahr]],'FuE Vorhaben'!D$45,MitarbeiterFTE[[Ausbildungsstatus]:[Ausbildungsstatus]],0,MitarbeiterFTE[[Vorhaben]:[Vorhaben]],D75),2) -> 0 | E48: =ROUND(SUMIFS(MitarbeiterFTE[[Stunden]:[Stunden]],MitarbeiterFTE[[Jahr]:[Jahr]],'FuE Vorhaben'!E$45,MitarbeiterFTE[[Ausbildungsstatus]:[Ausbildungsstatus]],0,MitarbeiterFTE[[Vorhaben]:[Vorhaben]],E75),2) -> 0 | F48: =ROUND(SUMIFS(MitarbeiterFTE[[Stunden]:[Stunden]],MitarbeiterFTE[[Jahr]:[Jahr]],'FuE Vorhaben'!F$45,MitarbeiterFTE[[Ausbildungsstatus]:[Ausbildungsstatus]],0,MitarbeiterFTE[[Vorhaben]:[Vorhaben]],F75),2) -> 0 | G48: =ROUND(SUMIFS(MitarbeiterFTE[[Stunden]:[Stunden]],MitarbeiterFTE[[Jahr]:[Jahr]],'FuE Vorhaben'!G$45,MitarbeiterFTE[[Ausbildungsstatus]:[Ausbildungsstatus]],0,MitarbeiterFTE[[Vorhaben]:[Vorhaben]],G75),2) -> 0 | H48: =ROUND(SUMIFS(MitarbeiterFTE[[Stunden]:[Stunden]],MitarbeiterFTE[[Jahr]:[Jahr]],'FuE Vorhaben'!H$45,MitarbeiterFTE[[Ausbildungsstatus]:[Ausbildungsstatus]],0,MitarbeiterFTE[[Vorhaben]:[Vorhaben]],H75),2) -> 0 | I48: =ROUND(SUMIFS(MitarbeiterFTE[[Stunden]:[Stunden]],MitarbeiterFTE[[Jahr]:[Jahr]],'FuE Vorhaben'!I$45,MitarbeiterFTE[[Ausbildungsstatus]:[Ausbildungsstatus]],0,MitarbeiterFTE[[Vorhaben]:[Vorhaben]],I75),2) -> 0 | J48: =ROUND(SUMIFS(MitarbeiterFTE[[Stunden]:[Stunden]],MitarbeiterFTE[[Jahr]:[Jahr]],'FuE Vorhaben'!J$45,MitarbeiterFTE[[Ausbildungsstatus]:[Ausbildungsstatus]],0,MitarbeiterFTE[[Vorhaben]:[Vorhaben]],J75),2) -> 0 | O48: MA mit sonstigem Abschluss [Std.] | P48: =ROUND(SUMIFS(MitarbeiterFTE[[Stunden]:[Stunden]],MitarbeiterFTE[[Jahr]:[Jahr]],'FuE Vorhaben'!P$45,MitarbeiterFTE[[Ausbildungsstatus]:[Ausbildungsstatus]],0,MitarbeiterFTE[[Vorhaben]:[Vorhaben]],P75),2) -> 0 | Q48: =ROUND(SUMIFS(MitarbeiterFTE[[Stunden]:[Stunden]],MitarbeiterFTE[[Jahr]:[Jahr]],'FuE Vorhaben'!Q$45,MitarbeiterFTE[[Ausbildungsstatus]:[Ausbildungsstatus]],0,MitarbeiterFTE[[Vorhaben]:[Vorhaben]],Q75),2) -> 0 | R48: =ROUND(SUMIFS(MitarbeiterFTE[[Stunden]:[Stunden]],MitarbeiterFTE[[Jahr]:[Jahr]],'FuE Vorhaben'!R$45,MitarbeiterFTE[[Ausbildungsstatus]:[Ausbildungsstatus]],0,MitarbeiterFTE[[Vorhaben]:[Vorhaben]],R75),2) -> 0 | S48: =ROUND(SUMIFS(MitarbeiterFTE[[Stunden]:[Stunden]],MitarbeiterFTE[[Jahr]:[Jahr]],'FuE Vorhaben'!S$45,MitarbeiterFTE[[Ausbildungsstatus]:[Ausbildungsstatus]],0,MitarbeiterFTE[[Vorhaben]:[Vorhaben]],S75),2) -> 0 | T48: =ROUND(SUMIFS(MitarbeiterFTE[[Stunden]:[Stunden]],MitarbeiterFTE[[Jahr]:[Jahr]],'FuE Vorhaben'!T$45,MitarbeiterFTE[[Ausbildungsstatus]:[Ausbildungsstatus]],0,MitarbeiterFTE[[Vorhaben]:[Vorhaben]],T75),2) -> 0 | U48: =ROUND(SUMIFS(MitarbeiterFTE[[Stunden]:[Stunden]],MitarbeiterFTE[[Jahr]:[Jahr]],'FuE Vorhaben'!U$45,MitarbeiterFTE[[Ausbildungsstatus]:[Ausbildungsstatus]],0,MitarbeiterFTE[[Vorhaben]:[Vorhaben]],U75),2) -> 0 | V48: =ROUND(SUMIFS(MitarbeiterFTE[[Stunden]:[Stunden]],MitarbeiterFTE[[Jahr]:[Jahr]],'FuE Vorhaben'!V$45,MitarbeiterFTE[[Ausbildungsstatus]:[Ausbildungsstatus]],0,MitarbeiterFTE[[Vorhaben]:[Vorhaben]],V75),2) -> 0 | W48: =ROUND(SUMIFS(MitarbeiterFTE[[Stunden]:[Stunden]],MitarbeiterFTE[[Jahr]:[Jahr]],'FuE Vorhaben'!W$45,MitarbeiterFTE[[Ausbildungsstatus]:[Ausbildungsstatus]],0,MitarbeiterFTE[[Vorhaben]:[Vorhaben]],W75),2) -> 0 | AB48: MA mit sonstigem Abschluss [Std.] | AC48: =ROUND(SUMIFS(MitarbeiterFTE[[Stunden]:[Stunden]],MitarbeiterFTE[[Jahr]:[Jahr]],'FuE Vorhaben'!AC$45,MitarbeiterFTE[[Ausbildungsstatus]:[Ausbildungsstatus]],0,MitarbeiterFTE[[Vorhaben]:[Vorhaben]],AC75),2) -> 0 | AD48: =ROUND(SUMIFS(MitarbeiterFTE[[Stunden]:[Stunden]],MitarbeiterFTE[[Jahr]:[Jahr]],'FuE Vorhaben'!AD$45,MitarbeiterFTE[[Ausbildungsstatus]:[Ausbildungsstatus]],0,MitarbeiterFTE[[Vorhaben]:[Vorhaben]],AD75),2) -> 0 | AE48: =ROUND(SUMIFS(MitarbeiterFTE[[Stunden]:[Stunden]],MitarbeiterFTE[[Jahr]:[Jahr]],'FuE Vorhaben'!AE$45,MitarbeiterFTE[[Ausbildungsstatus]:[Ausbildungsstatus]],0,MitarbeiterFTE[[Vorhaben]:[Vorhaben]],AE75),2) -> 0 | AF48: =ROUND(SUMIFS(MitarbeiterFTE[[Stunden]:[Stunden]],MitarbeiterFTE[[Jahr]:[Jahr]],'FuE Vorhaben'!AF$45,MitarbeiterFTE[[Ausbildungsstatus]:[Ausbildungsstatus]],0,MitarbeiterFTE[[Vorhaben]:[Vorhaben]],AF75),2) -> 0 | AG48: =ROUND(SUMIFS(MitarbeiterFTE[[Stunden]:[Stunden]],MitarbeiterFTE[[Jahr]:[Jahr]],'FuE Vorhaben'!AG$45,MitarbeiterFTE[[Ausbildungsstatus]:[Ausbildungsstatus]],0,MitarbeiterFTE[[Vorhaben]:[Vorhaben]],AG75),2) -> 0 | AH48: =ROUND(SUMIFS(MitarbeiterFTE[[Stunden]:[Stunden]],MitarbeiterFTE[[Jahr]:[Jahr]],'FuE Vorhaben'!AH$45,MitarbeiterFTE[[Ausbildungsstatus]:[Ausbildungsstatus]],0,MitarbeiterFTE[[Vorhaben]:[Vorhaben]],AH75),2) -> 0 | AI48: =ROUND(SUMIFS(MitarbeiterFTE[[Stunden]:[Stunden]],MitarbeiterFTE[[Jahr]:[Jahr]],'FuE Vorhaben'!AI$45,MitarbeiterFTE[[Ausbildungsstatus]:[Ausbildungsstatus]],0,MitarbeiterFTE[[Vorhaben]:[Vorhaben]],AI75),2) -> 0 | AJ48: =ROUND(SUMIFS(MitarbeiterFTE[[Stunden]:[Stunden]],MitarbeiterFTE[[Jahr]:[Jahr]],'FuE Vorhaben'!AJ$45,MitarbeiterFTE[[Ausbildungsstatus]:[Ausbildungsstatus]],0,MitarbeiterFTE[[Vorhaben]:[Vorhaben]],AJ75),2) -> 0 | AO48: MA mit sonstigem Abschluss [Std.] | AP48: =ROUND(SUMIFS(MitarbeiterFTE[[Stunden]:[Stunden]],MitarbeiterFTE[[Jahr]:[Jahr]],'FuE Vorhaben'!AP$45,MitarbeiterFTE[[Ausbildungsstatus]:[Ausbildungsstatus]],0,MitarbeiterFTE[[Vorhaben]:[Vorhaben]],AP75),2) -> 0 | AQ48: =ROUND(SUMIFS(MitarbeiterFTE[[Stunden]:[Stunden]],MitarbeiterFTE[[Jahr]:[Jahr]],'FuE Vorhaben'!AQ$45,MitarbeiterFTE[[Ausbildungsstatus]:[Ausbildungsstatus]],0,MitarbeiterFTE[[Vorhaben]:[Vorhaben]],AQ75),2) -> 0 | AR48: =ROUND(SUMIFS(MitarbeiterFTE[[Stunden]:[Stunden]],MitarbeiterFTE[[Jahr]:[Jahr]],'FuE Vorhaben'!AR$45,MitarbeiterFTE[[Ausbildungsstatus]:[Ausbildungsstatus]],0,MitarbeiterFTE[[Vorhaben]:[Vorhaben]],AR75),2) -> 0 | AS48: =ROUND(SUMIFS(MitarbeiterFTE[[Stunden]:[Stunden]],MitarbeiterFTE[[Jahr]:[Jahr]],'FuE Vorhaben'!AS$45,MitarbeiterFTE[[Ausbildungsstatus]:[Ausbildungsstatus]],0,MitarbeiterFTE[[Vorhaben]:[Vorhaben]],AS75),2) -> 0 | AT48: =ROUND(SUMIFS(MitarbeiterFTE[[Stunden]:[Stunden]],MitarbeiterFTE[[Jahr]:[Jahr]],'FuE Vorhaben'!AT$45,MitarbeiterFTE[[Ausbildungsstatus]:[Ausbildungsstatus]],0,MitarbeiterFTE[[Vorhaben]:[Vorhaben]],AT75),2) -> 0 | AU48: =ROUND(SUMIFS(MitarbeiterFTE[[Stunden]:[Stunden]],MitarbeiterFTE[[Jahr]:[Jahr]],'FuE Vorhaben'!AU$45,MitarbeiterFTE[[Ausbildungsstatus]:[Ausbildungsstatus]],0,MitarbeiterFTE[[Vorhaben]:[Vorhaben]],AU75),2) -> 0 | AV48: =ROUND(SUMIFS(MitarbeiterFTE[[Stunden]:[Stunden]],MitarbeiterFTE[[Jahr]:[Jahr]],'FuE Vorhaben'!AV$45,MitarbeiterFTE[[Ausbildungsstatus]:[Ausbildungsstatus]],0,MitarbeiterFTE[[Vorhaben]:[Vorhaben]],AV75),2) -> 0 | AW48: =ROUND(SUMIFS(MitarbeiterFTE[[Stunden]:[Stunden]],MitarbeiterFTE[[Jahr]:[Jahr]],'FuE Vorhaben'!AW$45,MitarbeiterFTE[[Ausbildungsstatus]:[Ausbildungsstatus]],0,MitarbeiterFTE[[Vorhaben]:[Vorhaben]],AW75),2) -> 0 | BB48: MA mit sonstigem Abschluss [Std.] | BC48: =ROUND(SUMIFS(MitarbeiterFTE[[Stunden]:[Stunden]],MitarbeiterFTE[[Jahr]:[Jahr]],'FuE Vorhaben'!BC$45,MitarbeiterFTE[[Ausbildungsstatus]:[Ausbildungsstatus]],0,MitarbeiterFTE[[Vorhaben]:[Vorhaben]],BC75),2) -> 0 | BD48: =ROUND(SUMIFS(MitarbeiterFTE[[Stunden]:[Stunden]],MitarbeiterFTE[[Jahr]:[Jahr]],'FuE Vorhaben'!BD$45,MitarbeiterFTE[[Ausbildungsstatus]:[Ausbildungsstatus]],0,MitarbeiterFTE[[Vorhaben]:[Vorhaben]],BD75),2) -> 0 | BE48: =ROUND(SUMIFS(MitarbeiterFTE[[Stunden]:[Stunden]],MitarbeiterFTE[[Jahr]:[Jahr]],'FuE Vorhaben'!BE$45,MitarbeiterFTE[[Ausbildungsstatus]:[Ausbildungsstatus]],0,MitarbeiterFTE[[Vorhaben]:[Vorhaben]],BE75),2) -> 0 | BF48: =ROUND(SUMIFS(MitarbeiterFTE[[Stunden]:[Stunden]],MitarbeiterFTE[[Jahr]:[Jahr]],'FuE Vorhaben'!BF$45,MitarbeiterFTE[[Ausbildungsstatus]:[Ausbildungsstatus]],0,MitarbeiterFTE[[Vorhaben]:[Vorhaben]],BF75),2) -> 0 | BG48: =ROUND(SUMIFS(MitarbeiterFTE[[Stunden]:[Stunden]],MitarbeiterFTE[[Jahr]:[Jahr]],'FuE Vorhaben'!BG$45,MitarbeiterFTE[[Ausbildungsstatus]:[Ausbildungsstatus]],0,MitarbeiterFTE[[Vorhaben]:[Vorhaben]],BG75),2) -> 0 | BH48: =ROUND(SUMIFS(MitarbeiterFTE[[Stunden]:[Stunden]],MitarbeiterFTE[[Jahr]:[Jahr]],'FuE Vorhaben'!BH$45,MitarbeiterFTE[[Ausbildungsstatus]:[Ausbildungsstatus]],0,MitarbeiterFTE[[Vorhaben]:[Vorhaben]],BH75),2) -> 0 | BI48: =ROUND(SUMIFS(MitarbeiterFTE[[Stunden]:[Stunden]],MitarbeiterFTE[[Jahr]:[Jahr]],'FuE Vorhaben'!BI$45,MitarbeiterFTE[[Ausbildungsstatus]:[Ausbildungsstatus]],0,MitarbeiterFTE[[Vorhaben]:[Vorhaben]],BI75),2) -> 0 | BJ48: =ROUND(SUMIFS(MitarbeiterFTE[[Stunden]:[Stunden]],MitarbeiterFTE[[Jahr]:[Jahr]],'FuE Vorhaben'!BJ$45,MitarbeiterFTE[[Ausbildungsstatus]:[Ausbildungsstatus]],0,MitarbeiterFTE[[Vorhaben]:[Vorhaben]],BJ75),2) -> 0 | BO48: MA mit sonstigem Abschluss [Std.] | BP48: =ROUND(SUMIFS(MitarbeiterFTE[[Stunden]:[Stunden]],MitarbeiterFTE[[Jahr]:[Jahr]],'FuE Vorhaben'!BP$45,MitarbeiterFTE[[Ausbildungsstatus]:[Ausbildungsstatus]],0,MitarbeiterFTE[[Vorhaben]:[Vorhaben]],BP75),2) -> 0 | BQ48: =ROUND(SUMIFS(MitarbeiterFTE[[Stunden]:[Stunden]],MitarbeiterFTE[[Jahr]:[Jahr]],'FuE Vorhaben'!BQ$45,MitarbeiterFTE[[Ausbildungsstatus]:[Ausbildungsstatus]],0,MitarbeiterFTE[[Vorhaben]:[Vorhaben]],BQ75),2) -> 0 | BR48: =ROUND(SUMIFS(MitarbeiterFTE[[Stunden]:[Stunden]],MitarbeiterFTE[[Jahr]:[Jahr]],'FuE Vorhaben'!BR$45,MitarbeiterFTE[[Ausbildungsstatus]:[Ausbildungsstatus]],0,MitarbeiterFTE[[Vorhaben]:[Vorhaben]],BR75),2) -> 0 | BS48: =ROUND(SUMIFS(MitarbeiterFTE[[Stunden]:[Stunden]],MitarbeiterFTE[[Jahr]:[Jahr]],'FuE Vorhaben'!BS$45,MitarbeiterFTE[[Ausbildungsstatus]:[Ausbildungsstatus]],0,MitarbeiterFTE[[Vorhaben]:[Vorhaben]],BS75),2) -> 0 | BT48: =ROUND(SUMIFS(MitarbeiterFTE[[Stunden]:[Stunden]],MitarbeiterFTE[[Jahr]:[Jahr]],'FuE Vorhaben'!BT$45,MitarbeiterFTE[[Ausbildungsstatus]:[Ausbildungsstatus]],0,MitarbeiterFTE[[Vorhaben]:[Vorhaben]],BT75),2) -> 0 | BU48: =ROUND(SUMIFS(MitarbeiterFTE[[Stunden]:[Stunden]],MitarbeiterFTE[[Jahr]:[Jahr]],'FuE Vorhaben'!BU$45,MitarbeiterFTE[[Ausbildungsstatus]:[Ausbildungsstatus]],0,MitarbeiterFTE[[Vorhaben]:[Vorhaben]],BU75),2) -> 0 | BV48: =ROUND(SUMIFS(MitarbeiterFTE[[Stunden]:[Stunden]],MitarbeiterFTE[[Jahr]:[Jahr]],'FuE Vorhaben'!BV$45,MitarbeiterFTE[[Ausbildungsstatus]:[Ausbildungsstatus]],0,MitarbeiterFTE[[Vorhaben]:[Vorhaben]],BV75),2) -> 0 | BW48: =ROUND(SUMIFS(MitarbeiterFTE[[Stunden]:[Stunden]],MitarbeiterFTE[[Jahr]:[Jahr]],'FuE Vorhaben'!BW$45,MitarbeiterFTE[[Ausbildungsstatus]:[Ausbildungsstatus]],0,MitarbeiterFTE[[Vorhaben]:[Vorhaben]],BW75),2) -> 0 | CB48: MA mit sonstigem Abschluss [Std.] | CC48: =ROUND(SUMIFS(MitarbeiterFTE[[Stunden]:[Stunden]],MitarbeiterFTE[[Jahr]:[Jahr]],'FuE Vorhaben'!CC$45,MitarbeiterFTE[[Ausbildungsstatus]:[Ausbildungsstatus]],0,MitarbeiterFTE[[Vorhaben]:[Vorhaben]],CC75),2) -> 0 | CD48: =ROUND(SUMIFS(MitarbeiterFTE[[Stunden]:[Stunden]],MitarbeiterFTE[[Jahr]:[Jahr]],'FuE Vorhaben'!CD$45,MitarbeiterFTE[[Ausbildungsstatus]:[Ausbildungsstatus]],0,MitarbeiterFTE[[Vorhaben]:[Vorhaben]],CD75),2) -> 0 | CE48: =ROUND(SUMIFS(MitarbeiterFTE[[Stunden]:[Stunden]],MitarbeiterFTE[[Jahr]:[Jahr]],'FuE Vorhaben'!CE$45,MitarbeiterFTE[[Ausbildungsstatus]:[Ausbildungsstatus]],0,MitarbeiterFTE[[Vorhaben]:[Vorhaben]],CE75),2) -> 0 | CF48: =ROUND(SUMIFS(MitarbeiterFTE[[Stunden]:[Stunden]],MitarbeiterFTE[[Jahr]:[Jahr]],'FuE Vorhaben'!CF$45,MitarbeiterFTE[[Ausbildungsstatus]:[Ausbildungsstatus]],0,MitarbeiterFTE[[Vorhaben]:[Vorhaben]],CF75),2) -> 0 | CG48: =ROUND(SUMIFS(MitarbeiterFTE[[Stunden]:[Stunden]],MitarbeiterFTE[[Jahr]:[Jahr]],'FuE Vorhaben'!CG$45,MitarbeiterFTE[[Ausbildungsstatus]:[Ausbildungsstatus]],0,MitarbeiterFTE[[Vorhaben]:[Vorhaben]],CG75),2) -> 0 | CH48: =ROUND(SUMIFS(MitarbeiterFTE[[Stunden]:[Stunden]],MitarbeiterFTE[[Jahr]:[Jahr]],'FuE Vorhaben'!CH$45,MitarbeiterFTE[[Ausbildungsstatus]:[Ausbildungsstatus]],0,MitarbeiterFTE[[Vorhaben]:[Vorhaben]],CH75),2) -> 0 | CI48: =ROUND(SUMIFS(MitarbeiterFTE[[Stunden]:[Stunden]],MitarbeiterFTE[[Jahr]:[Jahr]],'FuE Vorhaben'!CI$45,MitarbeiterFTE[[Ausbildungsstatus]:[Ausbildungsstatus]],0,MitarbeiterFTE[[Vorhaben]:[Vorhaben]],CI75),2) -> 0 | CJ48: =ROUND(SUMIFS(MitarbeiterFTE[[Stunden]:[Stunden]],MitarbeiterFTE[[Jahr]:[Jahr]],'FuE Vorhaben'!CJ$45,MitarbeiterFTE[[Ausbildungsstatus]:[Ausbildungsstatus]],0,MitarbeiterFTE[[Vorhaben]:[Vorhaben]],CJ75),2) -> 0
B49: =LEFT(B46,LEN(B46)-6) & "[PM]" -> MA mit Hochschulabschluss [PM] | C49: =C46/142 -> 0 | D49: =D46/142 -> 0 | E49: =E46/142 -> 0 | F49: =F46/142 -> 0 | G49: =G46/142 -> 0.82964789 | H49: =H46/142 -> 2.3988732 | I49: =I46/142 -> 4.7076056 | J49: =J46/142 -> 0 | O49: =LEFT(O46,LEN(O46)-6) & "[PM]" -> MA mit Hochschulabschluss [PM] | P49: =P46/142 -> 0 | Q49: =Q46/142 -> 0 | R49: =R46/142 -> 0 | S49: =S46/142 -> 0 | T49: =T46/142 -> 0 | U49: =U46/142 -> 0 | V49: =V46/142 -> 0 | W49: =W46/142 -> 0 | AB49: =LEFT(AB46,LEN(AB46)-6) & "[PM]" -> MA mit Hochschulabschluss [PM] | AC49: =AC46/142 -> 0 | AD49: =AD46/142 -> 0 | AE49: =AE46/142 -> 0 | AF49: =AF46/142 -> 0 | AG49: =AG46/142 -> 0 | AH49: =AH46/142 -> 0 | AI49: =AI46/142 -> 0 | AJ49: =AJ46/142 -> 0 | AO49: =LEFT(AO46,LEN(AO46)-6) & "[PM]" -> MA mit Hochschulabschluss [PM] | AP49: =AP46/142 -> 0 | AQ49: =AQ46/142 -> 0 | AR49: =AR46/142 -> 0 | AS49: =AS46/142 -> 0 | AT49: =AT46/142 -> 0 | AU49: =AU46/142 -> 0 | AV49: =AV46/142 -> 0 | AW49: =AW46/142 -> 0 | BB49: =LEFT(BB46,LEN(BB46)-6) & "[PM]" -> MA mit Hochschulabschluss [PM] | BC49: =BC46/142 -> 0 | BD49: =BD46/142 -> 0 | BE49: =BE46/142 -> 0 | BF49: =BF46/142 -> 0 | BG49: =BG46/142 -> 0 | BH49: =BH46/142 -> 0 | BI49: =BI46/142 -> 0 | BJ49: =BJ46/142 -> 0 | BO49: =LEFT(BO46,LEN(BO46)-6) & "[PM]" -> MA mit Hochschulabschluss [PM] | BP49: =BP46/142 -> 0 | BQ49: =BQ46/142 -> 0 | BR49: =BR46/142 -> 0 | BS49: =BS46/142 -> 0 | BT49: =BT46/142 -> 0 | BU49: =BU46/142 -> 0 | BV49: =BV46/142 -> 0 | BW49: =BW46/142 -> 0 | CB49: =LEFT(CB46,LEN(CB46)-6) & "[PM]" -> MA mit Hochschulabschluss [PM] | CC49: =CC46/142 -> 0 | CD49: =CD46/142 -> 0 | CE49: =CE46/142 -> 0 | CF49: =CF46/142 -> 0 | CG49: =CG46/142 -> 0 | CH49: =CH46/142 -> 0 | CI49: =CI46/142 -> 0 | CJ49: =CJ46/142 -> 0
B50: =LEFT(B47,LEN(B47)-6) & "[PM]" -> MA techn. Ausbildung [PM] | C50: =C47/142 -> 0 | D50: =D47/142 -> 0 | E50: =E47/142 -> 0 | F50: =F47/142 -> 0 | G50: =G47/142 -> 0 | H50: =H47/142 -> 0 | I50: =I47/142 -> 0 | J50: =J47/142 -> 0 | O50: =LEFT(O47,LEN(O47)-6) & "[PM]" -> MA techn. Ausbildung [PM] | P50: =P47/142 -> 0 | Q50: =Q47/142 -> 0 | R50: =R47/142 -> 0 | S50: =S47/142 -> 0 | T50: =T47/142 -> 0 | U50: =U47/142 -> 0 | V50: =V47/142 -> 0 | W50: =W47/142 -> 0 | AB50: =LEFT(AB47,LEN(AB47)-6) & "[PM]" -> MA techn. Ausbildung [PM] | AC50: =AC47/142 -> 0 | AD50: =AD47/142 -> 0 | AE50: =AE47/142 -> 0 | AF50: =AF47/142 -> 0 | AG50: =AG47/142 -> 0 | AH50: =AH47/142 -> 0 | AI50: =AI47/142 -> 0 | AJ50: =AJ47/142 -> 0 | AO50: =LEFT(AO47,LEN(AO47)-6) & "[PM]" -> MA techn. Ausbildung [PM] | AP50: =AP47/142 -> 0 | AQ50: =AQ47/142 -> 0 | AR50: =AR47/142 -> 0 | AS50: =AS47/142 -> 0 | AT50: =AT47/142 -> 0 | AU50: =AU47/142 -> 0 | AV50: =AV47/142 -> 0 | AW50: =AW47/142 -> 0 | BB50: =LEFT(BB47,LEN(BB47)-6) & "[PM]" -> MA techn. Ausbildung [PM] | BC50: =BC47/142 -> 0 | BD50: =BD47/142 -> 0 | BE50: =BE47/142 -> 0 | BF50: =BF47/142 -> 0 | BG50: =BG47/142 -> 0 | BH50: =BH47/142 -> 0 | BI50: =BI47/142 -> 0 | BJ50: =BJ47/142 -> 0 | BO50: =LEFT(BO47,LEN(BO47)-6) & "[PM]" -> MA techn. Ausbildung [PM] | BP50: =BP47/142 -> 0 | BQ50: =BQ47/142 -> 0 | BR50: =BR47/142 -> 0 | BS50: =BS47/142 -> 0 | BT50: =BT47/142 -> 0 | BU50: =BU47/142 -> 0 | BV50: =BV47/142 -> 0 | BW50: =BW47/142 -> 0 | CB50: =LEFT(CB47,LEN(CB47)-6) & "[PM]" -> MA techn. Ausbildung [PM] | CC50: =CC47/142 -> 0 | CD50: =CD47/142 -> 0 | CE50: =CE47/142 -> 0 | CF50: =CF47/142 -> 0 | CG50: =CG47/142 -> 0 | CH50: =CH47/142 -> 0 | CI50: =CI47/142 -> 0 | CJ50: =CJ47/142 -> 0
B51: =LEFT(B48,LEN(B48)-6) & "[PM]" -> MA mit sonstigem Abschluss [PM] | C51: =C48/142 -> 0 | D51: =D48/142 -> 0 | E51: =E48/142 -> 0 | F51: =F48/142 -> 0 | G51: =G48/142 -> 0 | H51: =H48/142 -> 0 | I51: =I48/142 -> 0 | J51: =J48/142 -> 0 | O51: =LEFT(O48,LEN(O48)-6) & "[PM]" -> MA mit sonstigem Abschluss [PM] | P51: =P48/142 -> 0 | Q51: =Q48/142 -> 0 | R51: =R48/142 -> 0 | S51: =S48/142 -> 0 | T51: =T48/142 -> 0 | U51: =U48/142 -> 0 | V51: =V48/142 -> 0 | W51: =W48/142 -> 0 | AB51: =LEFT(AB48,LEN(AB48)-6) & "[PM]" -> MA mit sonstigem Abschluss [PM] | AC51: =AC48/142 -> 0 | AD51: =AD48/142 -> 0 | AE51: =AE48/142 -> 0 | AF51: =AF48/142 -> 0 | AG51: =AG48/142 -> 0 | AH51: =AH48/142 -> 0 | AI51: =AI48/142 -> 0 | AJ51: =AJ48/142 -> 0 | AO51: =LEFT(AO48,LEN(AO48)-6) & "[PM]" -> MA mit sonstigem Abschluss [PM] | AP51: =AP48/142 -> 0 | AQ51: =AQ48/142 -> 0 | AR51: =AR48/142 -> 0 | AS51: =AS48/142 -> 0 | AT51: =AT48/142 -> 0 | AU51: =AU48/142 -> 0 | AV51: =AV48/142 -> 0 | AW51: =AW48/142 -> 0 | BB51: =LEFT(BB48,LEN(BB48)-6) & "[PM]" -> MA mit sonstigem Abschluss [PM] | BC51: =BC48/142 -> 0 | BD51: =BD48/142 -> 0 | BE51: =BE48/142 -> 0 | BF51: =BF48/142 -> 0 | BG51: =BG48/142 -> 0 | BH51: =BH48/142 -> 0 | BI51: =BI48/142 -> 0 | BJ51: =BJ48/142 -> 0 | BO51: =LEFT(BO48,LEN(BO48)-6) & "[PM]" -> MA mit sonstigem Abschluss [PM] | BP51: =BP48/142 -> 0 | BQ51: =BQ48/142 -> 0 | BR51: =BR48/142 -> 0 | BS51: =BS48/142 -> 0 | BT51: =BT48/142 -> 0 | BU51: =BU48/142 -> 0 | BV51: =BV48/142 -> 0 | BW51: =BW48/142 -> 0 | CB51: =LEFT(CB48,LEN(CB48)-6) & "[PM]" -> MA mit sonstigem Abschluss [PM] | CC51: =CC48/142 -> 0 | CD51: =CD48/142 -> 0 | CE51: =CE48/142 -> 0 | CF51: =CF48/142 -> 0 | CG51: =CG48/142 -> 0 | CH51: =CH48/142 -> 0 | CI51: =CI48/142 -> 0 | CJ51: =CJ48/142 -> 0
C52: =_xlfn.LET( _xlpm.vorhabenStartDatum,C7, _xlpm.vorhabenEndDatum,C8,_xlpm.stundenAmVorhaben,SUM(C46:C48), _xlpm.startDatum,IF(YEAR(_xlpm.vorhabenStartDatum)=C45,_xlpm.vorhabenStartDatum,DATE(C45,1,1)), _xlpm.endDatum,IF(YEAR(_xlpm.vorhabenEndDatum)=C45,_xlpm.vorhabenEndDatum,DATE(C45,12,31)), _xlpm.arbeitstageImJahr,NETWORKDAYS(_xlpm.startDatum,_xlpm.endDatum), _xlpm.out,ROUND(_xlpm.stundenAmVorhaben/(_xlpm.arbeitstageImJahr*8),2), IF(C9,_xlpm.out,0)) -> 0 | D52: =_xlfn.LET( _xlpm.vorhabenStartDatum,C7, _xlpm.vorhabenEndDatum,C8, _xlpm.stundenAmVorhaben,SUM(D46:D48), _xlpm.startDatum,IF(YEAR(_xlpm.vorhabenStartDatum)=D45,_xlpm.vorhabenStartDatum,DATE(D45,1,1)), _xlpm.endDatum,IF(YEAR(_xlpm.vorhabenEndDatum)=D45,_xlpm.vorhabenEndDatum,DATE(D45,12,31)), _xlpm.arbeitstageImJahr,NETWORKDAYS(_xlpm.startDatum,_xlpm.endDatum), _xlpm.out,ROUND(_xlpm.stundenAmVorhaben/(_xlpm.arbeitstageImJahr*8),2), IF(D9,_xlpm.out,0)) -> 0 | E52: =_xlfn.LET( _xlpm.vorhabenStartDatum,C7, _xlpm.vorhabenEndDatum,C8, _xlpm.stundenAmVorhaben,SUM(E46:E48), _xlpm.startDatum,IF(YEAR(_xlpm.vorhabenStartDatum)=E45,_xlpm.vorhabenStartDatum,DATE(E45,1,1)), _xlpm.endDatum,IF(YEAR(_xlpm.vorhabenEndDatum)=E45,_xlpm.vorhabenEndDatum,DATE(E45,12,31)), _xlpm.arbeitstageImJahr,NETWORKDAYS(_xlpm.startDatum,_xlpm.endDatum), _xlpm.out,ROUND(_xlpm.stundenAmVorhaben/(_xlpm.arbeitstageImJahr*8),2), IF(E9,_xlpm.out,0)) -> 0 | F52: =_xlfn.LET( _xlpm.vorhabenStartDatum,C7, _xlpm.vorhabenEndDatum,C8, _xlpm.stundenAmVorhaben,SUM(F46:F48), _xlpm.startDatum,IF(YEAR(_xlpm.vorhabenStartDatum)=F45,_xlpm.vorhabenStartDatum,DATE(F45,1,1)), _xlpm.endDatum,IF(YEAR(_xlpm.vorhabenEndDatum)=F45,_xlpm.vorhabenEndDatum,DATE(F45,12,31)), _xlpm.arbeitstageImJahr,NETWORKDAYS(_xlpm.startDatum,_xlpm.endDatum), _xlpm.out,ROUND(_xlpm.stundenAmVorhaben/(_xlpm.arbeitstageImJahr*8),2), IF(F9,_xlpm.out,0)) -> 0 | G52: =_xlfn.LET( _xlpm.vorhabenStartDatum,C7, _xlpm.vorhabenEndDatum,C8, _xlpm.stundenAmVorhaben,SUM(G46:G48), _xlpm.startDatum,IF(YEAR(_xlpm.vorhabenStartDatum)=G45,_xlpm.vorhabenStartDatum,DATE(G45,1,1)), _xlpm.endDatum,IF(YEAR(_xlpm.vorhabenEndDatum)=G45,_xlpm.vorhabenEndDatum,DATE(G45,12,31)), _xlpm.arbeitstageImJahr,NETWORKDAYS(_xlpm.startDatum,_xlpm.endDatum), _xlpm.out,ROUND(_xlpm.stundenAmVorhaben/(_xlpm.arbeitstageImJahr*8),2), IF(G9,_xlpm.out,0)) -> 0.06 | H52: =_xlfn.LET( _xlpm.vorhabenStartDatum,D7, _xlpm.vorhabenEndDatum,D8, _xlpm.stundenAmVorhaben,SUM(H46:H48), _xlpm.startDatum,IF(YEAR(_xlpm.vorhabenStartDatum)=H45,_xlpm.vorhabenStartDatum,DATE(H45,1,1)), _xlpm.endDatum,IF(YEAR(_xlpm.vorhabenEndDatum)=H45,_xlpm.vorhabenEndDatum,DATE(H45,12,31)), _xlpm.arbeitstageImJahr,NETWORKDAYS(_xlpm.startDatum,_xlpm.endDatum), _xlpm.out,ROUND(_xlpm.stundenAmVorhaben/(_xlpm.arbeitstageImJahr*8),2), IF(H9,_xlpm.out,0)) -> 0.16 | I52: =_xlfn.LET( _xlpm.vorhabenStartDatum,E7, _xlpm.vorhabenEndDatum,E8, _xlpm.stundenAmVorhaben,SUM(I46:I48), _xlpm.startDatum,IF(YEAR(_xlpm.vorhabenStartDatum)=I45,_xlpm.vorhabenStartDatum,DATE(I45,1,1)), _xlpm.endDatum,IF(YEAR(_xlpm.vorhabenEndDatum)=I45,_xlpm.vorhabenEndDatum,DATE(I45,12,31)), _xlpm.arbeitstageImJahr,NETWORKDAYS(_xlpm.startDatum,_xlpm.endDatum), _xlpm.out,ROUND(_xlpm.stundenAmVorhaben/(_xlpm.arbeitstageImJahr*8),2), IF(I9,_xlpm.out,0)) -> 0.32 | J52: =_xlfn.LET( _xlpm.vorhabenStartDatum,F7, _xlpm.vorhabenEndDatum,F8, _xlpm.stundenAmVorhaben,SUM(J46:J48), _xlpm.startDatum,IF(YEAR(_xlpm.vorhabenStartDatum)=J45,_xlpm.vorhabenStartDatum,DATE(J45,1,1)), _xlpm.endDatum,IF(YEAR(_xlpm.vorhabenEndDatum)=J45,_xlpm.vorhabenEndDatum,DATE(J45,12,31)), _xlpm.arbeitstageImJahr,NETWORKDAYS(_xlpm.startDatum,_xlpm.endDatum), _xlpm.out,ROUND(_xlpm.stundenAmVorhaben/(_xlpm.arbeitstageImJahr*8),2), IF(J9,_xlpm.out,0)) -> 0 | P52: =_xlfn.LET( _xlpm.vorhabenStartDatum,P7, _xlpm.vorhabenEndDatum,P8,_xlpm.stundenAmVorhaben,SUM(P46:P48), _xlpm.startDatum,IF(YEAR(_xlpm.vorhabenStartDatum)=P45,_xlpm.vorhabenStartDatum,DATE(P45,1,1)), _xlpm.endDatum,IF(YEAR(_xlpm.vorhabenEndDatum)=P45,_xlpm.vorhabenEndDatum,DATE(P45,12,31)), _xlpm.arbeitstageImJahr,NETWORKDAYS(_xlpm.startDatum,_xlpm.endDatum), _xlpm.out,ROUND(_xlpm.stundenAmVorhaben/(_xlpm.arbeitstageImJahr*8),2), IF(P9,_xlpm.out,0)) -> 0 | Q52: =_xlfn.LET( _xlpm.vorhabenStartDatum,P7, _xlpm.vorhabenEndDatum,P8, _xlpm.stundenAmVorhaben,SUM(Q46:Q48), _xlpm.startDatum,IF(YEAR(_xlpm.vorhabenStartDatum)=Q45,_xlpm.vorhabenStartDatum,DATE(Q45,1,1)), _xlpm.endDatum,IF(YEAR(_xlpm.vorhabenEndDatum)=Q45,_xlpm.vorhabenEndDatum,DATE(Q45,12,31)), _xlpm.arbeitstageImJahr,NETWORKDAYS(_xlpm.startDatum,_xlpm.endDatum), _xlpm.out,ROUND(_xlpm.stundenAmVorhaben/(_xlpm.arbeitstageImJahr*8),2), IF(Q9,_xlpm.out,0)) -> 0 | R52: =_xlfn.LET( _xlpm.vorhabenStartDatum,P7, _xlpm.vorhabenEndDatum,P8, _xlpm.stundenAmVorhaben,SUM(R46:R48), _xlpm.startDatum,IF(YEAR(_xlpm.vorhabenStartDatum)=R45,_xlpm.vorhabenStartDatum,DATE(R45,1,1)), _xlpm.endDatum,IF(YEAR(_xlpm.vorhabenEndDatum)=R45,_xlpm.vorhabenEndDatum,DATE(R45,12,31)), _xlpm.arbeitstageImJahr,NETWORKDAYS(_xlpm.startDatum,_xlpm.endDatum), _xlpm.out,ROUND(_xlpm.stundenAmVorhaben/(_xlpm.arbeitstageImJahr*8),2), IF(R9,_xlpm.out,0)) -> 0 | S52: =_xlfn.LET( _xlpm.vorhabenStartDatum,P7, _xlpm.vorhabenEndDatum,P8, _xlpm.stundenAmVorhaben,SUM(S46:S48), _xlpm.startDatum,IF(YEAR(_xlpm.vorhabenStartDatum)=S45,_xlpm.vorhabenStartDatum,DATE(S45,1,1)), _xlpm.endDatum,IF(YEAR(_xlpm.vorhabenEndDatum)=S45,_xlpm.vorhabenEndDatum,DATE(S45,12,31)), _xlpm.arbeitstageImJahr,NETWORKDAYS(_xlpm.startDatum,_xlpm.endDatum), _xlpm.out,ROUND(_xlpm.stundenAmVorhaben/(_xlpm.arbeitstageImJahr*8),2), IF(S9,_xlpm.out,0)) -> 0 | T52: =_xlfn.LET( _xlpm.vorhabenStartDatum,P7, _xlpm.vorhabenEndDatum,P8, _xlpm.stundenAmVorhaben,SUM(T46:T48), _xlpm.startDatum,IF(YEAR(_xlpm.vorhabenStartDatum)=T45,_xlpm.vorhabenStartDatum,DATE(T45,1,1)), _xlpm.endDatum,IF(YEAR(_xlpm.vorhabenEndDatum)=T45,_xlpm.vorhabenEndDatum,DATE(T45,12,31)), _xlpm.arbeitstageImJahr,NETWORKDAYS(_xlpm.startDatum,_xlpm.endDatum), _xlpm.out,ROUND(_xlpm.stundenAmVorhaben/(_xlpm.arbeitstageImJahr*8),2), IF(T9,_xlpm.out,0)) -> 0 | U52: =_xlfn.LET( _xlpm.vorhabenStartDatum,P7, _xlpm.vorhabenEndDatum,P8, _xlpm.stundenAmVorhaben,SUM(U46:U48), _xlpm.startDatum,IF(YEAR(_xlpm.vorhabenStartDatum)=U45,_xlpm.vorhabenStartDatum,DATE(U45,1,1)), _xlpm.endDatum,IF(YEAR(_xlpm.vorhabenEndDatum)=U45,_xlpm.vorhabenEndDatum,DATE(U45,12,31)), _xlpm.arbeitstageImJahr,NETWORKDAYS(_xlpm.startDatum,_xlpm.endDatum), _xlpm.out,ROUND(_xlpm.stundenAmVorhaben/(_xlpm.arbeitstageImJahr*8),2), IF(U9,_xlpm.out,0)) -> 0 | V52: =_xlfn.LET( _xlpm.vorhabenStartDatum,Q7, _xlpm.vorhabenEndDatum,Q8, _xlpm.stundenAmVorhaben,SUM(V46:V48), _xlpm.startDatum,IF(YEAR(_xlpm.vorhabenStartDatum)=V45,_xlpm.vorhabenStartDatum,DATE(V45,1,1)), _xlpm.endDatum,IF(YEAR(_xlpm.vorhabenEndDatum)=V45,_xlpm.vorhabenEndDatum,DATE(V45,12,31)), _xlpm.arbeitstageImJahr,NETWORKDAYS(_xlpm.startDatum,_xlpm.endDatum), _xlpm.out,ROUND(_xlpm.stundenAmVorhaben/(_xlpm.arbeitstageImJahr*8),2), IF(V9,_xlpm.out,0)) -> 0 | W52: =_xlfn.LET( _xlpm.vorhabenStartDatum,R7, _xlpm.vorhabenEndDatum,R8, _xlpm.stundenAmVorhaben,SUM(W46:W48), _xlpm.startDatum,IF(YEAR(_xlpm.vorhabenStartDatum)=W45,_xlpm.vorhabenStartDatum,DATE(W45,1,1)), _xlpm.endDatum,IF(YEAR(_xlpm.vorhabenEndDatum)=W45,_xlpm.vorhabenEndDatum,DATE(W45,12,31)), _xlpm.arbeitstageImJahr,NETWORKDAYS(_xlpm.startDatum,_xlpm.endDatum), _xlpm.out,ROUND(_xlpm.stundenAmVorhaben/(_xlpm.arbeitstageImJahr*8),2), IF(W9,_xlpm.out,0)) -> 0 | AC52: =_xlfn.LET( _xlpm.vorhabenStartDatum,AC7, _xlpm.vorhabenEndDatum,AC8,_xlpm.stundenAmVorhaben,SUM(AC46:AC48), _xlpm.startDatum,IF(YEAR(_xlpm.vorhabenStartDatum)=AC45,_xlpm.vorhabenStartDatum,DATE(AC45,1,1)), _xlpm.endDatum,IF(YEAR(_xlpm.vorhabenEndDatum)=AC45,_xlpm.vorhabenEndDatum,DATE(AC45,12,31)), _xlpm.arbeitstageImJahr,NETWORKDAYS(_xlpm.startDatum,_xlpm.endDatum), _xlpm.out,ROUND(_xlpm.stundenAmVorhaben/(_xlpm.arbeitstageImJahr*8),2), IF(AC9,_xlpm.out,0)) -> 0 | AD52: =_xlfn.LET( _xlpm.vorhabenStartDatum,AC7, _xlpm.vorhabenEndDatum,AC8, _xlpm.stundenAmVorhaben,SUM(AD46:AD48), _xlpm.startDatum,IF(YEAR(_xlpm.vorhabenStartDatum)=AD45,_xlpm.vorhabenStartDatum,DATE(AD45,1,1)), _xlpm.endDatum,IF(YEAR(_xlpm.vorhabenEndDatum)=AD45,_xlpm.vorhabenEndDatum,DATE(AD45,12,31)), _xlpm.arbeitstageImJahr,NETWORKDAYS(_xlpm.startDatum,_xlpm.endDatum), _xlpm.out,ROUND(_xlpm.stundenAmVorhaben/(_xlpm.arbeitstageImJahr*8),2), IF(AD9,_xlpm.out,0)) -> 0 | AE52: =_xlfn.LET( _xlpm.vorhabenStartDatum,AC7, _xlpm.vorhabenEndDatum,AC8, _xlpm.stundenAmVorhaben,SUM(AE46:AE48), _xlpm.startDatum,IF(YEAR(_xlpm.vorhabenStartDatum)=AE45,_xlpm.vorhabenStartDatum,DATE(AE45,1,1)), _xlpm.endDatum,IF(YEAR(_xlpm.vorhabenEndDatum)=AE45,_xlpm.vorhabenEndDatum,DATE(AE45,12,31)), _xlpm.arbeitstageImJahr,NETWORKDAYS(_xlpm.startDatum,_xlpm.endDatum), _xlpm.out,ROUND(_xlpm.stundenAmVorhaben/(_xlpm.arbeitstageImJahr*8),2), IF(AE9,_xlpm.out,0)) -> 0 | AF52: =_xlfn.LET( _xlpm.vorhabenStartDatum,AC7, _xlpm.vorhabenEndDatum,AC8, _xlpm.stundenAmVorhaben,SUM(AF46:AF48), _xlpm.startDatum,IF(YEAR(_xlpm.vorhabenStartDatum)=AF45,_xlpm.vorhabenStartDatum,DATE(AF45,1,1)), _xlpm.endDatum,IF(YEAR(_xlpm.vorhabenEndDatum)=AF45,_xlpm.vorhabenEndDatum,DATE(AF45,12,31)), _xlpm.arbeitstageImJahr,NETWORKDAYS(_xlpm.startDatum,_xlpm.endDatum), _xlpm.out,ROUND(_xlpm.stundenAmVorhaben/(_xlpm.arbeitstageImJahr*8),2), IF(AF9,_xlpm.out,0)) -> 0 | AG52: =_xlfn.LET( _xlpm.vorhabenStartDatum,AC7, _xlpm.vorhabenEndDatum,AC8, _xlpm.stundenAmVorhaben,SUM(AG46:AG48), _xlpm.startDatum,IF(YEAR(_xlpm.vorhabenStartDatum)=AG45,_xlpm.vorhabenStartDatum,DATE(AG45,1,1)), _xlpm.endDatum,IF(YEAR(_xlpm.vorhabenEndDatum)=AG45,_xlpm.vorhabenEndDatum,DATE(AG45,12,31)), _xlpm.arbeitstageImJahr,NETWORKDAYS(_xlpm.startDatum,_xlpm.endDatum), _xlpm.out,ROUND(_xlpm.stundenAmVorhaben/(_xlpm.arbeitstageImJahr*8),2), IF(AG9,_xlpm.out,0)) -> 0 | AH52: =_xlfn.LET( _xlpm.vorhabenStartDatum,AC7, _xlpm.vorhabenEndDatum,AC8, _xlpm.stundenAmVorhaben,SUM(AH46:AH48), _xlpm.startDatum,IF(YEAR(_xlpm.vorhabenStartDatum)=AH45,_xlpm.vorhabenStartDatum,DATE(AH45,1,1)), _xlpm.endDatum,IF(YEAR(_xlpm.vorhabenEndDatum)=AH45,_xlpm.vorhabenEndDatum,DATE(AH45,12,31)), _xlpm.arbeitstageImJahr,NETWORKDAYS(_xlpm.startDatum,_xlpm.endDatum), _xlpm.out,ROUND(_xlpm.stundenAmVorhaben/(_xlpm.arbeitstageImJahr*8),2), IF(AH9,_xlpm.out,0)) -> 0 | AI52: =_xlfn.LET( _xlpm.vorhabenStartDatum,AD7, _xlpm.vorhabenEndDatum,AD8, _xlpm.stundenAmVorhaben,SUM(AI46:AI48), _xlpm.startDatum,IF(YEAR(_xlpm.vorhabenStartDatum)=AI45,_xlpm.vorhabenStartDatum,DATE(AI45,1,1)), _xlpm.endDatum,IF(YEAR(_xlpm.vorhabenEndDatum)=AI45,_xlpm.vorhabenEndDatum,DATE(AI45,12,31)), _xlpm.arbeitstageImJahr,NETWORKDAYS(_xlpm.startDatum,_xlpm.endDatum), _xlpm.out,ROUND(_xlpm.stundenAmVorhaben/(_xlpm.arbeitstageImJahr*8),2), IF(AI9,_xlpm.out,0)) -> 0 | AJ52: =_xlfn.LET( _xlpm.vorhabenStartDatum,AE7, _xlpm.vorhabenEndDatum,AE8, _xlpm.stundenAmVorhaben,SUM(AJ46:AJ48), _xlpm.startDatum,IF(YEAR(_xlpm.vorhabenStartDatum)=AJ45,_xlpm.vorhabenStartDatum,DATE(AJ45,1,1)), _xlpm.endDatum,IF(YEAR(_xlpm.vorhabenEndDatum)=AJ45,_xlpm.vorhabenEndDatum,DATE(AJ45,12,31)), _xlpm.arbeitstageImJahr,NETWORKDAYS(_xlpm.startDatum,_xlpm.endDatum), _xlpm.out,ROUND(_xlpm.stundenAmVorhaben/(_xlpm.arbeitstageImJahr*8),2), IF(AJ9,_xlpm.out,0)) -> 0 | AP52: =_xlfn.LET( _xlpm.vorhabenStartDatum,AP7, _xlpm.vorhabenEndDatum,AP8,_xlpm.stundenAmVorhaben,SUM(AP46:AP48), _xlpm.startDatum,IF(YEAR(_xlpm.vorhabenStartDatum)=AP45,_xlpm.vorhabenStartDatum,DATE(AP45,1,1)), _xlpm.endDatum,IF(YEAR(_xlpm.vorhabenEndDatum)=AP45,_xlpm.vorhabenEndDatum,DATE(AP45,12,31)), _xlpm.arbeitstageImJahr,NETWORKDAYS(_xlpm.startDatum,_xlpm.endDatum), _xlpm.out,ROUND(_xlpm.stundenAmVorhaben/(_xlpm.arbeitstageImJahr*8),2), IF(AP9,_xlpm.out,0)) -> 0 | AQ52: =_xlfn.LET( _xlpm.vorhabenStartDatum,AP7, _xlpm.vorhabenEndDatum,AP8, _xlpm.stundenAmVorhaben,SUM(AQ46:AQ48), _xlpm.startDatum,IF(YEAR(_xlpm.vorhabenStartDatum)=AQ45,_xlpm.vorhabenStartDatum,DATE(AQ45,1,1)), _xlpm.endDatum,IF(YEAR(_xlpm.vorhabenEndDatum)=AQ45,_xlpm.vorhabenEndDatum,DATE(AQ45,12,31)), _xlpm.arbeitstageImJahr,NETWORKDAYS(_xlpm.startDatum,_xlpm.endDatum), _xlpm.out,ROUND(_xlpm.stundenAmVorhaben/(_xlpm.arbeitstageImJahr*8),2), IF(AQ9,_xlpm.out,0)) -> 0 | AR52: =_xlfn.LET( _xlpm.vorhabenStartDatum,AP7, _xlpm.vorhabenEndDatum,AP8, _xlpm.stundenAmVorhaben,SUM(AR46:AR48), _xlpm.startDatum,IF(YEAR(_xlpm.vorhabenStartDatum)=AR45,_xlpm.vorhabenStartDatum,DATE(AR45,1,1)), _xlpm.endDatum,IF(YEAR(_xlpm.vorhabenEndDatum)=AR45,_xlpm.vorhabenEndDatum,DATE(AR45,12,31)), _xlpm.arbeitstageImJahr,NETWORKDAYS(_xlpm.startDatum,_xlpm.endDatum), _xlpm.out,ROUND(_xlpm.stundenAmVorhaben/(_xlpm.arbeitstageImJahr*8),2), IF(AR9,_xlpm.out,0)) -> 0 | AS52: =_xlfn.LET( _xlpm.vorhabenStartDatum,AP7, _xlpm.vorhabenEndDatum,AP8, _xlpm.stundenAmVorhaben,SUM(AS46:AS48), _xlpm.startDatum,IF(YEAR(_xlpm.vorhabenStartDatum)=AS45,_xlpm.vorhabenStartDatum,DATE(AS45,1,1)), _xlpm.endDatum,IF(YEAR(_xlpm.vorhabenEndDatum)=AS45,_xlpm.vorhabenEndDatum,DATE(AS45,12,31)), _xlpm.arbeitstageImJahr,NETWORKDAYS(_xlpm.startDatum,_xlpm.endDatum), _xlpm.out,ROUND(_xlpm.stundenAmVorhaben/(_xlpm.arbeitstageImJahr*8),2), IF(AS9,_xlpm.out,0)) -> 0 | AT52: =_xlfn.LET( _xlpm.vorhabenStartDatum,AP7, _xlpm.vorhabenEndDatum,AP8, _xlpm.stundenAmVorhaben,SUM(AT46:AT48), _xlpm.startDatum,IF(YEAR(_xlpm.vorhabenStartDatum)=AT45,_xlpm.vorhabenStartDatum,DATE(AT45,1,1)), _xlpm.endDatum,IF(YEAR(_xlpm.vorhabenEndDatum)=AT45,_xlpm.vorhabenEndDatum,DATE(AT45,12,31)), _xlpm.arbeitstageImJahr,NETWORKDAYS(_xlpm.startDatum,_xlpm.endDatum), _xlpm.out,ROUND(_xlpm.stundenAmVorhaben/(_xlpm.arbeitstageImJahr*8),2), IF(AT9,_xlpm.out,0)) -> 0 | AU52: =_xlfn.LET( _xlpm.vorhabenStartDatum,AP7, _xlpm.vorhabenEndDatum,AP8, _xlpm.stundenAmVorhaben,SUM(AU46:AU48), _xlpm.startDatum,IF(YEAR(_xlpm.vorhabenStartDatum)=AU45,_xlpm.vorhabenStartDatum,DATE(AU45,1,1)), _xlpm.endDatum,IF(YEAR(_xlpm.vorhabenEndDatum)=AU45,_xlpm.vorhabenEndDatum,DATE(AU45,12,31)), _xlpm.arbeitstageImJahr,NETWORKDAYS(_xlpm.startDatum,_xlpm.endDatum), _xlpm.out,ROUND(_xlpm.stundenAmVorhaben/(_xlpm.arbeitstageImJahr*8),2), IF(AU9,_xlpm.out,0)) -> 0 | AV52: =_xlfn.LET( _xlpm.vorhabenStartDatum,AQ7, _xlpm.vorhabenEndDatum,AQ8, _xlpm.stundenAmVorhaben,SUM(AV46:AV48), _xlpm.startDatum,IF(YEAR(_xlpm.vorhabenStartDatum)=AV45,_xlpm.vorhabenStartDatum,DATE(AV45,1,1)), _xlpm.endDatum,IF(YEAR(_xlpm.vorhabenEndDatum)=AV45,_xlpm.vorhabenEndDatum,DATE(AV45,12,31)), _xlpm.arbeitstageImJahr,NETWORKDAYS(_xlpm.startDatum,_xlpm.endDatum), _xlpm.out,ROUND(_xlpm.stundenAmVorhaben/(_xlpm.arbeitstageImJahr*8),2), IF(AV9,_xlpm.out,0)) -> 0 | AW52: =_xlfn.LET( _xlpm.vorhabenStartDatum,AR7, _xlpm.vorhabenEndDatum,AR8, _xlpm.stundenAmVorhaben,SUM(AW46:AW48), _xlpm.startDatum,IF(YEAR(_xlpm.vorhabenStartDatum)=AW45,_xlpm.vorhabenStartDatum,DATE(AW45,1,1)), _xlpm.endDatum,IF(YEAR(_xlpm.vorhabenEndDatum)=AW45,_xlpm.vorhabenEndDatum,DATE(AW45,12,31)), _xlpm.arbeitstageImJahr,NETWORKDAYS(_xlpm.startDatum,_xlpm.endDatum), _xlpm.out,ROUND(_xlpm.stundenAmVorhaben/(_xlpm.arbeitstageImJahr*8),2), IF(AW9,_xlpm.out,0)) -> 0 | BC52: =_xlfn.LET( _xlpm.vorhabenStartDatum,BC7, _xlpm.vorhabenEndDatum,BC8,_xlpm.stundenAmVorhaben,SUM(BC46:BC48), _xlpm.startDatum,IF(YEAR(_xlpm.vorhabenStartDatum)=BC45,_xlpm.vorhabenStartDatum,DATE(BC45,1,1)), _xlpm.endDatum,IF(YEAR(_xlpm.vorhabenEndDatum)=BC45,_xlpm.vorhabenEndDatum,DATE(BC45,12,31)), _xlpm.arbeitstageImJahr,NETWORKDAYS(_xlpm.startDatum,_xlpm.endDatum), _xlpm.out,ROUND(_xlpm.stundenAmVorhaben/(_xlpm.arbeitstageImJahr*8),2), IF(BC9,_xlpm.out,0)) -> 0 | BD52: =_xlfn.LET( _xlpm.vorhabenStartDatum,BC7, _xlpm.vorhabenEndDatum,BC8, _xlpm.stundenAmVorhaben,SUM(BD46:BD48), _xlpm.startDatum,IF(YEAR(_xlpm.vorhabenStartDatum)=BD45,_xlpm.vorhabenStartDatum,DATE(BD45,1,1)), _xlpm.endDatum,IF(YEAR(_xlpm.vorhabenEndDatum)=BD45,_xlpm.vorhabenEndDatum,DATE(BD45,12,31)), _xlpm.arbeitstageImJahr,NETWORKDAYS(_xlpm.startDatum,_xlpm.endDatum), _xlpm.out,ROUND(_xlpm.stundenAmVorhaben/(_xlpm.arbeitstageImJahr*8),2), IF(BD9,_xlpm.out,0)) -> 0 | BE52: =_xlfn.LET( _xlpm.vorhabenStartDatum,BC7, _xlpm.vorhabenEndDatum,BC8, _xlpm.stundenAmVorhaben,SUM(BE46:BE48), _xlpm.startDatum,IF(YEAR(_xlpm.vorhabenStartDatum)=BE45,_xlpm.vorhabenStartDatum,DATE(BE45,1,1)), _xlpm.endDatum,IF(YEAR(_xlpm.vorhabenEndDatum)=BE45,_xlpm.vorhabenEndDatum,DATE(BE45,12,31)), _xlpm.arbeitstageImJahr,NETWORKDAYS(_xlpm.startDatum,_xlpm.endDatum), _xlpm.out,ROUND(_xlpm.stundenAmVorhaben/(_xlpm.arbeitstageImJahr*8),2), IF(BE9,_xlpm.out,0)) -> 0 | BF52: =_xlfn.LET( _xlpm.vorhabenStartDatum,BC7, _xlpm.vorhabenEndDatum,BC8, _xlpm.stundenAmVorhaben,SUM(BF46:BF48), _xlpm.startDatum,IF(YEAR(_xlpm.vorhabenStartDatum)=BF45,_xlpm.vorhabenStartDatum,DATE(BF45,1,1)), _xlpm.endDatum,IF(YEAR(_xlpm.vorhabenEndDatum)=BF45,_xlpm.vorhabenEndDatum,DATE(BF45,12,31)), _xlpm.arbeitstageImJahr,NETWORKDAYS(_xlpm.startDatum,_xlpm.endDatum), _xlpm.out,ROUND(_xlpm.stundenAmVorhaben/(_xlpm.arbeitstageImJahr*8),2), IF(BF9,_xlpm.out,0)) -> 0 | BG52: =_xlfn.LET( _xlpm.vorhabenStartDatum,BC7, _xlpm.vorhabenEndDatum,BC8, _xlpm.stundenAmVorhaben,SUM(BG46:BG48), _xlpm.startDatum,IF(YEAR(_xlpm.vorhabenStartDatum)=BG45,_xlpm.vorhabenStartDatum,DATE(BG45,1,1)), _xlpm.endDatum,IF(YEAR(_xlpm.vorhabenEndDatum)=BG45,_xlpm.vorhabenEndDatum,DATE(BG45,12,31)), _xlpm.arbeitstageImJahr,NETWORKDAYS(_xlpm.startDatum,_xlpm.endDatum), _xlpm.out,ROUND(_xlpm.stundenAmVorhaben/(_xlpm.arbeitstageImJahr*8),2), IF(BG9,_xlpm.out,0)) -> 0 | BH52: =_xlfn.LET( _xlpm.vorhabenStartDatum,BC7, _xlpm.vorhabenEndDatum,BC8, _xlpm.stundenAmVorhaben,SUM(BH46:BH48), _xlpm.startDatum,IF(YEAR(_xlpm.vorhabenStartDatum)=BH45,_xlpm.vorhabenStartDatum,DATE(BH45,1,1)), _xlpm.endDatum,IF(YEAR(_xlpm.vorhabenEndDatum)=BH45,_xlpm.vorhabenEndDatum,DATE(BH45,12,31)), _xlpm.arbeitstageImJahr,NETWORKDAYS(_xlpm.startDatum,_xlpm.endDatum), _xlpm.out,ROUND(_xlpm.stundenAmVorhaben/(_xlpm.arbeitstageImJahr*8),2), IF(BH9,_xlpm.out,0)) -> 0 | BI52: =_xlfn.LET( _xlpm.vorhabenStartDatum,BD7, _xlpm.vorhabenEndDatum,BD8, _xlpm.stundenAmVorhaben,SUM(BI46:BI48), _xlpm.startDatum,IF(YEAR(_xlpm.vorhabenStartDatum)=BI45,_xlpm.vorhabenStartDatum,DATE(BI45,1,1)), _xlpm.endDatum,IF(YEAR(_xlpm.vorhabenEndDatum)=BI45,_xlpm.vorhabenEndDatum,DATE(BI45,12,31)), _xlpm.arbeitstageImJahr,NETWORKDAYS(_xlpm.startDatum,_xlpm.endDatum), _xlpm.out,ROUND(_xlpm.stundenAmVorhaben/(_xlpm.arbeitstageImJahr*8),2), IF(BI9,_xlpm.out,0)) -> 0 | BJ52: =_xlfn.LET( _xlpm.vorhabenStartDatum,BE7, _xlpm.vorhabenEndDatum,BE8, _xlpm.stundenAmVorhaben,SUM(BJ46:BJ48), _xlpm.startDatum,IF(YEAR(_xlpm.vorhabenStartDatum)=BJ45,_xlpm.vorhabenStartDatum,DATE(BJ45,1,1)), _xlpm.endDatum,IF(YEAR(_xlpm.vorhabenEndDatum)=BJ45,_xlpm.vorhabenEndDatum,DATE(BJ45,12,31)), _xlpm.arbeitstageImJahr,NETWORKDAYS(_xlpm.startDatum,_xlpm.endDatum), _xlpm.out,ROUND(_xlpm.stundenAmVorhaben/(_xlpm.arbeitstageImJahr*8),2), IF(BJ9,_xlpm.out,0)) -> 0 | BP52: =_xlfn.LET( _xlpm.vorhabenStartDatum,BP7, _xlpm.vorhabenEndDatum,BP8,_xlpm.stundenAmVorhaben,SUM(BP46:BP48), _xlpm.startDatum,IF(YEAR(_xlpm.vorhabenStartDatum)=BP45,_xlpm.vorhabenStartDatum,DATE(BP45,1,1)), _xlpm.endDatum,IF(YEAR(_xlpm.vorhabenEndDatum)=BP45,_xlpm.vorhabenEndDatum,DATE(BP45,12,31)), _xlpm.arbeitstageImJahr,NETWORKDAYS(_xlpm.startDatum,_xlpm.endDatum), _xlpm.out,ROUND(_xlpm.stundenAmVorhaben/(_xlpm.arbeitstageImJahr*8),2), IF(BP9,_xlpm.out,0)) -> 0 | BQ52: =_xlfn.LET( _xlpm.vorhabenStartDatum,BP7, _xlpm.vorhabenEndDatum,BP8, _xlpm.stundenAmVorhaben,SUM(BQ46:BQ48), _xlpm.startDatum,IF(YEAR(_xlpm.vorhabenStartDatum)=BQ45,_xlpm.vorhabenStartDatum,DATE(BQ45,1,1)), _xlpm.endDatum,IF(YEAR(_xlpm.vorhabenEndDatum)=BQ45,_xlpm.vorhabenEndDatum,DATE(BQ45,12,31)), _xlpm.arbeitstageImJahr,NETWORKDAYS(_xlpm.startDatum,_xlpm.endDatum), _xlpm.out,ROUND(_xlpm.stundenAmVorhaben/(_xlpm.arbeitstageImJahr*8),2), IF(BQ9,_xlpm.out,0)) -> 0 | BR52: =_xlfn.LET( _xlpm.vorhabenStartDatum,BP7, _xlpm.vorhabenEndDatum,BP8, _xlpm.stundenAmVorhaben,SUM(BR46:BR48), _xlpm.startDatum,IF(YEAR(_xlpm.vorhabenStartDatum)=BR45,_xlpm.vorhabenStartDatum,DATE(BR45,1,1)), _xlpm.endDatum,IF(YEAR(_xlpm.vorhabenEndDatum)=BR45,_xlpm.vorhabenEndDatum,DATE(BR45,12,31)), _xlpm.arbeitstageImJahr,NETWORKDAYS(_xlpm.startDatum,_xlpm.endDatum), _xlpm.out,ROUND(_xlpm.stundenAmVorhaben/(_xlpm.arbeitstageImJahr*8),2), IF(BR9,_xlpm.out,0)) -> 0 | BS52: =_xlfn.LET( _xlpm.vorhabenStartDatum,BP7, _xlpm.vorhabenEndDatum,BP8, _xlpm.stundenAmVorhaben,SUM(BS46:BS48), _xlpm.startDatum,IF(YEAR(_xlpm.vorhabenStartDatum)=BS45,_xlpm.vorhabenStartDatum,DATE(BS45,1,1)), _xlpm.endDatum,IF(YEAR(_xlpm.vorhabenEndDatum)=BS45,_xlpm.vorhabenEndDatum,DATE(BS45,12,31)), _xlpm.arbeitstageImJahr,NETWORKDAYS(_xlpm.startDatum,_xlpm.endDatum), _xlpm.out,ROUND(_xlpm.stundenAmVorhaben/(_xlpm.arbeitstageImJahr*8),2), IF(BS9,_xlpm.out,0)) -> 0 | BT52: =_xlfn.LET( _xlpm.vorhabenStartDatum,BP7, _xlpm.vorhabenEndDatum,BP8, _xlpm.stundenAmVorhaben,SUM(BT46:BT48), _xlpm.startDatum,IF(YEAR(_xlpm.vorhabenStartDatum)=BT45,_xlpm.vorhabenStartDatum,DATE(BT45,1,1)), _xlpm.endDatum,IF(YEAR(_xlpm.vorhabenEndDatum)=BT45,_xlpm.vorhabenEndDatum,DATE(BT45,12,31)), _xlpm.arbeitstageImJahr,NETWORKDAYS(_xlpm.startDatum,_xlpm.endDatum), _xlpm.out,ROUND(_xlpm.stundenAmVorhaben/(_xlpm.arbeitstageImJahr*8),2), IF(BT9,_xlpm.out,0)) -> 0 | BU52: =_xlfn.LET( _xlpm.vorhabenStartDatum,BP7, _xlpm.vorhabenEndDatum,BP8, _xlpm.stundenAmVorhaben,SUM(BU46:BU48), _xlpm.startDatum,IF(YEAR(_xlpm.vorhabenStartDatum)=BU45,_xlpm.vorhabenStartDatum,DATE(BU45,1,1)), _xlpm.endDatum,IF(YEAR(_xlpm.vorhabenEndDatum)=BU45,_xlpm.vorhabenEndDatum,DATE(BU45,12,31)), _xlpm.arbeitstageImJahr,NETWORKDAYS(_xlpm.startDatum,_xlpm.endDatum), _xlpm.out,ROUND(_xlpm.stundenAmVorhaben/(_xlpm.arbeitstageImJahr*8),2), IF(BU9,_xlpm.out,0)) -> 0 | BV52: =_xlfn.LET( _xlpm.vorhabenStartDatum,BQ7, _xlpm.vorhabenEndDatum,BQ8, _xlpm.stundenAmVorhaben,SUM(BV46:BV48), _xlpm.startDatum,IF(YEAR(_xlpm.vorhabenStartDatum)=BV45,_xlpm.vorhabenStartDatum,DATE(BV45,1,1)), _xlpm.endDatum,IF(YEAR(_xlpm.vorhabenEndDatum)=BV45,_xlpm.vorhabenEndDatum,DATE(BV45,12,31)), _xlpm.arbeitstageImJahr,NETWORKDAYS(_xlpm.startDatum,_xlpm.endDatum), _xlpm.out,ROUND(_xlpm.stundenAmVorhaben/(_xlpm.arbeitstageImJahr*8),2), IF(BV9,_xlpm.out,0)) -> 0 | BW52: =_xlfn.LET( _xlpm.vorhabenStartDatum,BR7, _xlpm.vorhabenEndDatum,BR8, _xlpm.stundenAmVorhaben,SUM(BW46:BW48), _xlpm.startDatum,IF(YEAR(_xlpm.vorhabenStartDatum)=BW45,_xlpm.vorhabenStartDatum,DATE(BW45,1,1)), _xlpm.endDatum,IF(YEAR(_xlpm.vorhabenEndDatum)=BW45,_xlpm.vorhabenEndDatum,DATE(BW45,12,31)), _xlpm.arbeitstageImJahr,NETWORKDAYS(_xlpm.startDatum,_xlpm.endDatum), _xlpm.out,ROUND(_xlpm.stundenAmVorhaben/(_xlpm.arbeitstageImJahr*8),2), IF(BW9,_xlpm.out,0)) -> 0 | CC52: =_xlfn.LET( _xlpm.vorhabenStartDatum,CC7, _xlpm.vorhabenEndDatum,CC8,_xlpm.stundenAmVorhaben,SUM(CC46:CC48), _xlpm.startDatum,IF(YEAR(_xlpm.vorhabenStartDatum)=CC45,_xlpm.vorhabenStartDatum,DATE(CC45,1,1)), _xlpm.endDatum,IF(YEAR(_xlpm.vorhabenEndDatum)=CC45,_xlpm.vorhabenEndDatum,DATE(CC45,12,31)), _xlpm.arbeitstageImJahr,NETWORKDAYS(_xlpm.startDatum,_xlpm.endDatum), _xlpm.out,ROUND(_xlpm.stundenAmVorhaben/(_xlpm.arbeitstageImJahr*8),2), IF(CC9,_xlpm.out,0)) -> 0 | CD52: =_xlfn.LET( _xlpm.vorhabenStartDatum,CC7, _xlpm.vorhabenEndDatum,CC8, _xlpm.stundenAmVorhaben,SUM(CD46:CD48), _xlpm.startDatum,IF(YEAR(_xlpm.vorhabenStartDatum)=CD45,_xlpm.vorhabenStartDatum,DATE(CD45,1,1)), _xlpm.endDatum,IF(YEAR(_xlpm.vorhabenEndDatum)=CD45,_xlpm.vorhabenEndDatum,DATE(CD45,12,31)), _xlpm.arbeitstageImJahr,NETWORKDAYS(_xlpm.startDatum,_xlpm.endDatum), _xlpm.out,ROUND(_xlpm.stundenAmVorhaben/(_xlpm.arbeitstageImJahr*8),2), IF(CD9,_xlpm.out,0)) -> 0 | CE52: =_xlfn.LET( _xlpm.vorhabenStartDatum,CC7, _xlpm.vorhabenEndDatum,CC8, _xlpm.stundenAmVorhaben,SUM(CE46:CE48), _xlpm.startDatum,IF(YEAR(_xlpm.vorhabenStartDatum)=CE45,_xlpm.vorhabenStartDatum,DATE(CE45,1,1)), _xlpm.endDatum,IF(YEAR(_xlpm.vorhabenEndDatum)=CE45,_xlpm.vorhabenEndDatum,DATE(CE45,12,31)), _xlpm.arbeitstageImJahr,NETWORKDAYS(_xlpm.startDatum,_xlpm.endDatum), _xlpm.out,ROUND(_xlpm.stundenAmVorhaben/(_xlpm.arbeitstageImJahr*8),2), IF(CE9,_xlpm.out,0)) -> 0 | CF52: =_xlfn.LET( _xlpm.vorhabenStartDatum,CC7, _xlpm.vorhabenEndDatum,CC8, _xlpm.stundenAmVorhaben,SUM(CF46:CF48), _xlpm.startDatum,IF(YEAR(_xlpm.vorhabenStartDatum)=CF45,_xlpm.vorhabenStartDatum,DATE(CF45,1,1)), _xlpm.endDatum,IF(YEAR(_xlpm.vorhabenEndDatum)=CF45,_xlpm.vorhabenEndDatum,DATE(CF45,12,31)), _xlpm.arbeitstageImJahr,NETWORKDAYS(_xlpm.startDatum,_xlpm.endDatum), _xlpm.out,ROUND(_xlpm.stundenAmVorhaben/(_xlpm.arbeitstageImJahr*8),2), IF(CF9,_xlpm.out,0)) -> 0 | CG52: =_xlfn.LET( _xlpm.vorhabenStartDatum,CC7, _xlpm.vorhabenEndDatum,CC8, _xlpm.stundenAmVorhaben,SUM(CG46:CG48), _xlpm.startDatum,IF(YEAR(_xlpm.vorhabenStartDatum)=CG45,_xlpm.vorhabenStartDatum,DATE(CG45,1,1)), _xlpm.endDatum,IF(YEAR(_xlpm.vorhabenEndDatum)=CG45,_xlpm.vorhabenEndDatum,DATE(CG45,12,31)), _xlpm.arbeitstageImJahr,NETWORKDAYS(_xlpm.startDatum,_xlpm.endDatum), _xlpm.out,ROUND(_xlpm.stundenAmVorhaben/(_xlpm.arbeitstageImJahr*8),2), IF(CG9,_xlpm.out,0)) -> 0 | CH52: =_xlfn.LET( _xlpm.vorhabenStartDatum,CC7, _xlpm.vorhabenEndDatum,CC8, _xlpm.stundenAmVorhaben,SUM(CH46:CH48), _xlpm.startDatum,IF(YEAR(_xlpm.vorhabenStartDatum)=CH45,_xlpm.vorhabenStartDatum,DATE(CH45,1,1)), _xlpm.endDatum,IF(YEAR(_xlpm.vorhabenEndDatum)=CH45,_xlpm.vorhabenEndDatum,DATE(CH45,12,31)), _xlpm.arbeitstageImJahr,NETWORKDAYS(_xlpm.startDatum,_xlpm.endDatum), _xlpm.out,ROUND(_xlpm.stundenAmVorhaben/(_xlpm.arbeitstageImJahr*8),2), IF(CH9,_xlpm.out,0)) -> 0 | CI52: =_xlfn.LET( _xlpm.vorhabenStartDatum,CD7, _xlpm.vorhabenEndDatum,CD8, _xlpm.stundenAmVorhaben,SUM(CI46:CI48), _xlpm.startDatum,IF(YEAR(_xlpm.vorhabenStartDatum)=CI45,_xlpm.vorhabenStartDatum,DATE(CI45,1,1)), _xlpm.endDatum,IF(YEAR(_xlpm.vorhabenEndDatum)=CI45,_xlpm.vorhabenEndDatum,DATE(CI45,12,31)), _xlpm.arbeitstageImJahr,NETWORKDAYS(_xlpm.startDatum,_xlpm.endDatum), _xlpm.out,ROUND(_xlpm.stundenAmVorhaben/(_xlpm.arbeitstageImJahr*8),2), IF(CI9,_xlpm.out,0)) -> 0 | CJ52: =_xlfn.LET( _xlpm.vorhabenStartDatum,CE7, _xlpm.vorhabenEndDatum,CE8, _xlpm.stundenAmVorhaben,SUM(CJ46:CJ48), _xlpm.startDatum,IF(YEAR(_xlpm.vorhabenStartDatum)=CJ45,_xlpm.vorhabenStartDatum,DATE(CJ45,1,1)), _xlpm.endDatum,IF(YEAR(_xlpm.vorhabenEndDatum)=CJ45,_xlpm.vorhabenEndDatum,DATE(CJ45,12,31)), _xlpm.arbeitstageImJahr,NETWORKDAYS(_xlpm.startDatum,_xlpm.endDatum), _xlpm.out,ROUND(_xlpm.stundenAmVorhaben/(_xlpm.arbeitstageImJahr*8),2), IF(CJ9,_xlpm.out,0)) -> 0
B53: Auftragnehmer | C53: Adresse | G53: Kurzbeschreibung der Tätigkeit/Leistung | O53: Auftragnehmer | P53: Adresse | T53: Kurzbeschreibung der Tätigkeit/Leistung | AB53: Auftragnehmer | AC53: Adresse | AG53: Kurzbeschreibung der Tätigkeit/Leistung | AO53: Auftragnehmer | AP53: Adresse | AT53: Kurzbeschreibung der Tätigkeit/Leistung | BB53: Auftragnehmer | BC53: Adresse | BG53: Kurzbeschreibung der Tätigkeit/Leistung | BO53: Auftragnehmer | BP53: Adresse | BT53: Kurzbeschreibung der Tätigkeit/Leistung | CB53: Auftragnehmer | CC53: Adresse | CG53: Kurzbeschreibung der Tätigkeit/Leistung
B54: Firmierung / Name | C54: Straße /Hausnr. | D54: PLZ / Ort | E54: Steuernummer (nicht UStID) | F54: Rechnungs-summe | O54: Firmierung / Name | P54: Straße /Hausnr. | Q54: PLZ / Ort | R54: Steuernummer (nicht UStID) | S54: Rechnungs-summe | AB54: Firmierung / Name | AC54: Straße /Hausnr. | AD54: PLZ / Ort | AE54: Steuernummer (nicht UStID) | AF54: Rechnungs-summe | AO54: Firmierung / Name | AP54: Straße /Hausnr. | AQ54: PLZ / Ort | AR54: Steuernummer (nicht UStID) | AS54: Rechnungs-summe | BB54: Firmierung / Name | BC54: Straße /Hausnr. | BD54: PLZ / Ort | BE54: Steuernummer (nicht UStID) | BF54: Rechnungs-summe | BO54: Firmierung / Name | BP54: Straße /Hausnr. | BQ54: PLZ / Ort | BR54: Steuernummer (nicht UStID) | BS54: Rechnungs-summe | CB54: Firmierung / Name | CC54: Straße /Hausnr. | CD54: PLZ / Ort | CE54: Steuernummer (nicht UStID) | CF54: Rechnungs-summe
A55: {=IFERROR("#"&_xlfn.SEQUENCE(COUNTA(B55:B64)),"")} -> #1 | B55: =B17 -> Auftragnehmer 1 | F55: =SUMIF(C$9:J$9,TRUE,C17:J17) -> 0 | N55: {=IFERROR("#"&_xlfn.SEQUENCE(COUNTA(O55:O64)),"")} -> #1 | O55: =O17 -> Auftragnehmer 1 | S55: =SUMIF(Q$9:W$9,TRUE,Q17:W17) -> 0 | AA55: {=IFERROR("#"&_xlfn.SEQUENCE(COUNTA(AB55:AB64)),"")} -> #1 | AB55: =AB17 -> Auftragnehmer 1 | AF55: =SUMIF(AD$9:AJ$9,TRUE,AD17:AJ17) -> 0 | AN55: {=IFERROR("#"&_xlfn.SEQUENCE(COUNTA(AO55:AO64)),"")} -> #1 | AO55: =AO17 -> Auftragnehmer 1 | AS55: =SUMIF(AQ$9:AW$9,TRUE,AQ17:AW17) -> 0 | BA55: {=IFERROR("#"&_xlfn.SEQUENCE(COUNTA(BB55:BB64)),"")} -> #1 | BB55: =BB17 -> Auftragnehmer 1 | BF55: =SUMIF(BD$9:BJ$9,TRUE,BD17:BJ17) -> 0 | BN55: {=IFERROR("#"&_xlfn.SEQUENCE(COUNTA(BO55:BO64)),"")} -> #1 | BO55: =BO17 -> Auftragnehmer 1 | BS55: =SUMIF(BQ$9:BW$9,TRUE,BQ17:BW17) -> 0 | CA55: {=IFERROR("#"&_xlfn.SEQUENCE(COUNTA(CB55:CB64)),"")} -> #1 | CB55: =CB17 -> Auftragnehmer 1 | CF55: =SUMIF(CD$9:CJ$9,TRUE,CD17:CJ17) -> 0
A56: #2 | B56: =B18 -> Auftragnehmer 2 | F56: =SUMIF(C$9:J$9,TRUE,C18:J18) -> 0 | N56: #2 | O56: =O18 -> Auftragnehmer 2 | S56: =SUM(Q18:W18) -> 0 | AA56: #2 | AB56: =AB18 -> Auftragnehmer 2 | AF56: =SUM(AD18:AJ18) -> 0 | AN56: #2 | AO56: =AO18 -> Auftragnehmer 2 | AS56: =SUM(AQ18:AW18) -> 0 | BA56: #2 | BB56: =BB18 -> Auftragnehmer 2 | BF56: =SUM(BD18:BJ18) -> 0 | BN56: #2 | BO56: =BO18 -> Auftragnehmer 2 | BS56: =SUM(BQ18:BW18) -> 0 | CA56: #2 | CB56: =CB18 -> Auftragnehmer 2 | CF56: =SUM(CD18:CJ18) -> 0
A57: #3 | B57: =B19 -> Auftragnehmer 3 | F57: =SUMIF(C$9:J$9,TRUE,C19:J19) -> 0 | N57: #3 | O57: =O19 -> Auftragnehmer 3 | S57: =SUM(Q19:W19) -> 0 | AA57: #3 | AB57: =AB19 -> Auftragnehmer 3 | AF57: =SUM(AD19:AJ19) -> 0 | AN57: #3 | AO57: =AO19 -> Auftragnehmer 3 | AS57: =SUM(AQ19:AW19) -> 0 | BA57: #3 | BB57: =BB19 -> Auftragnehmer 3 | BF57: =SUM(BD19:BJ19) -> 0 | BN57: #3 | BO57: =BO19 -> Auftragnehmer 3 | BS57: =SUM(BQ19:BW19) -> 0 | CA57: #3 | CB57: =CB19 -> Auftragnehmer 3 | CF57: =SUM(CD19:CJ19) -> 0
A58: #4 | B58: =B20 -> Auftragnehmer 4 | F58: =SUMIF(C$9:J$9,TRUE,C20:J20) -> 0 | N58: #4 | O58: =O20 -> Auftragnehmer 4 | S58: =SUM(Q20:W20) -> 0 | AA58: #4 | AB58: =AB20 -> Auftragnehmer 4 | AF58: =SUM(AD20:AJ20) -> 0 | AN58: #4 | AO58: =AO20 -> Auftragnehmer 4 | AS58: =SUM(AQ20:AW20) -> 0 | BA58: #4 | BB58: =BB20 -> Auftragnehmer 4 | BF58: =SUM(BD20:BJ20) -> 0 | BN58: #4 | BO58: =BO20 -> Auftragnehmer 4 | BS58: =SUM(BQ20:BW20) -> 0 | CA58: #4 | CB58: =CB20 -> Auftragnehmer 4 | CF58: =SUM(CD20:CJ20) -> 0
A59: #5 | B59: =B21 -> Auftragnehmer 5 | F59: =SUMIF(C$9:J$9,TRUE,C21:J21) -> 0 | N59: #5 | O59: =O21 -> Auftragnehmer 5 | S59: =SUM(Q21:W21) -> 0 | AA59: #5 | AB59: =AB21 -> Auftragnehmer 5 | AF59: =SUM(AD21:AJ21) -> 0 | AN59: #5 | AO59: =AO21 -> Auftragnehmer 5 | AS59: =SUM(AQ21:AW21) -> 0 | BA59: #5 | BB59: =BB21 -> Auftragnehmer 5 | BF59: =SUM(BD21:BJ21) -> 0 | BN59: #5 | BO59: =BO21 -> Auftragnehmer 5 | BS59: =SUM(BQ21:BW21) -> 0 | CA59: #5 | CB59: =CB21 -> Auftragnehmer 5 | CF59: =SUM(CD21:CJ21) -> 0
A60: #6 | B60: =B22 -> Auftragnehmer 6 | F60: =SUMIF(C$9:J$9,TRUE,C22:J22) -> 0 | N60: #6 | O60: =O22 -> Auftragnehmer 6 | S60: =SUM(Q22:W22) -> 0 | AA60: #6 | AB60: =AB22 -> Auftragnehmer 6 | AF60: =SUM(AD22:AJ22) -> 0 | AN60: #6 | AO60: =AO22 -> Auftragnehmer 6 | AS60: =SUM(AQ22:AW22) -> 0 | BA60: #6 | BB60: =BB22 -> Auftragnehmer 6 | BF60: =SUM(BD22:BJ22) -> 0 | BN60: #6 | BO60: =BO22 -> Auftragnehmer 6 | BS60: =SUM(BQ22:BW22) -> 0 | CA60: #6 | CB60: =CB22 -> Auftragnehmer 6 | CF60: =SUM(CD22:CJ22) -> 0
A61: #7 | B61: =B23 -> Auftragnehmer 7 | F61: =SUMIF(C$9:J$9,TRUE,C23:J23) -> 0 | N61: #7 | O61: =O23 -> Auftragnehmer 7 | S61: =SUM(Q23:W23) -> 0 | AA61: #7 | AB61: =AB23 -> Auftragnehmer 7 | AF61: =SUM(AD23:AJ23) -> 0 | AN61: #7 | AO61: =AO23 -> Auftragnehmer 7 | AS61: =SUM(AQ23:AW23) -> 0 | BA61: #7 | BB61: =BB23 -> Auftragnehmer 7 | BF61: =SUM(BD23:BJ23) -> 0 | BN61: #7 | BO61: =BO23 -> Auftragnehmer 7 | BS61: =SUM(BQ23:BW23) -> 0 | CA61: #7 | CB61: =CB23 -> Auftragnehmer 7 | CF61: =SUM(CD23:CJ23) -> 0
A62: #8 | B62: =B24 -> Auftragnehmer 8 | F62: =SUMIF(C$9:J$9,TRUE,C24:J24) -> 0 | N62: #8 | O62: =O24 -> Auftragnehmer 8 | S62: =SUM(Q24:W24) -> 0 | AA62: #8 | AB62: =AB24 -> Auftragnehmer 8 | AF62: =SUM(AD24:AJ24) -> 0 | AN62: #8 | AO62: =AO24 -> Auftragnehmer 8 | AS62: =SUM(AQ24:AW24) -> 0 | BA62: #8 | BB62: =BB24 -> Auftragnehmer 8 | BF62: =SUM(BD24:BJ24) -> 0 | BN62: #8 | BO62: =BO24 -> Auftragnehmer 8 | BS62: =SUM(BQ24:BW24) -> 0 | CA62: #8 | CB62: =CB24 -> Auftragnehmer 8 | CF62: =SUM(CD24:CJ24) -> 0
A63: #9 | B63: =B25 -> Auftragnehmer 9 | F63: =SUMIF(C$9:J$9,TRUE,C25:J25) -> 0 | N63: #9 | O63: =O25 -> Auftragnehmer 9 | S63: =SUM(Q25:W25) -> 0 | AA63: #9 | AB63: =AB25 -> Auftragnehmer 9 | AF63: =SUM(AD25:AJ25) -> 0 | AN63: #9 | AO63: =AO25 -> Auftragnehmer 9 | AS63: =SUM(AQ25:AW25) -> 0 | BA63: #9 | BB63: =BB25 -> Auftragnehmer 9 | BF63: =SUM(BD25:BJ25) -> 0 | BN63: #9 | BO63: =BO25 -> Auftragnehmer 9 | BS63: =SUM(BQ25:BW25) -> 0 | CA63: #9 | CB63: =CB25 -> Auftragnehmer 9 | CF63: =SUM(CD25:CJ25) -> 0
A64: #10 | B64: =B26 -> Auftragnehmer 10 | F64: =SUMIF(C$9:J$9,TRUE,C26:J26) -> 0 | N64: #10 | O64: =O26 -> Auftragnehmer 10 | S64: =SUM(Q26:W26) -> 0 | AA64: #10 | AB64: =AB26 -> Auftragnehmer 10 | AF64: =SUM(AD26:AJ26) -> 0 | AN64: #10 | AO64: =AO26 -> Auftragnehmer 10 | AS64: =SUM(AQ26:AW26) -> 0 | BA64: #10 | BB64: =BB26 -> Auftragnehmer 10 | BF64: =SUM(BD26:BJ26) -> 0 | BN64: #10 | BO64: =BO26 -> Auftragnehmer 10 | BS64: =SUM(BQ26:BW26) -> 0 | CA64: #10 | CB64: =CB26 -> Auftragnehmer 10 | CF64: =SUM(CD26:CJ26) -> 0
B66: Sachanlagen | O66: Sachanlagen | AB66: Sachanlagen | AO66: Sachanlagen | BB66: Sachanlagen | BO66: Sachanlagen | CB66: Sachanlagen
B67: Bezeichnung | C67: Hersteller & Modell | D67: Stückzahl | E67: Zuordnung Arbeitspaket | F67: Ausschließlich Eigenbetrieblich genutzt? | G67: Abnutzbar oder Bewegliches Gut? | H67: Warum für Projekt notwendig? | O67: Bezeichnung | P67: Hersteller & Modell | Q67: Stückzahl | R67: Zuordnung Arbeitspaket | S67: Ausschließlich Eigenbetrieblich genutzt? | T67: Abnutzbar oder Bewegliches Gut? | U67: Warum für Projekt notwendig? | AB67: Bezeichnung | AC67: Hersteller & Modell | AD67: Stückzahl | AE67: Zuordnung Arbeitspaket | AF67: Ausschließlich Eigenbetrieblich genutzt? | AG67: Abnutzbar oder Bewegliches Gut? | AH67: Warum für Projekt notwendig? | AO67: Bezeichnung | AP67: Hersteller & Modell | AQ67: Stückzahl | AR67: Zuordnung Arbeitspaket | AS67: Ausschließlich Eigenbetrieblich genutzt? | AT67: Abnutzbar oder Bewegliches Gut? | AU67: Warum für Projekt notwendig? | BB67: Bezeichnung | BC67: Hersteller & Modell | BD67: Stückzahl | BE67: Zuordnung Arbeitspaket | BF67: Ausschließlich Eigenbetrieblich genutzt? | BG67: Abnutzbar oder Bewegliches Gut? | BH67: Warum für Projekt notwendig? | BO67: Bezeichnung | BP67: Hersteller & Modell | BQ67: Stückzahl | BR67: Zuordnung Arbeitspaket | BS67: Ausschließlich Eigenbetrieblich genutzt? | BT67: Abnutzbar oder Bewegliches Gut? | BU67: Warum für Projekt notwendig? | CB67: Bezeichnung | CC67: Hersteller & Modell | CD67: Stückzahl | CE67: Zuordnung Arbeitspaket | CF67: Ausschließlich Eigenbetrieblich genutzt? | CG67: Abnutzbar oder Bewegliches Gut? | CH67: Warum für Projekt notwendig?
A68: {=IFERROR("#"&_xlfn.SEQUENCE(COUNTA(B68:B72)),"")} -> #1 | B68: {=IFERROR(INDIRECT(ADDRESS(10,MIN(IF(C29:J29<>"",COLUMN(C29:J29))),4))&": "&TEXT(ROUND(SUM(C29:J29),2),"#.##0,00") & " €"& " | "& B29,B29)} -> Sachanlage 1 | N68: {=IFERROR("#"&_xlfn.SEQUENCE(COUNTA(O68:O72)),"")} -> #1 | O68: {=IFERROR(INDIRECT(ADDRESS(10,MIN(IF(P29:W29<>"",COLUMN(P29:W29))),4))&": "&TEXT(ROUND(SUM(P29:W29),2),"#.##0,00") & " €"& " | "& O29,O29)} -> Sachanlage 1 | AA68: {=IFERROR("#"&_xlfn.SEQUENCE(COUNTA(AB68:AB72)),"")} -> #1 | AB68: {=IFERROR(INDIRECT(ADDRESS(10,MIN(IF(AC29:AJ29<>"",COLUMN(AC29:AJ29))),4))&": "&TEXT(ROUND(SUM(AC29:AJ29),2),"#.##0,00") & " €"& " | "& AB29,AB29)} -> Sachanlage 1 | AN68: {=IFERROR("#"&_xlfn.SEQUENCE(COUNTA(AO68:AO72)),"")} -> #1 | AO68: {=IFERROR(INDIRECT(ADDRESS(10,MIN(IF(AP29:AW29<>"",COLUMN(AP29:AW29))),4))&": "&TEXT(ROUND(SUM(AP29:AW29),2),"#.##0,00") & " €"& " | "& AO29,AO29)} -> Sachanlage 1 | BA68: {=IFERROR("#"&_xlfn.SEQUENCE(COUNTA(BB68:BB72)),"")} -> #1 | BB68: {=IFERROR(INDIRECT(ADDRESS(10,MIN(IF(BC29:BJ29<>"",COLUMN(BC29:BJ29))),4))&": "&TEXT(ROUND(SUM(BC29:BJ29),2),"#.##0,00") & " €"& " | "& BB29,BB29)} -> Sachanlage 1 | BN68: {=IFERROR("#"&_xlfn.SEQUENCE(COUNTA(BO68:BO72)),"")} -> #1 | BO68: {=IFERROR(INDIRECT(ADDRESS(10,MIN(IF(BP29:BW29<>"",COLUMN(BP29:BW29))),4))&": "&TEXT(ROUND(SUM(BP29:BW29),2),"#.##0,00") & " €"& " | "& BO29,BO29)} -> Sachanlage 1 | CA68: {=IFERROR("#"&_xlfn.SEQUENCE(COUNTA(CB68:CB72)),"")} -> #1 | CB68: {=IFERROR(INDIRECT(ADDRESS(10,MIN(IF(CC29:CJ29<>"",COLUMN(CC29:CJ29))),4))&": "&TEXT(ROUND(SUM(CC29:CJ29),2),"#.##0,00") & " €"& " | "& CB29,CB29)} -> Sachanlage 1
A69: #2 | B69: {=IFERROR(INDIRECT(ADDRESS(10,MIN(IF(C30:J30<>"",COLUMN(C30:J30))),4))&": "&TEXT(ROUND(SUM(C30:J30),2),"#.##0,00") & " €"& " | "& B30,B30)} -> Sachanlage 2 | N69: #2 | O69: {=IFERROR(INDIRECT(ADDRESS(10,MIN(IF(P30:W30<>"",COLUMN(P30:W30))),4))&": "&TEXT(ROUND(SUM(P30:W30),2),"#.##0,00") & " €"& " | "& O30,O30)} -> Sachanlage 2 | AA69: #2 | AB69: {=IFERROR(INDIRECT(ADDRESS(10,MIN(IF(AC30:AJ30<>"",COLUMN(AC30:AJ30))),4))&": "&TEXT(ROUND(SUM(AC30:AJ30),2),"#.##0,00") & " €"& " | "& AB30,AB30)} -> Sachanlage 2 | AN69: #2 | AO69: {=IFERROR(INDIRECT(ADDRESS(10,MIN(IF(AP30:AW30<>"",COLUMN(AP30:AW30))),4))&": "&TEXT(ROUND(SUM(AP30:AW30),2),"#.##0,00") & " €"& " | "& AO30,AO30)} -> Sachanlage 2 | BA69: #2 | BB69: {=IFERROR(INDIRECT(ADDRESS(10,MIN(IF(BC30:BJ30<>"",COLUMN(BC30:BJ30))),4))&": "&TEXT(ROUND(SUM(BC30:BJ30),2),"#.##0,00") & " €"& " | "& BB30,BB30)} -> Sachanlage 2 | BN69: #2 | BO69: {=IFERROR(INDIRECT(ADDRESS(10,MIN(IF(BP30:BW30<>"",COLUMN(BP30:BW30))),4))&": "&TEXT(ROUND(SUM(BP30:BW30),2),"#.##0,00") & " €"& " | "& BO30,BO30)} -> Sachanlage 2 | CA69: #2 | CB69: {=IFERROR(INDIRECT(ADDRESS(10,MIN(IF(CC30:CJ30<>"",COLUMN(CC30:CJ30))),4))&": "&TEXT(ROUND(SUM(CC30:CJ30),2),"#.##0,00") & " €"& " | "& CB30,CB30)} -> Sachanlage 2
A70: #3 | B70: {=IFERROR(INDIRECT(ADDRESS(10,MIN(IF(C31:J31<>"",COLUMN(C31:J31))),4))&": "&TEXT(ROUND(SUM(C31:J31),2),"#.##0,00") & " €"& " | "& B31,B31)} -> Sachanlage 3 | N70: #3 | O70: {=IFERROR(INDIRECT(ADDRESS(10,MIN(IF(P31:W31<>"",COLUMN(P31:W31))),4))&": "&TEXT(ROUND(SUM(P31:W31),2),"#.##0,00") & " €"& " | "& O31,O31)} -> Sachanlage 3 | AA70: #3 | AB70: {=IFERROR(INDIRECT(ADDRESS(10,MIN(IF(AC31:AJ31<>"",COLUMN(AC31:AJ31))),4))&": "&TEXT(ROUND(SUM(AC31:AJ31),2),"#.##0,00") & " €"& " | "& AB31,AB31)} -> Sachanlage 3 | AN70: #3 | AO70: {=IFERROR(INDIRECT(ADDRESS(10,MIN(IF(AP31:AW31<>"",COLUMN(AP31:AW31))),4))&": "&TEXT(ROUND(SUM(AP31:AW31),2),"#.##0,00") & " €"& " | "& AO31,AO31)} -> Sachanlage 3 | BA70: #3 | BB70: {=IFERROR(INDIRECT(ADDRESS(10,MIN(IF(BC31:BJ31<>"",COLUMN(BC31:BJ31))),4))&": "&TEXT(ROUND(SUM(BC31:BJ31),2),"#.##0,00") & " €"& " | "& BB31,BB31)} -> Sachanlage 3 | BN70: #3 | BO70: {=IFERROR(INDIRECT(ADDRESS(10,MIN(IF(BP31:BW31<>"",COLUMN(BP31:BW31))),4))&": "&TEXT(ROUND(SUM(BP31:BW31),2),"#.##0,00") & " €"& " | "& BO31,BO31)} -> Sachanlage 3 | CA70: #3 | CB70: {=IFERROR(INDIRECT(ADDRESS(10,MIN(IF(CC31:CJ31<>"",COLUMN(CC31:CJ31))),4))&": "&TEXT(ROUND(SUM(CC31:CJ31),2),"#.##0,00") & " €"& " | "& CB31,CB31)} -> Sachanlage 3
A71: #4 | B71: {=IFERROR(INDIRECT(ADDRESS(10,MIN(IF(C32:J32<>"",COLUMN(C32:J32))),4))&": "&TEXT(ROUND(SUM(C32:J32),2),"#.##0,00") & " €"& " | "& B32,B32)} -> Sachanlage 4 | N71: #4 | O71: {=IFERROR(INDIRECT(ADDRESS(10,MIN(IF(P32:W32<>"",COLUMN(P32:W32))),4))&": "&TEXT(ROUND(SUM(P32:W32),2),"#.##0,00") & " €"& " | "& O32,O32)} -> Sachanlage 4 | AA71: #4 | AB71: {=IFERROR(INDIRECT(ADDRESS(10,MIN(IF(AC32:AJ32<>"",COLUMN(AC32:AJ32))),4))&": "&TEXT(ROUND(SUM(AC32:AJ32),2),"#.##0,00") & " €"& " | "& AB32,AB32)} -> Sachanlage 4 | AN71: #4 | AO71: {=IFERROR(INDIRECT(ADDRESS(10,MIN(IF(AP32:AW32<>"",COLUMN(AP32:AW32))),4))&": "&TEXT(ROUND(SUM(AP32:AW32),2),"#.##0,00") & " €"& " | "& AO32,AO32)} -> Sachanlage 4 | BA71: #4 | BB71: {=IFERROR(INDIRECT(ADDRESS(10,MIN(IF(BC32:BJ32<>"",COLUMN(BC32:BJ32))),4))&": "&TEXT(ROUND(SUM(BC32:BJ32),2),"#.##0,00") & " €"& " | "& BB32,BB32)} -> Sachanlage 4 | BN71: #4 | BO71: {=IFERROR(INDIRECT(ADDRESS(10,MIN(IF(BP32:BW32<>"",COLUMN(BP32:BW32))),4))&": "&TEXT(ROUND(SUM(BP32:BW32),2),"#.##0,00") & " €"& " | "& BO32,BO32)} -> Sachanlage 4 | CA71: #4 | CB71: {=IFERROR(INDIRECT(ADDRESS(10,MIN(IF(CC32:CJ32<>"",COLUMN(CC32:CJ32))),4))&": "&TEXT(ROUND(SUM(CC32:CJ32),2),"#.##0,00") & " €"& " | "& CB32,CB32)} -> Sachanlage 4
A72: #5 | B72: {=IFERROR(INDIRECT(ADDRESS(10,MIN(IF(C33:J33<>"",COLUMN(C33:J33))),4))&": "&TEXT(ROUND(SUM(C33:J33),2),"#.##0,00") & " €"& " | "& B33,B33)} -> Sachanlage 5 | N72: #5 | O72: {=IFERROR(INDIRECT(ADDRESS(10,MIN(IF(P33:W33<>"",COLUMN(P33:W33))),4))&": "&TEXT(ROUND(SUM(P33:W33),2),"#.##0,00") & " €"& " | "& O33,O33)} -> Sachanlage 5 | AA72: #5 | AB72: {=IFERROR(INDIRECT(ADDRESS(10,MIN(IF(AC33:AJ33<>"",COLUMN(AC33:AJ33))),4))&": "&TEXT(ROUND(SUM(AC33:AJ33),2),"#.##0,00") & " €"& " | "& AB33,AB33)} -> Sachanlage 5 | AN72: #5 | AO72: {=IFERROR(INDIRECT(ADDRESS(10,MIN(IF(AP33:AW33<>"",COLUMN(AP33:AW33))),4))&": "&TEXT(ROUND(SUM(AP33:AW33),2),"#.##0,00") & " €"& " | "& AO33,AO33)} -> Sachanlage 5 | BA72: #5 | BB72: {=IFERROR(INDIRECT(ADDRESS(10,MIN(IF(BC33:BJ33<>"",COLUMN(BC33:BJ33))),4))&": "&TEXT(ROUND(SUM(BC33:BJ33),2),"#.##0,00") & " €"& " | "& BB33,BB33)} -> Sachanlage 5 | BN72: #5 | BO72: {=IFERROR(INDIRECT(ADDRESS(10,MIN(IF(BP33:BW33<>"",COLUMN(BP33:BW33))),4))&": "&TEXT(ROUND(SUM(BP33:BW33),2),"#.##0,00") & " €"& " | "& BO33,BO33)} -> Sachanlage 5 | CA72: #5 | CB72: {=IFERROR(INDIRECT(ADDRESS(10,MIN(IF(CC33:CJ33<>"",COLUMN(CC33:CJ33))),4))&": "&TEXT(ROUND(SUM(CC33:CJ33),2),"#.##0,00") & " €"& " | "& CB33,CB33)} -> Sachanlage 5
A75: =$C$6 -> Ping-Pong-Roboter | B75: =$C$6 -> Ping-Pong-Roboter | C75: =$C$6 -> Ping-Pong-Roboter | D75: =$C$6 -> Ping-Pong-Roboter | E75: =$C$6 -> Ping-Pong-Roboter | F75: =$C$6 -> Ping-Pong-Roboter | G75: =$C$6 -> Ping-Pong-Roboter | H75: =$C$6 -> Ping-Pong-Roboter | ... K75: =$C$6 -> Ping-Pong-Roboter | N75: =$P$6 -> 0 | O75: =$P$6 -> 0 | P75: =$P$6 -> 0 | Q75: =$P$6 -> 0 | R75: =$P$6 -> 0 | S75: =$P$6 -> 0 | T75: =$P$6 -> 0 | U75: =$P$6 -> 0 | W75: =$P$6 -> 0 | Y75: =$P$6 -> 0 | AA75: =$AC$6 -> 0 | AB75: =$AC$6 -> 0 | AC75: =$AC$6 -> 0 | AD75: =$AC$6 -> 0 | AE75: =$AC$6 -> 0 | AF75: =$AC$6 -> 0 | AG75: =$AC$6 -> 0 | AH75: =$AC$6 -> 0 | AJ75: =$AC$6 -> 0 | AL75: =$AC$6 -> 0 | AN75: =$AP$6 -> 0 | AO75: =$AP$6 -> 0 | AP75: =$AP$6 -> 0 | AQ75: =$AP$6 -> 0 | AR75: =$AP$6 -> 0 | AS75: =$AP$6 -> 0 | AT75: =$AP$6 -> 0 | AU75: =$AP$6 -> 0 | AW75: =$AP$6 -> 0 | AY75: =$AP$6 -> 0 | BA75: =$BC$6 -> 0 | BB75: =$BC$6 -> 0 | BC75: =$BC$6 -> 0 | BD75: =$BC$6 -> 0 | BE75: =$BC$6 -> 0 | BF75: =$BC$6 -> 0 | BG75: =$BC$6 -> 0 | BH75: =$BC$6 -> 0 | BJ75: =$BC$6 -> 0 | BL75: =$BC$6 -> 0 | BN75: =$BP$6 -> 0 | BO75: =$BP$6 -> 0 | BP75: =$BP$6 -> 0 | BQ75: =$BP$6 -> 0 | BR75: =$BP$6 -> 0 | BS75: =$BP$6 -> 0 | BT75: =$BP$6 -> 0 | BU75: =$BP$6 -> 0 | BW75: =$BP$6 -> 0 | BY75: =$BP$6 -> 0 | CA75: =$CC$6 -> 0 | CB75: =$CC$6 -> 0 | CC75: =$CC$6 -> 0 | CD75: =$CC$6 -> 0 | CE75: =$CC$6 -> 0 | CF75: =$CC$6 -> 0 | CG75: =$CC$6 -> 0 | CH75: =$CC$6 -> 0 | CJ75: =$CC$6 -> 0 | CL75: =$CC$6 -> 0
B77: Disclaimer: Alle kalkulierten Zahlen sind vom Anwender zu überprüfen. | D77: © consider it GmbH (2023). Die Vervielfältigung oder Veräußerung dieser Datei ist Dritten untersagt. | O77: Disclaimer: Alle kalkulierten Zahlen sind vom Anwender zu überprüfen. | Q77: © consider it GmbH (2023). Die Vervielfältigung oder Veräußerung dieser Datei ist Dritten untersagt. | AB77: Disclaimer: Alle kalkulierten Zahlen sind vom Anwender zu überprüfen. | AD77: © consider it GmbH (2023). Die Vervielfältigung oder Veräußerung dieser Datei ist Dritten untersagt. | AO77: Disclaimer: Alle kalkulierten Zahlen sind vom Anwender zu überprüfen. | AQ77: © consider it GmbH (2023). Die Vervielfältigung oder Veräußerung dieser Datei ist Dritten untersagt. | BB77: Disclaimer: Alle kalkulierten Zahlen sind vom Anwender zu überprüfen. | BD77: © consider it GmbH (2023). Die Vervielfältigung oder Veräußerung dieser Datei ist Dritten untersagt. | BO77: Disclaimer: Alle kalkulierten Zahlen sind vom Anwender zu überprüfen. | BQ77: © consider it GmbH (2023). Die Vervielfältigung oder Veräußerung dieser Datei ist Dritten untersagt. | CB77: Disclaimer: Alle kalkulierten Zahlen sind vom Anwender zu überprüfen. | CD77: © consider it GmbH (2023). Die Vervielfältigung oder Veräußerung dieser Datei ist Dritten untersagt.

Sheet Personaleingabe
I9: =_xlfn.LET( _xlpm.delimiter,", ", _xlpm.corrupted_cols,_xlfn.TEXTJOIN(_xlpm.delimiter,TRUE,$I$10:$AF$10), _xlpm.removed_chars,LEN(_xlpm.corrupted_cols)-LEN(SUBSTITUTE(_xlpm.corrupted_cols,_xlpm.delimiter,"")), _xlpm.amount_corrupted_cols,IF(LEN(_xlpm.corrupted_cols)=0,0,_xlpm.removed_chars/LEN(_xlpm.delimiter)+1), _xlpm.corrupted_cols_display, IF(_xlpm.amount_corrupted_cols>=2,SUBSTITUTE(_xlpm.corrupted_cols,_xlpm.delimiter," & ",_xlpm.amount_corrupted_cols-1),_xlpm.corrupted_cols), _xlpm.info_msg,IF(_xlpm.amount_corrupted_cols=0,"", IF(_xlpm.amount_corrupted_cols=1,"In Spalte "&_xlpm.corrupted_cols_display&" ist die Formel nicht mehr in allen Zeilen gefüllt.", "In den Spalten " & _xlpm.corrupted_cols_display & " ist die Formel nicht mehr in allen Zeilen gefüllt.")), IF(_xlpm.info_msg&"1"<>"1","Hinweis: " & _xlpm.info_msg,_xlpm.info_msg) ) -> Hinweis: In den Spalten S & T ist die Formel nicht mehr in allen Zeilen gefüllt.
S10: =_xlfn.LET( _xlpm.amount_missing,COUNTIF(MitarbeiterFTE[Steuerbrutto + AG-Anteile],""), _xlpm.adresse,ADDRESS(1,COLUMN(S10),4,1), IF(_xlpm.amount_missing>0,LEFT(_xlpm.adresse,LEN(_xlpm.adresse)-1),"")) -> S | T10: =_xlfn.LET( _xlpm.amount_missing,COUNTIF(MitarbeiterFTE[Steuerbrutto],""), _xlpm.adresse,ADDRESS(1,COLUMN(T10),4,1), IF(_xlpm.amount_missing>0,LEFT(_xlpm.adresse,LEN(_xlpm.adresse)-1),"")) -> T | V10: =_xlfn.LET( _xlpm.amount_missing,COUNTIF(MitarbeiterFTE[Feiertage],""), _xlpm.adresse,ADDRESS(1,COLUMN(V10),4,1), IF(_xlpm.amount_missing>0,LEFT(_xlpm.adresse,LEN(_xlpm.adresse)-1),"")) | W10: =_xlfn.LET( _xlpm.amount_missing,COUNTIF(MitarbeiterFTE[Sonst. Abwesend],""), _xlpm.adresse,ADDRESS(1,COLUMN(W10),4,1), IF(_xlpm.amount_missing>0,LEFT(_xlpm.adresse,LEN(_xlpm.adresse)-1),"")) | X10: =_xlfn.LET( _xlpm.amount_missing,COUNTIF(MitarbeiterFTE[Sum Abwesend],""), _xlpm.adresse,ADDRESS(1,COLUMN(X10),4,1), IF(_xlpm.amount_missing>0,LEFT(_xlpm.adresse,LEN(_xlpm.adresse)-1),"")) | Y10: =_xlfn.LET( _xlpm.amount_missing,COUNTIF(MitarbeiterFTE[Stunden],""), _xlpm.adresse,ADDRESS(1,COLUMN(Y10),4,1), IF(_xlpm.amount_missing>0,LEFT(_xlpm.adresse,LEN(_xlpm.adresse)-1),"")) | Z10: =_xlfn.LET( _xlpm.amount_missing,COUNTIF(MitarbeiterFTE[Kosten],""), _xlpm.adresse,ADDRESS(1,COLUMN(Z10),4,1), IF(_xlpm.amount_missing>0,LEFT(_xlpm.adresse,LEN(_xlpm.adresse)-1),"")) | AA10: =_xlfn.LET( _xlpm.amount_missing,COUNTIF(MitarbeiterFTE[lookup],""), _xlpm.adresse,ADDRESS(1,COLUMN(AA10),4,1), IF(_xlpm.amount_missing>0,LEFT(_xlpm.adresse,LEN(_xlpm.adresse)-1),"")) | AF10: =_xlfn.LET( _xlpm.amount_missing,COUNTIF(MitarbeiterFTE[Ausbildungsstatus],""), _xlpm.adresse,ADDRESS(1,COLUMN(AF10),4,1), IF(_xlpm.amount_missing>0,LEFT(_xlpm.adresse,LEN(_xlpm.adresse)-1),""))
E11: Name der Firma: | F11: =IF('Ganzes Unternehmen'!C8=0,"In Allg. Angaben eingeben.",'Ganzes Unternehmen'!C8) -> Ping Zhou Consulting | I11: Tragen Sie MitarbeiterInnen zudem hier ein! Sofern MitarbeiterInnen keine Zeit schreiben, füllen Sie die Urlaubs- und Krankheitsliste. Die Planstunden basieren entweder auf eingetragenen Abwesenheitstagen oder auf 28,9 (Ø in DE) Urlaubstagen und 11,2 (Ø in DE) Krankheitstagen. | V11: Excl. FT | W11: Excl. Abwesend | AO11: Jahr | AP11: Name | AZ11: {=_xlfn.UNIQUE(MitarbeiterFTE[Name])} -> Student 1
E12: Vorhabensname | F12: Vorhabens-ID | S12: Gehalt | V12: nein | W12: nein | AI12: Name | AJ12: Tag | AK12: Urlaub (U), Krankheit (K), Andere Tätigkeiten (A); Sonderurlaub (S) | AL12: FT/WE | AM12: lookup | AO12: {=_xlfn.UNIQUE(_xlfn._xlws.FILTER(Arbeitszeiten[Name]&"|"&YEAR(Arbeitszeiten[Tag]),Arbeitszeiten[Name]&"|"&YEAR(Arbeitszeiten[Tag])<>"|1900"))} -> #VALUE! | AP12: =IF(AO12&"1"<>"1",RIGHT(AO12,4),"") -> #VALUE! | AQ12: =IF(AO12&"1"="1","",LEFT(AO12,LEN(AO12)-5)) -> #VALUE! | AZ12: Student 2
E13: =_xlfn.LET(_xlpm.out,'Ganzes Unternehmen'!B16,IF(OR(_xlpm.out=0,_xlpm.out="Allgemein"),"",_xlpm.out)) -> Ping-Pong-Roboter | I13: Name | J13: Bundesland | K13: HS | L13: Tech | M13: Sonst | N13: Vorhaben | O13: Art d. Arbeiten | P13: Monat | Q13: Jahr | R13: %-Vorhaben | S13: Steuerbrutto + AG-Anteile | T13: Steuerbrutto | U13: Std. / Wo. | V13: Feiertage | W13: Sonst. Abwesend | X13: Sum Abwesend | Y13: Stunden | Z13: Kosten | AA13: lookup | AB13: BWD | AC13: NWD | AD13: BWD Jahr | AE13: NWD Jahr | AF13: Ausbildungsstatus | AI13: Max Mustermann | AJ13: 45296 | AK13: U | AL13: {=IF(Table6[[#This Row],[Name]]&"1"="1",2,_xlfn.LET( _xlpm.Bundesland,_xlfn.XLOOKUP(Table6[[#This Row],[Name]]&YEAR(Table6[[#This Row],[Tag]])&MONTH(Table6[[#This Row],[Tag]]),MitarbeiterFTE[Name]&MitarbeiterFTE[Jahr]&MitarbeiterFTE[Monat],MitarbeiterFTE[Bundesland],"Schleswig-Holstein",0,1), _xlpm.BundeslandAry,_xlfn.XLOOKUP(_xlpm.Bundesland,Bundesländer[Deutsch],Bundesländer[Abkürzung]), _xlpm.ary,_xlfn.XLOOKUP(_xlpm.BundeslandAry,Feiertage[[#Headers],[BW]:[TH]],Feiertage[IsWorkday]&Feiertage[Datum]&Feiertage[[BW]:[TH]],"",0,1), SUM(IF(_xlpm.ary="1"&Table6[[#This Row],[Tag]]&"x",1,0)))+IF(WEEKDAY(Table6[[#This Row],[Tag]],2)>=6,1,0))} -> 0 | AM13: =IF(Table6[[#This Row],[FT/WE]]=2,"",Table6[[#This Row],[Name]]&Table6[[#This Row],[Tag]]) -> Max Mustermann45296 | AP13: =IF(AO13&"1"<>"1",RIGHT(AO13,4),"") | AQ13: =IF(AO13&"1"="1","",LEFT(AO13,LEN(AO13)-5)) | AZ13: 0
E14: =_xlfn.LET(_xlpm.out,'Ganzes Unternehmen'!B17,IF(OR(_xlpm.out=0,_xlpm.out="Allgemein"),"",_xlpm.out)) | I14: Student 1 | J14: Baden-Württemberg | K14: ja | L14: nein | M14: nein | N14: Ping-Pong-Roboter | O14: FuE-Tätigkeiten am Vorhaben | P14: 9 | Q14: 2026 | R14: 1 | S14: 650 | T14: 500 | U14: 8 | V14: {=_xlfn.LET( _xlpm.BL,_xlfn.XLOOKUP(MitarbeiterFTE[[#This Row],[Bundesland]],Bundesländer[Deutsch],Bundesländer[Abkürzung]), _xlpm.ary,_xlfn.XLOOKUP(_xlpm.BL,Feiertage[[#Headers],[BW]:[TH]],Feiertage[IsWorkday]&Feiertage[MJJJJ]&Feiertage[[BW]:[TH]],"",0,1), _xlpm.out,IFERROR(SUM(IF(_xlpm.ary="1"&MitarbeiterFTE[[#This Row],[Monat]]&MitarbeiterFTE[[#This Row],[Jahr]]&"x",1,0)),"BL ausw."), IF(MitarbeiterFTE[[#This Row],[Name]]&"1"="1","input missing",_xlpm.out) )} -> 0 | W14: =_xlfn.LET( _xlpm.abw,COUNTIFS(Table6[Tag],">="&DATE(MitarbeiterFTE[[#This Row],[Jahr]],MitarbeiterFTE[[#This Row],[Monat]],1),Table6[Tag],"<="&EOMONTH(DATE(MitarbeiterFTE[[#This Row],[Jahr]],MitarbeiterFTE[[#This Row],[Monat]],1),0),Table6[Name],MitarbeiterFTE[[#This Row],[Name]],Table6[FT/WE],0), IF(MitarbeiterFTE[[#This Row],[Name]]&"1"="1","input missing",_xlpm.abw)) -> 0 | X14: =_xlfn.LET( _xlpm.abwStatistik,(28.9+11.2)/12, _xlpm.isEingetragen,COUNTIFS(Table6[Tag],">="&DATE(MitarbeiterFTE[[#This Row],[Jahr]],1,1),Table6[Tag],"<="&DATE(MitarbeiterFTE[[#This Row],[Jahr]],12,31),Table6[Name],MitarbeiterFTE[[#This Row],[Name]]), _xlpm.isExclAbw,$W$12="ja", _xlpm.abwesend,IF(_xlpm.isExclAbw,0, IF(_xlpm.isEingetragen, MitarbeiterFTE[[#This Row],[Sonst. Abwesend]], IF(MitarbeiterFTE[[#This Row],[Sonst. Abwesend]]>0,MitarbeiterFTE[[#This Row],[Sonst. Abwesend]], _xlpm.abwStatistik))), _xlpm.isExclFT,$V$12="ja", _xlpm.ExclFT,_xlpm.abwesend, _xlpm.ExclFTAbw,0, _xlpm.inklAlles,_xlpm.abwesend+MitarbeiterFTE[[#This Row],[Feiertage]], IFERROR(IF(AND(_xlpm.isExclAbw,_xlpm.isExclFT), _xlpm.ExclFTAbw, IF(_xlpm.isExclFT,_xlpm.ExclFT, _xlpm.inklAlles)),"input missing") ) -> 3.3416667 | Y14: =_xlfn.LET( _xlpm.Monat_Start,DATE(MitarbeiterFTE[[#This Row],[Jahr]],MitarbeiterFTE[[#This Row],[Monat]],1), _xlpm.AT_Monat,NETWORKDAYS(_xlpm.Monat_Start,EOMONTH(_xlpm.Monat_Start,0)), IFERROR((MitarbeiterFTE[[#This Row],[Std. / Wo.]]/5)*MitarbeiterFTE[[#This Row],[%-Vorhaben]]*(_xlpm.AT_Monat-MitarbeiterFTE[[#This Row],[Sum Abwesend]]),"input missing")) -> 29.853333 | Z14: =_xlfn.LET( _xlpm.AT_Jahr, NETWORKDAYS(DATE(MitarbeiterFTE[[#This Row],[Jahr]],1,1),DATE(MitarbeiterFTE[[#This Row],[Jahr]],12,31)), _xlpm.Monat_Start,DATE(MitarbeiterFTE[[#This Row],[Jahr]],MitarbeiterFTE[[#This Row],[Monat]],1), _xlpm.AT_Monat,NETWORKDAYS(_xlpm.Monat_Start,EOMONTH(_xlpm.Monat_Start,0))-MitarbeiterFTE[[#This Row],[Sum Abwesend]], _xlpm.Kalk_Gehalt_Jahr,MitarbeiterFTE[[#This Row],[Steuerbrutto + AG-Anteile]]/_xlpm.AT_Monat*_xlpm.AT_Jahr, _xlpm.Kalk_Stundensatz,_xlpm.Kalk_Gehalt_Jahr/(MitarbeiterFTE[[#This Row],[Std. / Wo.]]/5*_xlpm.AT_Jahr), _xlpm.Kalk_Kosten,_xlpm.Kalk_Stundensatz*MitarbeiterFTE[[#This Row],[Stunden]], IFERROR(_xlpm.Kalk_Kosten,"input missing") ) -> 650 | AA14: =_xlfn.LET(_xlpm.var,MitarbeiterFTE[[#This Row],[Name]]&"|"&MitarbeiterFTE[[#This Row],[Vorhaben]]&"|"&MitarbeiterFTE[[#This Row],[Monat]]&"|"&MitarbeiterFTE[[#This Row],[Jahr]], IF(_xlpm.var="|||","input missing",_xlpm.var)) -> Student 1|Ping-Pong-Roboter|9|2026 | AB14: =_xlfn.LET( _xlpm.start,DATE(MitarbeiterFTE[[#This Row],[Jahr]],MitarbeiterFTE[[#This Row],[Monat]],1), _xlpm.end,EOMONTH(_xlpm.start,0), NETWORKDAYS(_xlpm.start,_xlpm.end)) -> 22 | AC14: =MitarbeiterFTE[[#This Row],[BWD]]-MitarbeiterFTE[[#This Row],[Sum Abwesend]] -> 18.658333 | AD14: =SUMIFS(MitarbeiterFTE[BWD],MitarbeiterFTE[Jahr],MitarbeiterFTE[[#This Row],[Jahr]],MitarbeiterFTE[Name],MitarbeiterFTE[[#This Row],[Name]]) -> 88 | AE14: =SUMIFS(MitarbeiterFTE[NWD],MitarbeiterFTE[Jahr],MitarbeiterFTE[[#This Row],[Jahr]],MitarbeiterFTE[Name],MitarbeiterFTE[[#This Row],[Name]]) -> 73.633333 | AF14: =IF(MitarbeiterFTE[[#This Row],[HS]]="ja",2,IF(MitarbeiterFTE[[#This Row],[Tech]]="ja",1,IF(MitarbeiterFTE[[#This Row],[Sonst]]="ja",0,"input missing"))) -> 2 | AL14: {=IF(Table6[[#This Row],[Name]]&"1"="1",2,_xlfn.LET( _xlpm.Bundesland,_xlfn.XLOOKUP(Table6[[#This Row],[Name]]&YEAR(Table6[[#This Row],[Tag]])&MONTH(Table6[[#This Row],[Tag]]),MitarbeiterFTE[Name]&MitarbeiterFTE[Jahr]&MitarbeiterFTE[Monat],MitarbeiterFTE[Bundesland],"Schleswig-Holstein",0,1), _xlpm.BundeslandAry,_xlfn.XLOOKUP(_xlpm.Bundesland,Bundesländer[Deutsch],Bundesländer[Abkürzung]), _xlpm.ary,_xlfn.XLOOKUP(_xlpm.BundeslandAry,Feiertage[[#Headers],[BW]:[TH]],Feiertage[IsWorkday]&Feiertage[Datum]&Feiertage[[BW]:[TH]],"",0,1), SUM(IF(_xlpm.ary="1"&Table6[[#This Row],[Tag]]&"x",1,0)))+IF(WEEKDAY(Table6[[#This Row],[Tag]],2)>=6,1,0))} -> 2 | AM14: =IF(Table6[[#This Row],[FT/WE]]=2,"",Table6[[#This Row],[Name]]&Table6[[#This Row],[Tag]]) | AP14: =IF(AO14&"1"<>"1",RIGHT(AO14,4),"") | AQ14: =IF(AO14&"1"="1","",LEFT(AO14,LEN(AO14)-5))
E15: =_xlfn.LET(_xlpm.out,'Ganzes Unternehmen'!B18,IF(OR(_xlpm.out=0,_xlpm.out="Allgemein"),"",_xlpm.out)) | I15: Student 1 | J15: Baden-Württemberg | K15: ja | L15: nein | M15: nein | N15: Ping-Pong-Roboter | O15: FuE-Tätigkeiten am Vorhaben | P15: 10 | Q15: 2026 | R15: 1 | S15: 650 | T15: 500 | U15: 8 | V15: {=_xlfn.LET( _xlpm.BL,_xlfn.XLOOKUP(MitarbeiterFTE[[#This Row],[Bundesland]],Bundesländer[Deutsch],Bundesländer[Abkürzung]), _xlpm.ary,_xlfn.XLOOKUP(_xlpm.BL,Feiertage[[#Headers],[BW]:[TH]],Feiertage[IsWorkday]&Feiertage[MJJJJ]&Feiertage[[BW]:[TH]],"",0,1), _xlpm.out,IFERROR(SUM(IF(_xlpm.ary="1"&MitarbeiterFTE[[#This Row],[Monat]]&MitarbeiterFTE[[#This Row],[Jahr]]&"x",1,0)),"BL ausw."), IF(MitarbeiterFTE[[#This Row],[Name]]&"1"="1","input missing",_xlpm.out) )} -> 0 | W15: =_xlfn.LET( _xlpm.abw,COUNTIFS(Table6[Tag],">="&DATE(MitarbeiterFTE[[#This Row],[Jahr]],MitarbeiterFTE[[#This Row],[Monat]],1),Table6[Tag],"<="&EOMONTH(DATE(MitarbeiterFTE[[#This Row],[Jahr]],MitarbeiterFTE[[#This Row],[Monat]],1),0),Table6[Name],MitarbeiterFTE[[#This Row],[Name]],Table6[FT/WE],0), IF(MitarbeiterFTE[[#This Row],[Name]]&"1"="1","input missing",_xlpm.abw)) -> 0 | X15: =_xlfn.LET( _xlpm.abwStatistik,(28.9+11.2)/12, _xlpm.isEingetragen,COUNTIFS(Table6[Tag],">="&DATE(MitarbeiterFTE[[#This Row],[Jahr]],1,1),Table6[Tag],"<="&DATE(MitarbeiterFTE[[#This Row],[Jahr]],12,31),Table6[Name],MitarbeiterFTE[[#This Row],[Name]]), _xlpm.isExclAbw,$W$12="ja", _xlpm.abwesend,IF(_xlpm.isExclAbw,0, IF(_xlpm.isEingetragen, MitarbeiterFTE[[#This Row],[Sonst. Abwesend]], IF(MitarbeiterFTE[[#This Row],[Sonst. Abwesend]]>0,MitarbeiterFTE[[#This Row],[Sonst. Abwesend]], _xlpm.abwStatistik))), _xlpm.isExclFT,$V$12="ja", _xlpm.ExclFT,_xlpm.abwesend, _xlpm.ExclFTAbw,0, _xlpm.inklAlles,_xlpm.abwesend+MitarbeiterFTE[[#This Row],[Feiertage]], IFERROR(IF(AND(_xlpm.isExclAbw,_xlpm.isExclFT), _xlpm.ExclFTAbw, IF(_xlpm.isExclFT,_xlpm.ExclFT, _xlpm.inklAlles)),"input missing") ) -> 3.3416667 | Y15: =_xlfn.LET( _xlpm.Monat_Start,DATE(MitarbeiterFTE[[#This Row],[Jahr]],MitarbeiterFTE[[#This Row],[Monat]],1), _xlpm.AT_Monat,NETWORKDAYS(_xlpm.Monat_Start,EOMONTH(_xlpm.Monat_Start,0)), IFERROR((MitarbeiterFTE[[#This Row],[Std. / Wo.]]/5)*MitarbeiterFTE[[#This Row],[%-Vorhaben]]*(_xlpm.AT_Monat-MitarbeiterFTE[[#This Row],[Sum Abwesend]]),"input missing")) -> 29.853333 | Z15: =_xlfn.LET( _xlpm.AT_Jahr, NETWORKDAYS(DATE(MitarbeiterFTE[[#This Row],[Jahr]],1,1),DATE(MitarbeiterFTE[[#This Row],[Jahr]],12,31)), _xlpm.Monat_Start,DATE(MitarbeiterFTE[[#This Row],[Jahr]],MitarbeiterFTE[[#This Row],[Monat]],1), _xlpm.AT_Monat,NETWORKDAYS(_xlpm.Monat_Start,EOMONTH(_xlpm.Monat_Start,0))-MitarbeiterFTE[[#This Row],[Sum Abwesend]], _xlpm.Kalk_Gehalt_Jahr,MitarbeiterFTE[[#This Row],[Steuerbrutto + AG-Anteile]]/_xlpm.AT_Monat*_xlpm.AT_Jahr, _xlpm.Kalk_Stundensatz,_xlpm.Kalk_Gehalt_Jahr/(MitarbeiterFTE[[#This Row],[Std. / Wo.]]/5*_xlpm.AT_Jahr), _xlpm.Kalk_Kosten,_xlpm.Kalk_Stundensatz*MitarbeiterFTE[[#This Row],[Stunden]], IFERROR(_xlpm.Kalk_Kosten,"input missing") ) -> 650 | AA15: =_xlfn.LET(_xlpm.var,MitarbeiterFTE[[#This Row],[Name]]&"|"&MitarbeiterFTE[[#This Row],[Vorhaben]]&"|"&MitarbeiterFTE[[#This Row],[Monat]]&"|"&MitarbeiterFTE[[#This Row],[Jahr]], IF(_xlpm.var="|||","input missing",_xlpm.var)) -> Student 1|Ping-Pong-Roboter|10|2026 | AB15: =_xlfn.LET( _xlpm.start,DATE(MitarbeiterFTE[[#This Row],[Jahr]],MitarbeiterFTE[[#This Row],[Monat]],1), _xlpm.end,EOMONTH(_xlpm.start,0), NETWORKDAYS(_xlpm.start,_xlpm.end)) -> 22 | AC15: =MitarbeiterFTE[[#This Row],[BWD]]-MitarbeiterFTE[[#This Row],[Sum Abwesend]] -> 18.658333 | AD15: =SUMIFS(MitarbeiterFTE[BWD],MitarbeiterFTE[Jahr],MitarbeiterFTE[[#This Row],[Jahr]],MitarbeiterFTE[Name],MitarbeiterFTE[[#This Row],[Name]]) -> 88 | AE15: =SUMIFS(MitarbeiterFTE[NWD],MitarbeiterFTE[Jahr],MitarbeiterFTE[[#This Row],[Jahr]],MitarbeiterFTE[Name],MitarbeiterFTE[[#This Row],[Name]]) -> 73.633333 | AF15: =IF(MitarbeiterFTE[[#This Row],[HS]]="ja",2,IF(MitarbeiterFTE[[#This Row],[Tech]]="ja",1,IF(MitarbeiterFTE[[#This Row],[Sonst]]="ja",0,"input missing"))) -> 2 | AL15: {=IF(Table6[[#This Row],[Name]]&"1"="1",2,_xlfn.LET( _xlpm.Bundesland,_xlfn.XLOOKUP(Table6[[#This Row],[Name]]&YEAR(Table6[[#This Row],[Tag]])&MONTH(Table6[[#This Row],[Tag]]),MitarbeiterFTE[Name]&MitarbeiterFTE[Jahr]&MitarbeiterFTE[Monat],MitarbeiterFTE[Bundesland],"Schleswig-Holstein",0,1), _xlpm.BundeslandAry,_xlfn.XLOOKUP(_xlpm.Bundesland,Bundesländer[Deutsch],Bundesländer[Abkürzung]), _xlpm.ary,_xlfn.XLOOKUP(_xlpm.BundeslandAry,Feiertage[[#Headers],[BW]:[TH]],Feiertage[IsWorkday]&Feiertage[Datum]&Feiertage[[BW]:[TH]],"",0,1), SUM(IF(_xlpm.ary="1"&Table6[[#This Row],[Tag]]&"x",1,0)))+IF(WEEKDAY(Table6[[#This Row],[Tag]],2)>=6,1,0))} -> 2 | AM15: =IF(Table6[[#This Row],[FT/WE]]=2,"",Table6[[#This Row],[Name]]&Table6[[#This Row],[Tag]]) | AP15: =IF(AO15&"1"<>"1",RIGHT(AO15,4),"") | AQ15: =IF(AO15&"1"="1","",LEFT(AO15,LEN(AO15)-5))
E16: =_xlfn.LET(_xlpm.out,'Ganzes Unternehmen'!B19,IF(OR(_xlpm.out=0,_xlpm.out="Allgemein"),"",_xlpm.out)) | I16: Student 1 | J16: Baden-Württemberg | K16: ja | L16: nein | M16: nein | N16: Ping-Pong-Roboter | O16: FuE-Tätigkeiten am Vorhaben | P16: 11 | Q16: 2026 | R16: 1 | S16: 650 | T16: 500 | U16: 8 | V16: {=_xlfn.LET( _xlpm.BL,_xlfn.XLOOKUP(MitarbeiterFTE[[#This Row],[Bundesland]],Bundesländer[Deutsch],Bundesländer[Abkürzung]), _xlpm.ary,_xlfn.XLOOKUP(_xlpm.BL,Feiertage[[#Headers],[BW]:[TH]],Feiertage[IsWorkday]&Feiertage[MJJJJ]&Feiertage[[BW]:[TH]],"",0,1), _xlpm.out,IFERROR(SUM(IF(_xlpm.ary="1"&MitarbeiterFTE[[#This Row],[Monat]]&MitarbeiterFTE[[#This Row],[Jahr]]&"x",1,0)),"BL ausw."), IF(MitarbeiterFTE[[#This Row],[Name]]&"1"="1","input missing",_xlpm.out) )} -> 0 | W16: =_xlfn.LET( _xlpm.abw,COUNTIFS(Table6[Tag],">="&DATE(MitarbeiterFTE[[#This Row],[Jahr]],MitarbeiterFTE[[#This Row],[Monat]],1),Table6[Tag],"<="&EOMONTH(DATE(MitarbeiterFTE[[#This Row],[Jahr]],MitarbeiterFTE[[#This Row],[Monat]],1),0),Table6[Name],MitarbeiterFTE[[#This Row],[Name]],Table6[FT/WE],0), IF(MitarbeiterFTE[[#This Row],[Name]]&"1"="1","input missing",_xlpm.abw)) -> 0 | X16: =_xlfn.LET( _xlpm.abwStatistik,(28.9+11.2)/12, _xlpm.isEingetragen,COUNTIFS(Table6[Tag],">="&DATE(MitarbeiterFTE[[#This Row],[Jahr]],1,1),Table6[Tag],"<="&DATE(MitarbeiterFTE[[#This Row],[Jahr]],12,31),Table6[Name],MitarbeiterFTE[[#This Row],[Name]]), _xlpm.isExclAbw,$W$12="ja", _xlpm.abwesend,IF(_xlpm.isExclAbw,0, IF(_xlpm.isEingetragen, MitarbeiterFTE[[#This Row],[Sonst. Abwesend]], IF(MitarbeiterFTE[[#This Row],[Sonst. Abwesend]]>0,MitarbeiterFTE[[#This Row],[Sonst. Abwesend]], _xlpm.abwStatistik))), _xlpm.isExclFT,$V$12="ja", _xlpm.ExclFT,_xlpm.abwesend, _xlpm.ExclFTAbw,0, _xlpm.inklAlles,_xlpm.abwesend+MitarbeiterFTE[[#This Row],[Feiertage]], IFERROR(IF(AND(_xlpm.isExclAbw,_xlpm.isExclFT), _xlpm.ExclFTAbw, IF(_xlpm.isExclFT,_xlpm.ExclFT, _xlpm.inklAlles)),"input missing") ) -> 3.3416667 | Y16: =_xlfn.LET( _xlpm.Monat_Start,DATE(MitarbeiterFTE[[#This Row],[Jahr]],MitarbeiterFTE[[#This Row],[Monat]],1), _xlpm.AT_Monat,NETWORKDAYS(_xlpm.Monat_Start,EOMONTH(_xlpm.Monat_Start,0)), IFERROR((MitarbeiterFTE[[#This Row],[Std. / Wo.]]/5)*MitarbeiterFTE[[#This Row],[%-Vorhaben]]*(_xlpm.AT_Monat-MitarbeiterFTE[[#This Row],[Sum Abwesend]]),"input missing")) -> 28.253333 | Z16: =_xlfn.LET( _xlpm.AT_Jahr, NETWORKDAYS(DATE(MitarbeiterFTE[[#This Row],[Jahr]],1,1),DATE(MitarbeiterFTE[[#This Row],[Jahr]],12,31)), _xlpm.Monat_Start,DATE(MitarbeiterFTE[[#This Row],[Jahr]],MitarbeiterFTE[[#This Row],[Monat]],1), _xlpm.AT_Monat,NETWORKDAYS(_xlpm.Monat_Start,EOMONTH(_xlpm.Monat_Start,0))-MitarbeiterFTE[[#This Row],[Sum Abwesend]], _xlpm.Kalk_Gehalt_Jahr,MitarbeiterFTE[[#This Row],[Steuerbrutto + AG-Anteile]]/_xlpm.AT_Monat*_xlpm.AT_Jahr, _xlpm.Kalk_Stundensatz,_xlpm.Kalk_Gehalt_Jahr/(MitarbeiterFTE[[#This Row],[Std. / Wo.]]/5*_xlpm.AT_Jahr), _xlpm.Kalk_Kosten,_xlpm.Kalk_Stundensatz*MitarbeiterFTE[[#This Row],[Stunden]], IFERROR(_xlpm.Kalk_Kosten,"input missing") ) -> 650 | AA16: =_xlfn.LET(_xlpm.var,MitarbeiterFTE[[#This Row],[Name]]&"|"&MitarbeiterFTE[[#This Row],[Vorhaben]]&"|"&MitarbeiterFTE[[#This Row],[Monat]]&"|"&MitarbeiterFTE[[#This Row],[Jahr]], IF(_xlpm.var="|||","input missing",_xlpm.var)) -> Student 1|Ping-Pong-Roboter|11|2026 | AB16: =_xlfn.LET( _xlpm.start,DATE(MitarbeiterFTE[[#This Row],[Jahr]],MitarbeiterFTE[[#This Row],[Monat]],1), _xlpm.end,EOMONTH(_xlpm.start,0), NETWORKDAYS(_xlpm.start,_xlpm.end)) -> 21 | AC16: =MitarbeiterFTE[[#This Row],[BWD]]-MitarbeiterFTE[[#This Row],[Sum Abwesend]] -> 17.658333 | AD16: =SUMIFS(MitarbeiterFTE[BWD],MitarbeiterFTE[Jahr],MitarbeiterFTE[[#This Row],[Jahr]],MitarbeiterFTE[Name],MitarbeiterFTE[[#This Row],[Name]]) -> 88 | AE16: =SUMIFS(MitarbeiterFTE[NWD],MitarbeiterFTE[Jahr],MitarbeiterFTE[[#This Row],[Jahr]],MitarbeiterFTE[Name],MitarbeiterFTE[[#This Row],[Name]]) -> 73.633333 | AF16: =IF(MitarbeiterFTE[[#This Row],[HS]]="ja",2,IF(MitarbeiterFTE[[#This Row],[Tech]]="ja",1,IF(MitarbeiterFTE[[#This Row],[Sonst]]="ja",0,"input missing"))) -> 2 | AL16: {=IF(Table6[[#This Row],[Name]]&"1"="1",2,_xlfn.LET( _xlpm.Bundesland,_xlfn.XLOOKUP(Table6[[#This Row],[Name]]&YEAR(Table6[[#This Row],[Tag]])&MONTH(Table6[[#This Row],[Tag]]),MitarbeiterFTE[Name]&MitarbeiterFTE[Jahr]&MitarbeiterFTE[Monat],MitarbeiterFTE[Bundesland],"Schleswig-Holstein",0,1), _xlpm.BundeslandAry,_xlfn.XLOOKUP(_xlpm.Bundesland,Bundesländer[Deutsch],Bundesländer[Abkürzung]), _xlpm.ary,_xlfn.XLOOKUP(_xlpm.BundeslandAry,Feiertage[[#Headers],[BW]:[TH]],Feiertage[IsWorkday]&Feiertage[Datum]&Feiertage[[BW]:[TH]],"",0,1), SUM(IF(_xlpm.ary="1"&Table6[[#This Row],[Tag]]&"x",1,0)))+IF(WEEKDAY(Table6[[#This Row],[Tag]],2)>=6,1,0))} -> 2 | AM16: =IF(Table6[[#This Row],[FT/WE]]=2,"",Table6[[#This Row],[Name]]&Table6[[#This Row],[Tag]]) | AP16: =IF(AO16&"1"<>"1",RIGHT(AO16,4),"") | AQ16: =IF(AO16&"1"="1","",LEFT(AO16,LEN(AO16)-5))
E17: =_xlfn.LET(_xlpm.out,'Ganzes Unternehmen'!B20,IF(OR(_xlpm.out=0,_xlpm.out="Allgemein"),"",_xlpm.out)) | I17: Student 1 | J17: Baden-Württemberg | K17: ja | L17: nein | M17: nein | N17: Ping-Pong-Roboter | O17: FuE-Tätigkeiten am Vorhaben | P17: 12 | Q17: 2026 | R17: 1 | S17: 650 | T17: 500 | U17: 8 | V17: {=_xlfn.LET( _xlpm.BL,_xlfn.XLOOKUP(MitarbeiterFTE[[#This Row],[Bundesland]],Bundesländer[Deutsch],Bundesländer[Abkürzung]), _xlpm.ary,_xlfn.XLOOKUP(_xlpm.BL,Feiertage[[#Headers],[BW]:[TH]],Feiertage[IsWorkday]&Feiertage[MJJJJ]&Feiertage[[BW]:[TH]],"",0,1), _xlpm.out,IFERROR(SUM(IF(_xlpm.ary="1"&MitarbeiterFTE[[#This Row],[Monat]]&MitarbeiterFTE[[#This Row],[Jahr]]&"x",1,0)),"BL ausw."), IF(MitarbeiterFTE[[#This Row],[Name]]&"1"="1","input missing",_xlpm.out) )} -> 1 | W17: =_xlfn.LET( _xlpm.abw,COUNTIFS(Table6[Tag],">="&DATE(MitarbeiterFTE[[#This Row],[Jahr]],MitarbeiterFTE[[#This Row],[Monat]],1),Table6[Tag],"<="&EOMONTH(DATE(MitarbeiterFTE[[#This Row],[Jahr]],MitarbeiterFTE[[#This Row],[Monat]],1),0),Table6[Name],MitarbeiterFTE[[#This Row],[Name]],Table6[FT/WE],0), IF(MitarbeiterFTE[[#This Row],[Name]]&"1"="1","input missing",_xlpm.abw)) -> 0 | X17: =_xlfn.LET( _xlpm.abwStatistik,(28.9+11.2)/12, _xlpm.isEingetragen,COUNTIFS(Table6[Tag],">="&DATE(MitarbeiterFTE[[#This Row],[Jahr]],1,1),Table6[Tag],"<="&DATE(MitarbeiterFTE[[#This Row],[Jahr]],12,31),Table6[Name],MitarbeiterFTE[[#This Row],[Name]]), _xlpm.isExclAbw,$W$12="ja", _xlpm.abwesend,IF(_xlpm.isExclAbw,0, IF(_xlpm.isEingetragen, MitarbeiterFTE[[#This Row],[Sonst. Abwesend]], IF(MitarbeiterFTE[[#This Row],[Sonst. Abwesend]]>0,MitarbeiterFTE[[#This Row],[Sonst. Abwesend]], _xlpm.abwStatistik))), _xlpm.isExclFT,$V$12="ja", _xlpm.ExclFT,_xlpm.abwesend, _xlpm.ExclFTAbw,0, _xlpm.inklAlles,_xlpm.abwesend+MitarbeiterFTE[[#This Row],[Feiertage]], IFERROR(IF(AND(_xlpm.isExclAbw,_xlpm.isExclFT), _xlpm.ExclFTAbw, IF(_xlpm.isExclFT,_xlpm.ExclFT, _xlpm.inklAlles)),"input missing") ) -> 4.3416667 | Y17: =_xlfn.LET( _xlpm.Monat_Start,DATE(MitarbeiterFTE[[#This Row],[Jahr]],MitarbeiterFTE[[#This Row],[Monat]],1), _xlpm.AT_Monat,NETWORKDAYS(_xlpm.Monat_Start,EOMONTH(_xlpm.Monat_Start,0)), IFERROR((MitarbeiterFTE[[#This Row],[Std. / Wo.]]/5)*MitarbeiterFTE[[#This Row],[%-Vorhaben]]*(_xlpm.AT_Monat-MitarbeiterFTE[[#This Row],[Sum Abwesend]]),"input missing")) -> 29.853333 | Z17: =_xlfn.LET( _xlpm.AT_Jahr, NETWORKDAYS(DATE(MitarbeiterFTE[[#This Row],[Jahr]],1,1),DATE(MitarbeiterFTE[[#This Row],[Jahr]],12,31)), _xlpm.Monat_Start,DATE(MitarbeiterFTE[[#This Row],[Jahr]],MitarbeiterFTE[[#This Row],[Monat]],1), _xlpm.AT_Monat,NETWORKDAYS(_xlpm.Monat_Start,EOMONTH(_xlpm.Monat_Start,0))-MitarbeiterFTE[[#This Row],[Sum Abwesend]], _xlpm.Kalk_Gehalt_Jahr,MitarbeiterFTE[[#This Row],[Steuerbrutto + AG-Anteile]]/_xlpm.AT_Monat*_xlpm.AT_Jahr, _xlpm.Kalk_Stundensatz,_xlpm.Kalk_Gehalt_Jahr/(MitarbeiterFTE[[#This Row],[Std. / Wo.]]/5*_xlpm.AT_Jahr), _xlpm.Kalk_Kosten,_xlpm.Kalk_Stundensatz*MitarbeiterFTE[[#This Row],[Stunden]], IFERROR(_xlpm.Kalk_Kosten,"input missing") ) -> 650 | AA17: =_xlfn.LET(_xlpm.var,MitarbeiterFTE[[#This Row],[Name]]&"|"&MitarbeiterFTE[[#This Row],[Vorhaben]]&"|"&MitarbeiterFTE[[#This Row],[Monat]]&"|"&MitarbeiterFTE[[#This Row],[Jahr]], IF(_xlpm.var="|||","input missing",_xlpm.var)) -> Student 1|Ping-Pong-Roboter|12|2026 | AB17: =_xlfn.LET( _xlpm.start,DATE(MitarbeiterFTE[[#This Row],[Jahr]],MitarbeiterFTE[[#This Row],[Monat]],1), _xlpm.end,EOMONTH(_xlpm.start,0), NETWORKDAYS(_xlpm.start,_xlpm.end)) -> 23 | AC17: =MitarbeiterFTE[[#This Row],[BWD]]-MitarbeiterFTE[[#This Row],[Sum Abwesend]] -> 18.658333 | AD17: =SUMIFS(MitarbeiterFTE[BWD],MitarbeiterFTE[Jahr],MitarbeiterFTE[[#This Row],[Jahr]],MitarbeiterFTE[Name],MitarbeiterFTE[[#This Row],[Name]]) -> 88 | AE17: =SUMIFS(MitarbeiterFTE[NWD],MitarbeiterFTE[Jahr],MitarbeiterFTE[[#This Row],[Jahr]],MitarbeiterFTE[Name],MitarbeiterFTE[[#This Row],[Name]]) -> 73.633333 | AF17: =IF(MitarbeiterFTE[[#This Row],[HS]]="ja",2,IF(MitarbeiterFTE[[#This Row],[Tech]]="ja",1,IF(MitarbeiterFTE[[#This Row],[Sonst]]="ja",0,"input missing"))) -> 2 | AL17: {=IF(Table6[[#This Row],[Name]]&"1"="1",2,_xlfn.LET( _xlpm.Bundesland,_xlfn.XLOOKUP(Table6[[#This Row],[Name]]&YEAR(Table6[[#This Row],[Tag]])&MONTH(Table6[[#This Row],[Tag]]),MitarbeiterFTE[Name]&MitarbeiterFTE[Jahr]&MitarbeiterFTE[Monat],MitarbeiterFTE[Bundesland],"Schleswig-Holstein",0,1), _xlpm.BundeslandAry,_xlfn.XLOOKUP(_xlpm.Bundesland,Bundesländer[Deutsch],Bundesländer[Abkürzung]), _xlpm.ary,_xlfn.XLOOKUP(_xlpm.BundeslandAry,Feiertage[[#Headers],[BW]:[TH]],Feiertage[IsWorkday]&Feiertage[Datum]&Feiertage[[BW]:[TH]],"",0,1), SUM(IF(_xlpm.ary="1"&Table6[[#This Row],[Tag]]&"x",1,0)))+IF(WEEKDAY(Table6[[#This Row],[Tag]],2)>=6,1,0))} -> 2 | AM17: =IF(Table6[[#This Row],[FT/WE]]=2,"",Table6[[#This Row],[Name]]&Table6[[#This Row],[Tag]]) | AP17: =IF(AO17&"1"<>"1",RIGHT(AO17,4),"") | AQ17: =IF(AO17&"1"="1","",LEFT(AO17,LEN(AO17)-5))
E18: =_xlfn.LET(_xlpm.out,'Ganzes Unternehmen'!B21,IF(OR(_xlpm.out=0,_xlpm.out="Allgemein"),"",_xlpm.out)) | I18: Student 1 | J18: Baden-Württemberg | K18: ja | L18: nein | M18: nein | N18: Ping-Pong-Roboter | O18: FuE-Tätigkeiten am Vorhaben | P18: 1 | Q18: 2027 | R18: 1 | S18: 650 | T18: 500 | U18: 8 | V18: {=_xlfn.LET( _xlpm.BL,_xlfn.XLOOKUP(MitarbeiterFTE[[#This Row],[Bundesland]],Bundesländer[Deutsch],Bundesländer[Abkürzung]), _xlpm.ary,_xlfn.XLOOKUP(_xlpm.BL,Feiertage[[#Headers],[BW]:[TH]],Feiertage[IsWorkday]&Feiertage[MJJJJ]&Feiertage[[BW]:[TH]],"",0,1), _xlpm.out,IFERROR(SUM(IF(_xlpm.ary="1"&MitarbeiterFTE[[#This Row],[Monat]]&MitarbeiterFTE[[#This Row],[Jahr]]&"x",1,0)),"BL ausw."), IF(MitarbeiterFTE[[#This Row],[Name]]&"1"="1","input missing",_xlpm.out) )} -> 2 | W18: =_xlfn.LET( _xlpm.abw,COUNTIFS(Table6[Tag],">="&DATE(MitarbeiterFTE[[#This Row],[Jahr]],MitarbeiterFTE[[#This Row],[Monat]],1),Table6[Tag],"<="&EOMONTH(DATE(MitarbeiterFTE[[#This Row],[Jahr]],MitarbeiterFTE[[#This Row],[Monat]],1),0),Table6[Name],MitarbeiterFTE[[#This Row],[Name]],Table6[FT/WE],0), IF(MitarbeiterFTE[[#This Row],[Name]]&"1"="1","input missing",_xlpm.abw)) -> 0 | X18: =_xlfn.LET( _xlpm.abwStatistik,(28.9+11.2)/12, _xlpm.isEingetragen,COUNTIFS(Table6[Tag],">="&DATE(MitarbeiterFTE[[#This Row],[Jahr]],1,1),Table6[Tag],"<="&DATE(MitarbeiterFTE[[#This Row],[Jahr]],12,31),Table6[Name],MitarbeiterFTE[[#This Row],[Name]]), _xlpm.isExclAbw,$W$12="ja", _xlpm.abwesend,IF(_xlpm.isExclAbw,0, IF(_xlpm.isEingetragen, MitarbeiterFTE[[#This Row],[Sonst. Abwesend]], IF(MitarbeiterFTE[[#This Row],[Sonst. Abwesend]]>0,MitarbeiterFTE[[#This Row],[Sonst. Abwesend]], _xlpm.abwStatistik))), _xlpm.isExclFT,$V$12="ja", _xlpm.ExclFT,_xlpm.abwesend, _xlpm.ExclFTAbw,0, _xlpm.inklAlles,_xlpm.abwesend+MitarbeiterFTE[[#This Row],[Feiertage]], IFERROR(IF(AND(_xlpm.isExclAbw,_xlpm.isExclFT), _xlpm.ExclFTAbw, IF(_xlpm.isExclFT,_xlpm.ExclFT, _xlpm.inklAlles)),"input missing") ) -> 5.3416667 | Y18: =_xlfn.LET( _xlpm.Monat_Start,DATE(MitarbeiterFTE[[#This Row],[Jahr]],MitarbeiterFTE[[#This Row],[Monat]],1), _xlpm.AT_Monat,NETWORKDAYS(_xlpm.Monat_Start,EOMONTH(_xlpm.Monat_Start,0)), IFERROR((MitarbeiterFTE[[#This Row],[Std. / Wo.]]/5)*MitarbeiterFTE[[#This Row],[%-Vorhaben]]*(_xlpm.AT_Monat-MitarbeiterFTE[[#This Row],[Sum Abwesend]]),"input missing")) -> 25.053333 | Z18: =_xlfn.LET( _xlpm.AT_Jahr, NETWORKDAYS(DATE(MitarbeiterFTE[[#This Row],[Jahr]],1,1),DATE(MitarbeiterFTE[[#This Row],[Jahr]],12,31)), _xlpm.Monat_Start,DATE(MitarbeiterFTE[[#This Row],[Jahr]],MitarbeiterFTE[[#This Row],[Monat]],1), _xlpm.AT_Monat,NETWORKDAYS(_xlpm.Monat_Start,EOMONTH(_xlpm.Monat_Start,0))-MitarbeiterFTE[[#This Row],[Sum Abwesend]], _xlpm.Kalk_Gehalt_Jahr,MitarbeiterFTE[[#This Row],[Steuerbrutto + AG-Anteile]]/_xlpm.AT_Monat*_xlpm.AT_Jahr, _xlpm.Kalk_Stundensatz,_xlpm.Kalk_Gehalt_Jahr/(MitarbeiterFTE[[#This Row],[Std. / Wo.]]/5*_xlpm.AT_Jahr), _xlpm.Kalk_Kosten,_xlpm.Kalk_Stundensatz*MitarbeiterFTE[[#This Row],[Stunden]], IFERROR(_xlpm.Kalk_Kosten,"input missing") ) -> 650 | AA18: =_xlfn.LET(_xlpm.var,MitarbeiterFTE[[#This Row],[Name]]&"|"&MitarbeiterFTE[[#This Row],[Vorhaben]]&"|"&MitarbeiterFTE[[#This Row],[Monat]]&"|"&MitarbeiterFTE[[#This Row],[Jahr]], IF(_xlpm.var="|||","input missing",_xlpm.var)) -> Student 1|Ping-Pong-Roboter|1|2027 | AB18: =_xlfn.LET( _xlpm.start,DATE(MitarbeiterFTE[[#This Row],[Jahr]],MitarbeiterFTE[[#This Row],[Monat]],1), _xlpm.end,EOMONTH(_xlpm.start,0), NETWORKDAYS(_xlpm.start,_xlpm.end)) -> 21 | AC18: =MitarbeiterFTE[[#This Row],[BWD]]-MitarbeiterFTE[[#This Row],[Sum Abwesend]] -> 15.658333 | AD18: =SUMIFS(MitarbeiterFTE[BWD],MitarbeiterFTE[Jahr],MitarbeiterFTE[[#This Row],[Jahr]],MitarbeiterFTE[Name],MitarbeiterFTE[[#This Row],[Name]]) -> 261 | AE18: =SUMIFS(MitarbeiterFTE[NWD],MitarbeiterFTE[Jahr],MitarbeiterFTE[[#This Row],[Jahr]],MitarbeiterFTE[Name],MitarbeiterFTE[[#This Row],[Name]]) -> 212.9 | AF18: =IF(MitarbeiterFTE[[#This Row],[HS]]="ja",2,IF(MitarbeiterFTE[[#This Row],[Tech]]="ja",1,IF(MitarbeiterFTE[[#This Row],[Sonst]]="ja",0,"input missing"))) -> 2 | AL18: {=IF(Table6[[#This Row],[Name]]&"1"="1",2,_xlfn.LET( _xlpm.Bundesland,_xlfn.XLOOKUP(Table6[[#This Row],[Name]]&YEAR(Table6[[#This Row],[Tag]])&MONTH(Table6[[#This Row],[Tag]]),MitarbeiterFTE[Name]&MitarbeiterFTE[Jahr]&MitarbeiterFTE[Monat],MitarbeiterFTE[Bundesland],"Schleswig-Holstein",0,1), _xlpm.BundeslandAry,_xlfn.XLOOKUP(_xlpm.Bundesland,Bundesländer[Deutsch],Bundesländer[Abkürzung]), _xlpm.ary,_xlfn.XLOOKUP(_xlpm.BundeslandAry,Feiertage[[#Headers],[BW]:[TH]],Feiertage[IsWorkday]&Feiertage[Datum]&Feiertage[[BW]:[TH]],"",0,1), SUM(IF(_xlpm.ary="1"&Table6[[#This Row],[Tag]]&"x",1,0)))+IF(WEEKDAY(Table6[[#This Row],[Tag]],2)>=6,1,0))} -> 2 | AM18: =IF(Table6[[#This Row],[FT/WE]]=2,"",Table6[[#This Row],[Name]]&Table6[[#This Row],[Tag]]) | AP18: =IF(AO18&"1"<>"1",RIGHT(AO18,4),"") | AQ18: =IF(AO18&"1"="1","",LEFT(AO18,LEN(AO18)-5))
E19: =_xlfn.LET(_xlpm.out,'Ganzes Unternehmen'!B22,IF(OR(_xlpm.out=0,_xlpm.out="Allgemein"),"",_xlpm.out)) | I19: Student 1 | J19: Baden-Württemberg | K19: ja | L19: nein | M19: nein | N19: Ping-Pong-Roboter | O19: FuE-Tätigkeiten am Vorhaben | P19: 2 | Q19: 2027 | R19: 1 | S19: 650 | T19: 500 | U19: 8 | V19: {=_xlfn.LET( _xlpm.BL,_xlfn.XLOOKUP(MitarbeiterFTE[[#This Row],[Bundesland]],Bundesländer[Deutsch],Bundesländer[Abkürzung]), _xlpm.ary,_xlfn.XLOOKUP(_xlpm.BL,Feiertage[[#Headers],[BW]:[TH]],Feiertage[IsWorkday]&Feiertage[MJJJJ]&Feiertage[[BW]:[TH]],"",0,1), _xlpm.out,IFERROR(SUM(IF(_xlpm.ary="1"&MitarbeiterFTE[[#This Row],[Monat]]&MitarbeiterFTE[[#This Row],[Jahr]]&"x",1,0)),"BL ausw."), IF(MitarbeiterFTE[[#This Row],[Name]]&"1"="1","input missing",_xlpm.out) )} -> 0 | W19: =_xlfn.LET( _xlpm.abw,COUNTIFS(Table6[Tag],">="&DATE(MitarbeiterFTE[[#This Row],[Jahr]],MitarbeiterFTE[[#This Row],[Monat]],1),Table6[Tag],"<="&EOMONTH(DATE(MitarbeiterFTE[[#This Row],[Jahr]],MitarbeiterFTE[[#This Row],[Monat]],1),0),Table6[Name],MitarbeiterFTE[[#This Row],[Name]],Table6[FT/WE],0), IF(MitarbeiterFTE[[#This Row],[Name]]&"1"="1","input missing",_xlpm.abw)) -> 0 | X19: =_xlfn.LET( _xlpm.abwStatistik,(28.9+11.2)/12, _xlpm.isEingetragen,COUNTIFS(Table6[Tag],">="&DATE(MitarbeiterFTE[[#This Row],[Jahr]],1,1),Table6[Tag],"<="&DATE(MitarbeiterFTE[[#This Row],[Jahr]],12,31),Table6[Name],MitarbeiterFTE[[#This Row],[Name]]), _xlpm.isExclAbw,$W$12="ja", _xlpm.abwesend,IF(_xlpm.isExclAbw,0, IF(_xlpm.isEingetragen, MitarbeiterFTE[[#This Row],[Sonst. Abwesend]], IF(MitarbeiterFTE[[#This Row],[Sonst. Abwesend]]>0,MitarbeiterFTE[[#This Row],[Sonst. Abwesend]], _xlpm.abwStatistik))), _xlpm.isExclFT,$V$12="ja", _xlpm.ExclFT,_xlpm.abwesend, _xlpm.ExclFTAbw,0, _xlpm.inklAlles,_xlpm.abwesend+MitarbeiterFTE[[#This Row],[Feiertage]], IFERROR(IF(AND(_xlpm.isExclAbw,_xlpm.isExclFT), _xlpm.ExclFTAbw, IF(_xlpm.isExclFT,_xlpm.ExclFT, _xlpm.inklAlles)),"input missing") ) -> 3.3416667 | Y19: =_xlfn.LET( _xlpm.Monat_Start,DATE(MitarbeiterFTE[[#This Row],[Jahr]],MitarbeiterFTE[[#This Row],[Monat]],1), _xlpm.AT_Monat,NETWORKDAYS(_xlpm.Monat_Start,EOMONTH(_xlpm.Monat_Start,0)), IFERROR((MitarbeiterFTE[[#This Row],[Std. / Wo.]]/5)*MitarbeiterFTE[[#This Row],[%-Vorhaben]]*(_xlpm.AT_Monat-MitarbeiterFTE[[#This Row],[Sum Abwesend]]),"input missing")) -> 26.653333 | Z19: =_xlfn.LET( _xlpm.AT_Jahr, NETWORKDAYS(DATE(MitarbeiterFTE[[#This Row],[Jahr]],1,1),DATE(MitarbeiterFTE[[#This Row],[Jahr]],12,31)), _xlpm.Monat_Start,DATE(MitarbeiterFTE[[#This Row],[Jahr]],MitarbeiterFTE[[#This Row],[Monat]],1), _xlpm.AT_Monat,NETWORKDAYS(_xlpm.Monat_Start,EOMONTH(_xlpm.Monat_Start,0))-MitarbeiterFTE[[#This Row],[Sum Abwesend]], _xlpm.Kalk_Gehalt_Jahr,MitarbeiterFTE[[#This Row],[Steuerbrutto + AG-Anteile]]/_xlpm.AT_Monat*_xlpm.AT_Jahr, _xlpm.Kalk_Stundensatz,_xlpm.Kalk_Gehalt_Jahr/(MitarbeiterFTE[[#This Row],[Std. / Wo.]]/5*_xlpm.AT_Jahr), _xlpm.Kalk_Kosten,_xlpm.Kalk_Stundensatz*MitarbeiterFTE[[#This Row],[Stunden]], IFERROR(_xlpm.Kalk_Kosten,"input missing") ) -> 650 | AA19: =_xlfn.LET(_xlpm.var,MitarbeiterFTE[[#This Row],[Name]]&"|"&MitarbeiterFTE[[#This Row],[Vorhaben]]&"|"&MitarbeiterFTE[[#This Row],[Monat]]&"|"&MitarbeiterFTE[[#This Row],[Jahr]], IF(_xlpm.var="|||","input missing",_xlpm.var)) -> Student 1|Ping-Pong-Roboter|2|2027 | AB19: =_xlfn.LET( _xlpm.start,DATE(MitarbeiterFTE[[#This Row],[Jahr]],MitarbeiterFTE[[#This Row],[Monat]],1), _xlpm.end,EOMONTH(_xlpm.start,0), NETWORKDAYS(_xlpm.start,_xlpm.end)) -> 20 | AC19: =MitarbeiterFTE[[#This Row],[BWD]]-MitarbeiterFTE[[#This Row],[Sum Abwesend]] -> 16.658333 | AD19: =SUMIFS(MitarbeiterFTE[BWD],MitarbeiterFTE[Jahr],MitarbeiterFTE[[#This Row],[Jahr]],MitarbeiterFTE[Name],MitarbeiterFTE[[#This Row],[Name]]) -> 261 | AE19: =SUMIFS(MitarbeiterFTE[NWD],MitarbeiterFTE[Jahr],MitarbeiterFTE[[#This Row],[Jahr]],MitarbeiterFTE[Name],MitarbeiterFTE[[#This Row],[Name]]) -> 212.9 | AF19: =IF(MitarbeiterFTE[[#This Row],[HS]]="ja",2,IF(MitarbeiterFTE[[#This Row],[Tech]]="ja",1,IF(MitarbeiterFTE[[#This Row],[Sonst]]="ja",0,"input missing"))) -> 2 | AL19: {=IF(Table6[[#This Row],[Name]]&"1"="1",2,_xlfn.LET( _xlpm.Bundesland,_xlfn.XLOOKUP(Table6[[#This Row],[Name]]&YEAR(Table6[[#This Row],[Tag]])&MONTH(Table6[[#This Row],[Tag]]),MitarbeiterFTE[Name]&MitarbeiterFTE[Jahr]&MitarbeiterFTE[Monat],MitarbeiterFTE[Bundesland],"Schleswig-Holstein",0,1), _xlpm.BundeslandAry,_xlfn.XLOOKUP(_xlpm.Bundesland,Bundesländer[Deutsch],Bundesländer[Abkürzung]), _xlpm.ary,_xlfn.XLOOKUP(_xlpm.BundeslandAry,Feiertage[[#Headers],[BW]:[TH]],Feiertage[IsWorkday]&Feiertage[Datum]&Feiertage[[BW]:[TH]],"",0,1), SUM(IF(_xlpm.ary="1"&Table6[[#This Row],[Tag]]&"x",1,0)))+IF(WEEKDAY(Table6[[#This Row],[Tag]],2)>=6,1,0))} -> 2 | AM19: =IF(Table6[[#This Row],[FT/WE]]=2,"",Table6[[#This Row],[Name]]&Table6[[#This Row],[Tag]]) | AP19: =IF(AO19&"1"<>"1",RIGHT(AO19,4),"") | AQ19: =IF(AO19&"1"="1","",LEFT(AO19,LEN(AO19)-5))
I20: Student 1 | J20: Baden-Württemberg | K20: ja | L20: nein | M20: nein | N20: Ping-Pong-Roboter | O20: FuE-Tätigkeiten am Vorhaben | P20: 3 | Q20: 2027 | R20: 1 | S20: 650 | T20: 500 | U20: 8 | V20: {=_xlfn.LET( _xlpm.BL,_xlfn.XLOOKUP(MitarbeiterFTE[[#This Row],[Bundesland]],Bundesländer[Deutsch],Bundesländer[Abkürzung]), _xlpm.ary,_xlfn.XLOOKUP(_xlpm.BL,Feiertage[[#Headers],[BW]:[TH]],Feiertage[IsWorkday]&Feiertage[MJJJJ]&Feiertage[[BW]:[TH]],"",0,1), _xlpm.out,IFERROR(SUM(IF(_xlpm.ary="1"&MitarbeiterFTE[[#This Row],[Monat]]&MitarbeiterFTE[[#This Row],[Jahr]]&"x",1,0)),"BL ausw."), IF(MitarbeiterFTE[[#This Row],[Name]]&"1"="1","input missing",_xlpm.out) )} -> 2 | W20: =_xlfn.LET( _xlpm.abw,COUNTIFS(Table6[Tag],">="&DATE(MitarbeiterFTE[[#This Row],[Jahr]],MitarbeiterFTE[[#This Row],[Monat]],1),Table6[Tag],"<="&EOMONTH(DATE(MitarbeiterFTE[[#This Row],[Jahr]],MitarbeiterFTE[[#This Row],[Monat]],1),0),Table6[Name],MitarbeiterFTE[[#This Row],[Name]],Table6[FT/WE],0), IF(MitarbeiterFTE[[#This Row],[Name]]&"1"="1","input missing",_xlpm.abw)) -> 0 | X20: =_xlfn.LET( _xlpm.abwStatistik,(28.9+11.2)/12, _xlpm.isEingetragen,COUNTIFS(Table6[Tag],">="&DATE(MitarbeiterFTE[[#This Row],[Jahr]],1,1),Table6[Tag],"<="&DATE(MitarbeiterFTE[[#This Row],[Jahr]],12,31),Table6[Name],MitarbeiterFTE[[#This Row],[Name]]), _xlpm.isExclAbw,$W$12="ja", _xlpm.abwesend,IF(_xlpm.isExclAbw,0, IF(_xlpm.isEingetragen, MitarbeiterFTE[[#This Row],[Sonst. Abwesend]], IF(MitarbeiterFTE[[#This Row],[Sonst. Abwesend]]>0,MitarbeiterFTE[[#This Row],[Sonst. Abwesend]], _xlpm.abwStatistik))), _xlpm.isExclFT,$V$12="ja", _xlpm.ExclFT,_xlpm.abwesend, _xlpm.ExclFTAbw,0, _xlpm.inklAlles,_xlpm.abwesend+MitarbeiterFTE[[#This Row],[Feiertage]], IFERROR(IF(AND(_xlpm.isExclAbw,_xlpm.isExclFT), _xlpm.ExclFTAbw, IF(_xlpm.isExclFT,_xlpm.ExclFT, _xlpm.inklAlles)),"input missing") ) -> 5.3416667 | Y20: =_xlfn.LET( _xlpm.Monat_Start,DATE(MitarbeiterFTE[[#This Row],[Jahr]],MitarbeiterFTE[[#This Row],[Monat]],1), _xlpm.AT_Monat,NETWORKDAYS(_xlpm.Monat_Start,EOMONTH(_xlpm.Monat_Start,0)), IFERROR((MitarbeiterFTE[[#This Row],[Std. / Wo.]]/5)*MitarbeiterFTE[[#This Row],[%-Vorhaben]]*(_xlpm.AT_Monat-MitarbeiterFTE[[#This Row],[Sum Abwesend]]),"input missing")) -> 28.253333 | Z20: =_xlfn.LET( _xlpm.AT_Jahr, NETWORKDAYS(DATE(MitarbeiterFTE[[#This Row],[Jahr]],1,1),DATE(MitarbeiterFTE[[#This Row],[Jahr]],12,31)), _xlpm.Monat_Start,DATE(MitarbeiterFTE[[#This Row],[Jahr]],MitarbeiterFTE[[#This Row],[Monat]],1), _xlpm.AT_Monat,NETWORKDAYS(_xlpm.Monat_Start,EOMONTH(_xlpm.Monat_Start,0))-MitarbeiterFTE[[#This Row],[Sum Abwesend]], _xlpm.Kalk_Gehalt_Jahr,MitarbeiterFTE[[#This Row],[Steuerbrutto + AG-Anteile]]/_xlpm.AT_Monat*_xlpm.AT_Jahr, _xlpm.Kalk_Stundensatz,_xlpm.Kalk_Gehalt_Jahr/(MitarbeiterFTE[[#This Row],[Std. / Wo.]]/5*_xlpm.AT_Jahr), _xlpm.Kalk_Kosten,_xlpm.Kalk_Stundensatz*MitarbeiterFTE[[#This Row],[Stunden]], IFERROR(_xlpm.Kalk_Kosten,"input missing") ) -> 650 | AA20: =_xlfn.LET(_xlpm.var,MitarbeiterFTE[[#This Row],[Name]]&"|"&MitarbeiterFTE[[#This Row],[Vorhaben]]&"|"&MitarbeiterFTE[[#This Row],[Monat]]&"|"&MitarbeiterFTE[[#This Row],[Jahr]], IF(_xlpm.var="|||","input missing",_xlpm.var)) -> Student 1|Ping-Pong-Roboter|3|2027 | AB20: =_xlfn.LET( _xlpm.start,DATE(MitarbeiterFTE[[#This Row],[Jahr]],MitarbeiterFTE[[#This Row],[Monat]],1), _xlpm.end,EOMONTH(_xlpm.start,0), NETWORKDAYS(_xlpm.start,_xlpm.end)) -> 23 | AC20: =MitarbeiterFTE[[#This Row],[BWD]]-MitarbeiterFTE[[#This Row],[Sum Abwesend]] -> 17.658333 | AD20: =SUMIFS(MitarbeiterFTE[BWD],MitarbeiterFTE[Jahr],MitarbeiterFTE[[#This Row],[Jahr]],MitarbeiterFTE[Name],MitarbeiterFTE[[#This Row],[Name]]) -> 261 | AE20: =SUMIFS(MitarbeiterFTE[NWD],MitarbeiterFTE[Jahr],MitarbeiterFTE[[#This Row],[Jahr]],MitarbeiterFTE[Name],MitarbeiterFTE[[#This Row],[Name]]) -> 212.9 | AF20: =IF(MitarbeiterFTE[[#This Row],[HS]]="ja",2,IF(MitarbeiterFTE[[#This Row],[Tech]]="ja",1,IF(MitarbeiterFTE[[#This Row],[Sonst]]="ja",0,"input missing"))) -> 2 | AL20: {=IF(Table6[[#This Row],[Name]]&"1"="1",2,_xlfn.LET( _xlpm.Bundesland,_xlfn.XLOOKUP(Table6[[#This Row],[Name]]&YEAR(Table6[[#This Row],[Tag]])&MONTH(Table6[[#This Row],[Tag]]),MitarbeiterFTE[Name]&MitarbeiterFTE[Jahr]&MitarbeiterFTE[Monat],MitarbeiterFTE[Bundesland],"Schleswig-Holstein",0,1), _xlpm.BundeslandAry,_xlfn.XLOOKUP(_xlpm.Bundesland,Bundesländer[Deutsch],Bundesländer[Abkürzung]), _xlpm.ary,_xlfn.XLOOKUP(_xlpm.BundeslandAry,Feiertage[[#Headers],[BW]:[TH]],Feiertage[IsWorkday]&Feiertage[Datum]&Feiertage[[BW]:[TH]],"",0,1), SUM(IF(_xlpm.ary="1"&Table6[[#This Row],[Tag]]&"x",1,0)))+IF(WEEKDAY(Table6[[#This Row],[Tag]],2)>=6,1,0))} -> 2 | AM20: =IF(Table6[[#This Row],[FT/WE]]=2,"",Table6[[#This Row],[Name]]&Table6[[#This Row],[Tag]]) | AP20: =IF(AO20&"1"<>"1",RIGHT(AO20,4),"") | AQ20: =IF(AO20&"1"="1","",LEFT(AO20,LEN(AO20)-5))
